Workbook

Sheet How to use
A1: Gliped outreach tracker
A3: Tabs
A4: Leads | B4: Every lead with trigger, LinkedIn activity pattern, score and ready-to-send messages. One row per person. Add new batches at the bottom with the next ID (G061, G062, ...).
A5: Tracker | B5: Your working sheet. One row per lead ID. Fill the yellow cells as you go. Names, company, region and tier pull from Leads automatically by ID.
A6: Dashboard | B6: Counts and conversion rates by stage, region and activity pattern. Updates itself from Tracker.
A7: Sequence | B7: The shared outreach cadence, follow-up messages and send times.
A8: Lists | B8: Values behind the drop-downs. Edit here to change the options.
A10: How to fill the Tracker
A11: Status | B11: Pick from the drop-down. Move it forward each time something happens.
A12: Date columns | B12: Type dates as YYYY-MM-DD (for example 2026-09-29). Follow-up due dates calculate themselves.
A13: FU1 due | B13: First DM sent + 4 days. Turns red when overdue and FU1 sent is empty.
A14: FU2 due | B14: FU1 sent + 6 days. Turns red when overdue and FU2 sent is empty.
A15: Email | B15: Paste the verified work email in Leads (Email address). Tracker shows it and counts Email sent + 5 days for the email follow-up. Send LinkedIn first; email is the second channel for leads who don't accept or reply.
A16: Days since last touch | B16: Days since the latest date you've entered in that row.
A17: Yellow cells | B17: The only cells you need to edit. Grey or white cells are formulas or reference data.
A19: Example row (format only) | B19: G999 | Status: DM sent | Warm-up started 2026-09-26 | Connection sent 2026-10-01 | Accepted 2026-10-02 | First DM sent 2026-10-02 | FU1 due fills in as 2026-10-06 | Next action: send FU1 teardown offer
A21: Scoring | B21: Trigger in last 90 days (max 30) + profile gap (max 20) + fit (10) + active in last 30 days (10). Intent signals were not visible, so add +30 by hand when someone views your profile or engages with Gliped. Tier: 60+ Priority, 40 to 59 Warm, under 40 Nurture.
A22: Profile confirmed = No | B22: The LinkedIn link is a people search. Open it, match company and role, then paste the real profile URL into Leads and set Profile confirmed to Yes.
A23: Activity data | B23: Posting timelines come from publicly indexed LinkedIn posts, dated from each post's activity ID. The index only catches some posts, so 'last indexed own post' means at least that recent.

Sheet Leads
A1: ID | B1: Batch | C1: Date added | D1: Name | E1: Role | F1: Company | G1: Region | H1: City | I1: LinkedIn URL | J1: Profile confirmed | K1: Trigger | L1: Trigger date | M1: Source | N1: Activity pattern | O1: Last indexed own post | P1: Activity notes | Q1: Score | R1: Tier | S1: Angle | T1: Connection note | U1: First DM | V1: Teardown focus | W1: Notes | X1: Email address | Y1: Email subject | Z1: Email body | AA1: Email status | AB1: Email lookup note
A2: G001 | B2: 01 | C2: 2026-09-22 | D2: Ravi Ramachandran | E2: Founder & CEO | F2: Nua | G2: India | I2: https://www.linkedin.com/in/ravishankarramachandran | J2: Yes | K2: $50M Series C led by Peak XV and Filter Capital, around 7 Sep 2026. | L2: 2026-09 | N2: Milestone-only | O2: 2026-02 | P2: milestone-only. Indexed posts: the Nua x Zepto "zero irritation promise" campaign (Apr 2025) and a "Zero to Scale" video episode on building Nua (Feb 2026). The Series C shows up through FemTech Insider's post, but no post of his own is indexed yet. | Q2: 60 | R2: =IF(Q2>=60,"Priority",IF(Q2>=40,"Warm","Nurture")) | S2: the post-Series C window. Hiring, category leadership, and keeping the founder story alive between campaigns. | T2: Hi Ravi, congrats on the Series C. Came across your Zero to Scale episode on building Nua. [one line on a specific moment from it] Would be good to connect. | U2: Thanks for connecting, Ravi. Quick one. After a round like this, is your own LinkedIn something you want to put real time into? Or is Nua's page doing that job for now? | V2: headline vs the Series C story, no featured section pointing to Nua, and the gap between the video episode and what he writes himself. | W2: India. Warm, respectful tone. Expect a CoS or comms lead in the decision. | X2: ravi@nuawoman.com | Y2: Nua after the Series C | Z2: Hi Ravi, Congrats on the $50M Series C. Nua's story gets told at big moments, like the Zero to Scale episode, then it goes quiet. In women's wellness, the founder's voice is a trust asset between campaigns too. We run LinkedIn for founders: strategy, writing and posting, built around your voice. Worth a 15-minute call next week to see what that could look like for you? Prabal Gliped | LinkedIn personal branding for founders Not relevant? Reply "no" and I won't follow up. | AA2: Verified | AB2: Prospeo SMTP
A3: G002 | B3: 01 | C3: 2026-09-22 | D3: Karishma Rathaur | E3: Co-founder | F3: Firi | G3: India | I3: https://www.linkedin.com/in/karishmarathaur | J3: Yes | K3: Firi was incorporated in June 2026 and raised a $3M seed led by 360 ONE Asset, with Better Capital and Kunal Shah, in September. It runs 9-minute beauty delivery in Gurugram. Before this she co-built Honestly; she and co-founder Vivek Madani met at Uber India and Flipkart. | L3: 2026-06 | N3: Milestone-only | O3: 2024-04 | P3: almost invisible. One indexed personal post, about advice she got growing up (Apr 2024). | Q3: 60 | R3: =IF(Q3>=60,"Priority",IF(Q3>=40,"Warm","Nurture")) | S3: a launch-stage founder brand. Customers, first hires, and the next round all check the founder. | T3: Hi Karishma, saw the Firi news. Nine-minute beauty delivery is a bold promise. Following what you and Vivek are building. Would be good to connect. | U3: Thanks for connecting, Karishma. Curious how you're thinking about your own voice for Firi. In beauty, people buy from people. Is founder content part of the launch plan? | V3: headline still reflecting the old role, no Firi story on the profile, and what three posts a month could look like (building dark stores, what the AI picks up from Reddit and YouTube reviews, operator lessons from Uber and Flipkart). | W3: India, early stage and price-conscious. Lead with a starter plan and mention the pilot option early. | Y3: Firi's founder story | Z3: Hi Karishma, Nine-minute beauty delivery and a seed round in the same quarter. Strong start. In beauty, people buy from people. Right now Firi's story lives in press coverage, not on your LinkedIn, and that's where hires, partners and your next investors will look. We build founder brands on LinkedIn, from positioning to weekly posts. Open to a quick call to map out your first 90 days? Prabal Gliped | LinkedIn personal branding for founders Not relevant? Reply "no" and I won't follow up. | AA3: Not found
A4: G003 | B4: 01 | C4: 2026-09-22 | D4: Sadra Hosseini | E4: Co-founder & CEO | F4: Ryft | G4: UK | I4: https://www.linkedin.com/in/sadra-hosseini | J4: Yes | K4: €23M to speed up European expansion, Sep 2026. | L4: 2026-09 | N4: Went quiet | O4: 2025-04 | P4: went quiet. From 2022 to 2025 he posted steadily: FCA licence (56 comments), a practical post for founders who are fundraising, marketplace payments posts, Innovate UK grant. The last indexed post is Apr 2025. | Q4: 60 | R4: =IF(Q4>=60,"Priority",IF(Q4>=40,"Warm","Nurture")) | S4: entering new markets. Buyers in France, Germany and the Netherlands will look him up before taking a call. | T4: Hi Sadra, congrats on the raise and the push into Europe. Came across your post with advice for founders who are fundraising. [one line on the point you agreed with] Would be good to connect. | U4: Thanks for connecting, Sadra. One question. With Europe in focus, do you see your own LinkedIn doing any of the market-entry work? Or is that all sales and partnerships? | V4: a UK-only framing, the last post being 17 months ago, and a content line on marketplace payments for EU platforms. | W4: UK. Plain and understated. "Might be useful" over "huge opportunity". | X4: sadra@ryftpay.com | Y4: Ryft's European push | Z4: Hi Sadra, Congrats on the EUR 23M and the move into Europe. Buyers in new markets will look you up before they take a call. Your last post was in April 2025, and your FCA licence post shows your audience responds when you do post. We help founders turn that into a steady weekly presence without eating their week. Worth 15 minutes to talk through a Europe-facing plan? Prabal Gliped | LinkedIn personal branding for founders Not relevant? Reply "no" and I won't follow up. | AA4: Verified | AB4: Prospeo SMTP
A5: G004 | B5: 01 | C5: 2026-09-22 | D5: Erin Kelly | E5: Co-founder & CEO | F5: askpolly | G5: Canada | I5: https://www.linkedin.com/in/erinottawa | J5: Yes | K5: $3M seed led by Differential Ventures (with The 98 and Forum Ventures), Sep 2026, to grow go-to-market in the US. askpolly grew out of Advanced Symbolics and turns social media conversations into market research. | L5: 2026-09 | N5: Went quiet | O5: 2024-06 | P5: went quiet. Sporadic posts (a hotel-industry marketing post, Jun 2024), and the company ran its own webinars and an AMA. | Q5: 60 | R5: =IF(Q5>=60,"Priority",IF(Q5>=40,"Warm","Nurture")) | S5: US buyers don't know her yet. One askpolly insight post a week would work as both content and product demo. | T5: Hi Erin, congrats on the seed and the US push. Turning social conversations into valid research is a smart angle. Would be good to connect. | U5: Thanks for connecting, Erin. Honest question. askpolly surfaces the kind of insight that does really well on LinkedIn. Have you thought about posting some of it under your own name for the US market? | V5: a profile framed around Ottawa and Canada, no featured insight or demo, and a weekly "what people are actually saying about X" format. | W5: Canada. Polite and practical. If you email, CASL applies: it must be relevant to her role and include an unsubscribe. CASL applies to email | Y5: askpolly's US launch | Z5: Hi Erin, Congrats on the seed and the US go-to-market push. askpolly turns social conversations into insight. That kind of data does very well on LinkedIn, and right now none of it goes out under your name to the US buyers you want to reach. We build founder brands on LinkedIn, one insight post a week to start. Open to a 15-minute call to sketch it out? Prabal Gliped | LinkedIn personal branding for founders Not relevant? Reply "no" and I won't follow up. | AA5: Not found
A6: G005 | B6: 01 | C6: 2026-09-22 | D6: Radhika Patil | E6: Co-founder & CEO | F6: Cradlewise | G6: US | I6: https://www.linkedin.com/in/radhika-gandhi-patil | J6: Yes | K6: $12M Series A led by 3one4 Capital and Prudent, Sep 2026, for channel expansion, R&D and international markets. She's on the Forbes Technology Council. | L6: 2026-09 | N6: Milestone-only | O6: 2023-06 | P6: milestone-only, and silent recently. Indexed posts: product design award (2019), $7M raise (Nov 2021), US team growth (Apr 2022), #startupstories (Jun 2023). Nothing indexed since mid-2023. | Q6: 60 | R6: =IF(Q6>=60,"Priority",IF(Q6>=40,"Warm","Nurture")) | S6: a consumer hardware brand entering new markets. Her public voice builds retail partner and parent trust. | T6: Hi Radhika, congrats on the Series A. Cradlewise has been one of the more thoughtful hardware stories out of the India-US corridor. Would be good to connect. | U6: Thanks for connecting, Radhika. Quick one. With new channels and markets coming, do you want your own LinkedIn doing some of that trust-building? Or is it mostly a press and product-led push? | V6: activity gap since 2023, a featured section that doesn't reflect the Series A, and a content line on sleep science plus building hardware across two countries. | W6: US, based in SF, with an India connection. Be direct but warm. | Y6: Cradlewise, new markets | Z6: Hi Radhika, Congrats on the Series A and the international push. You've built great press around Cradlewise, but your own LinkedIn has been quiet since mid-2023. New retail partners and parents will look you up first. We run LinkedIn for founders: positioning, writing and a steady posting rhythm in your voice. Would a 15-minute call next week be useful? Prabal Gliped | LinkedIn personal branding for founders Not relevant? Reply "no" and I won't follow up. | AA6: Not found
A7: G006 | B7: 01 | C7: 2026-09-22 | D7: Shourya Agarwal | E7: Founder & CEO | F7: Flam | G7: US/India | I7: https://www.linkedin.com/in/shourya-agarwal-015947b5 | J7: Yes | K7: $40M Series B led by QED Investors, Sep 2026, with Olivier Pomel, Martin Chavez and Shah Rukh Khan among the backers. | L7: 2026-09 | N7: Company-news voice | O7: 2025-06 | P7: company-news voice. Regular posts through mid-2025 about customer wins (Aditya Birla Capital, Axis Max Life, Salesforce, Business Today), each one a logo announcement. Last indexed Jun 2025. | Q7: 60 | R7: =IF(Q7>=60,"Priority",IF(Q7>=40,"Warm","Nurture")) | S7: the buyers are CMOs, and they follow people. A point of view on "content people interact with" fits his product exactly. | T7: Hi Shourya, congrats on the Series B. The Salesforce and Axis Max Life rollouts on Flam were interesting to follow. Would be good to connect. | U7: Thanks for connecting, Shourya. Curious, with the US push, do you see your own LinkedIn as part of how CMOs discover Flam? Right now the posts are mostly launches, which undersells the thinking behind it. | V7: all posts are announcements, no view of his own on the future of brand content, and no US-facing framing. | W7: SF and Bengaluru. Use a US-direct tone and offer IST or PT slots. | X7: shourya@flamapp.com | Y7: Flam and US CMOs | Z7: Hi Shourya, Congrats on the $40M Series B. Flam sells interactive content to CMOs, yet your feed is mostly launch announcements. CMOs follow people with a point of view, and yours is the story behind Flam. We help founders build that voice on LinkedIn, from strategy to weekly posts. Open to 15 minutes to talk through a US-facing plan? Prabal Gliped | LinkedIn personal branding for founders Not relevant? Reply "no" and I won't follow up. | AA7: Verified | AB7: Prospeo BOUNCEBAN
A8: G007 | B8: 01 | C8: 2026-09-22 | D8: Jagnoor Singh | E8: CEO | F8: Practo | G8: India | I8: https://www.linkedin.com/in/jagnoors | J8: Yes | K8: named CEO effective 1 Sep 2026, after joining as COO in Jan 2025. Previously held senior roles at Airtel, Unacademy and OYO. Practo reports 40% growth and has been profitable for 2.5 years. | L8: 2026-09 | N8: Emerging writer | O8: 2026-07 | P8: emerging writer. Original leadership and health posts roughly every quarter: #growprofitably (Feb 2025, 56 comments), preventive health (Apr 2026), "Firm in meetings, approachable outside" (Jul 2026). | Q8: 50 | R8: =IF(Q8>=60,"Priority",IF(Q8>=40,"Warm","Nurture")) | S8: building a CEO voice distinct from the founder's. | T8: Hi Jagnoor, congrats on the CEO role. Saw your post on being firm in meetings and approachable outside. [one line on why it landed] Would be good to connect. | U8: Thanks for connecting, Jagnoor. The first months in a CEO seat are when people decide what you stand for. Is LinkedIn part of how you want to set that, or more of a side channel? | V8: a headline still in COO mode (check this), no CEO narrative yet, and a cadence of one post a quarter against a potential of one a week. | W8: same company as lead 19. Message Jagnoor first. Don't contact Shashank in the same week. If Jagnoor replies, the pitch can grow into a leadership pair (founder plus CEO). Contact before Shashank ND | X8: jagnoor.singh@practo.com | Y8: Your first 100 days | Z8: Hi Jagnoor, Congrats on stepping in as Practo's CEO. The first months in the seat are when the market decides what a CEO stands for. Your posts get real engagement (56 comments on #growprofitably), but they come about once a quarter. We help CXOs turn that into a steady, credible weekly presence with little time from them. Worth a 15-minute call to map your first 100 days on LinkedIn? Prabal Gliped | LinkedIn personal branding for founders Not relevant? Reply "no" and I won't follow up. | AA8: Verified | AB8: Prospeo BOUNCEBAN Prospeo profile linkedin.com/in/jagnoor-singh-65580910 (title still COO)
A9: G008 | B9: 01 | C9: 2026-09-22 | D9: Madhulima Tewari | E9: CEO | F9: VerifAIX | G9: India/US | I9: https://www.linkedin.com/in/maddietewari | J9: Yes | K9: $5M seed co-led by Endiya Partners and Bluehill VC, Sep 2026, for product, customer deployments and engineering hires. Co-founders are Kenneth Roe and Avner Landver. | L9: 2026-09 | N9: Milestone-only | O9: 2025-10 | P9: milestone-only. The one indexed post is about the RISC-V Summit (Oct 2025). | Q9: 50 | R9: =IF(Q9>=60,"Priority",IF(Q9>=40,"Warm","Nurture")) | S9: a technical thought-leadership voice to build trust with semiconductor buyers and senior engineers. | T9: Hi Madhulima, congrats on the seed. An AI trust layer for chip verification is a real gap. Saw VerifAIX at the RISC-V Summit. Would be good to connect. | U9: Thanks for connecting, Madhulima. In a field this specialised, a few people deciding to trust you matters more than reach. Is your LinkedIn part of how you reach verification leads, or mostly conferences? | V9: posts only at events, a profile that doesn't explain VerifAIX in one line, and a content line on verification bottlenecks. | W9: confirm where she's based before sending (India or US) and set the tone to match. Confirm location | Y9: VerifAIX, trust first | Z9: Hi Madhulima, Congrats on the $5M seed. In chip verification a handful of senior engineers decide who they trust. Right now VerifAIX shows up at events like the RISC-V Summit, but not much on LinkedIn between them. We build technical founder brands on LinkedIn, aimed at the few people who matter. Open to a quick call to see if it fits? Prabal Gliped | LinkedIn personal branding for founders Not relevant? Reply "no" and I won't follow up. | AA9: Not found
A10: G009 | B10: 01 | C10: 2026-09-22 | D10: Ben Armstrong | E10: CEO | F10: Cytix | G10: UK | I10: https://www.linkedin.com/in/benarmstrong2 | J10: Yes | K10: $7M (£5M) Series A led by Northern Gritstone, Aug 2026. He speaks at the Cyber Leaders' Summit. | L10: 2026-08 | N10: Went quiet | O10: 2024-09 | P10: went quiet. He used to post with personality in 2022 and 2023 ("We did it again!" with 29 comments, a post on why consultancies struggle with day rates, video content). Last indexed own post Sep 2024. The Series A was posted by Soapbox VC, not by him. | Q10: 50 | R10: =IF(Q10>=60,"Priority",IF(Q10>=40,"Warm","Nurture")) | S10: bring back what worked, a candid take on security testing, on a steady cadence. | T10: Hi Ben, congrats on the Series A. Came across your post on why consultancies struggle to drop the day rate. Still a live problem. Would be good to connect. | U10: Thanks for connecting, Ben. You used to post a fair bit, then it went quiet. Totally normal while building. Is getting back to it on the list now the round's done? | V10: a 2-year gap, the Series A story told by others, and a content line on AI-driven software change risk. | W10: UK, and North of England. Keep it low-key and skip the hype words. | Y10: Back to posting? | Z10: Hi Ben, Congrats on the Series A. You used to post regularly on LinkedIn, then it went quiet around 2024. The round was announced by others, not you. Enterprise security buyers respond to founders they recognise. We help founders get back to a steady rhythm without writing every post themselves. Worth 15 minutes next week to talk it through? Prabal Gliped | LinkedIn personal branding for founders Not relevant? Reply "no" and I won't follow up. | AA10: Not found
A11: G010 | B11: 01 | C11: 2026-09-22 | D11: Theo Saville | E11: Co-founder & CEO | F11: CloudNC | G11: UK | I11: https://www.linkedin.com/in/theosaville | J11: Yes | K11: €17.2M to scale AI-powered precision machining, Sep 2026. | L11: 2026-09 | N11: Went quiet | O11: 2024-02 | P11: went quiet after a strong run. 2023 was good: a "story of CloudNC" series, "Stealth mode: is it worth it?", CAM Assist at EMO, and a post from the CNC community on Reddit (Feb 2024). The company page now carries it (a drone tour of the factory, podcast clips). | Q11: 50 | R11: =IF(Q11>=60,"Priority",IF(Q11>=40,"Warm","Nurture")) | S11: restart the founder series. Machinists, manufacturers and investors all respond to him directly. | T11: Hi Theo, congrats on the new round. Went back through your "story of CloudNC" posts from 2023. [one line on the part that stuck] Would be good to connect. | U11: Thanks for connecting, Theo. Honest question. Those 2023 posts clearly worked, then the feed went to the company page. Was that a deliberate call or just time? | V11: a 2.5-year gap on his own feed, the company page doing work his voice did better, and a restart plan (the factory, machinists, the Reddit community). | W11: UK. Direct and specific. He'll spot generic copy immediately. Check for in-house marketing | X11: theo.saville@cloudnc.com | Y11: The CloudNC story, restarted | Z11: Hi Theo, Congrats on the new round. In 2023 you told the CloudNC story yourself on LinkedIn. Since early 2024 the storytelling has moved to the company page. Machinists and manufacturers follow you, not the logo. We help founders restart and keep that rhythm, with you in control of the voice. Open to a 15-minute call to see what a restart could look like? Prabal Gliped | LinkedIn personal branding for founders Not relevant? Reply "no" and I won't follow up. | AA11: Verified | AB11: Prospeo BOUNCEBAN
A12: G011 | B12: 01 | C12: 2026-09-22 | D12: Adrian Murray | E12: Founder & CEO | F12: Fisent Technologies | G12: Canada | I12: https://www.linkedin.com/in/adrianmurrray | J12: Yes | K12: $4.3M raise, Aug to Sep 2026. Toronto, GenAI process automation ("BizAI"). | L12: 2026-08 | N12: Milestone-only | O12: 2025-06 | P12: milestone-only. Company announcements from 2024 to 2025 ("growing fast", "successfully completes"), and others interviewing him (Pulse 2.0 in 2025, LaunchPad in May 2026). Last indexed own post Jun 2025. | Q12: 50 | R12: =IF(Q12>=60,"Priority",IF(Q12>=40,"Warm","Nurture")) | S12: turn the interview material into his own weekly posts for enterprise ops and finance buyers. | T12: Hi Adrian, congrats on the raise. The outcomes-as-a-service framing for GenAI automation is a sharp one. Would be good to connect. | U12: Thanks for connecting, Adrian. Other people keep telling Fisent's story in interviews. Your own feed doesn't yet. Is that something you'd want to change this year? | V12: interviews not reused as posts, a headline without the buyer outcome, and the gap since Jun 2025. | W12: Canada, Toronto. Polite and practical. | Y12: Fisent's story, your voice | Z12: Hi Adrian, Congrats on the raise. Other people keep telling Fisent's story in interviews, but your own LinkedIn has been quiet since mid-2025. Outcomes-as-a-service is a strong idea to own in public. We turn founders' thinking into a steady LinkedIn presence for enterprise buyers. Worth a 15-minute call to see how? Prabal Gliped | LinkedIn personal branding for founders Not relevant? Reply "no" and I won't follow up. | AA12: Not found
A13: G012 | B13: 01 | C13: 2026-09-22 | D13: Raghav Midha | E13: Co-founder & CEO | F13: Terminal | G13: Canada | I13: https://www.linkedin.com/in/raghavmidha | J13: Yes | K13: $20M Series A, Jul 2026. YC S23, a telematics data API for trucking. | L13: 2026-07 | N13: Company-news voice | O13: 2025-10 | P13: company-news voice. Indexed posts are hiring and job posts (Chief of Staff Jul 2024, jobs Mar 2025, engineers Oct 2025). | Q13: 50 | R13: =IF(Q13>=60,"Priority",IF(Q13>=40,"Warm","Nurture")) | S13: a founder brand as a recruiting engine, plus credibility with fleet and logistics buyers. | T13: Hi Raghav, congrats on the Series A. Telematics integration is unglamorous and really important. Following Terminal. Would be good to connect. | U13: Thanks for connecting, Raghav. I noticed your posts are mostly hiring. Makes sense. Have you tried writing about the problem itself? It tends to pull better engineers than job posts do. | V13: job posts only, no view of his own on trucking data, and a technical-founder content line for recruiting. | W13: Canada, Toronto, with a US and YC audience. Short and direct. | X13: raghav@withterminal.com | Y13: Hiring after the Series A | Z13: Hi Raghav, Congrats on the $20M Series A. Your LinkedIn is mostly job posts right now. Strong engineers pick founders whose thinking they've already seen. We help technical founders write about the problem they're solving, so hiring and fleet buyers come to them. Open to 15 minutes to talk it through? Prabal Gliped | LinkedIn personal branding for founders Not relevant? Reply "no" and I won't follow up. | AA13: Verified | AB13: Prospeo SMTP
A14: G013 | B14: 01 | C14: 2026-09-22 | D14: Doug Schweitzer | E14: CEO & co-founder | F14: Ultimarii | G14: Canada | I14: https://www.linkedin.com/in/doug-schweitzer-573a443b | J14: Yes | K14: Series A of more than $13M CAD led by BDC's Industrial Innovation Venture Fund, Sep 2026. Calgary, regulatory AI for infrastructure approvals. He's a former Alberta innovation minister and co-founded Blue Rock Law. | L14: 2026-09 | N14: Went quiet | O14: 2024-01 | P14: went quiet. From 2022 to 2024 he mostly shared news links about the Alberta economy (IBM Calgary with 42 comments, oil and gas labour with 39 comments). Last indexed Jan 2024. The Ultimarii page carries the company voice now. | Q14: 50 | R14: =IF(Q14>=60,"Priority",IF(Q14>=40,"Warm","Nurture")) | S14: move from minister and lawyer to AI infrastructure founder. The audience is energy and infrastructure executives and regulators. | T14: Hi Doug, congrats on the Ultimarii Series A. Speeding up infrastructure approvals is one of the more practical uses of AI I've seen. Would be good to connect. | U14: Thanks for connecting, Doug. People know you from your years in government. Fewer know you as a founder yet. Is shifting that part of the plan for this year? | V14: posts are shared articles rather than his own view, the positioning is still political and legal, and a founder narrative on approvals and energy projects. | W14: Canada, Alberta. Respectful. He likely has advisers, so expect a gatekeeper. Former Alberta minister | X14: doug.schweitzer@ultimarii.com | Y14: From minister to founder | Z14: Hi Doug, Congrats on Ultimarii's Series A. People know you from your years in government. Fewer know you yet as the founder speeding up infrastructure approvals with AI, and your LinkedIn still reads like the old role. We help founders reposition on LinkedIn with a steady voice aimed at energy and infrastructure leaders. Worth a 15-minute call? Prabal Gliped | LinkedIn personal branding for founders Not relevant? Reply "no" and I won't follow up. | AA14: Verified | AB14: Prospeo BOUNCEBAN
A15: G014 | B15: 01 | C15: 2026-09-22 | D15: Gabriel Rivest | E15: CEO & co-founder | F15: Scopia Surgical | G15: Canada | I15: https://www.linkedin.com/in/gabriel-rivest-11a019b4 | J15: Yes | K15: $2.65M CAD pre-seed co-led by Linearis Ventures and Anges Québec, Sep 2026. Montreal, AI surgical navigation. | L15: 2026-09 | N15: Milestone-only | O15: 2026-09-04 | P15: milestone-only, but active right now. A vision post (Feb 2025) and the funding post (4 Sep 2026). This is the only lead confirmed active in the last 30 days. | Q15: 50 | R15: =IF(Q15>=60,"Priority",IF(Q15>=40,"Warm","Nurture")) | S15: building credibility with clinicians and partners ahead of trials, with bilingual content. | T15: Hi Gabriel, congrats on closing the pre-seed. Real-time navigation for robotic surgery is a big bet. Following Scopia. Would be good to connect. | U15: Thanks for connecting, Gabriel. In medtech, surgeons and partners tend to check the founder before the product. Is building that voice something you're planning, in French, English or both? | V15: posts only at milestones, the profile language (FR vs EN), and a clinician-facing content line. | W15: Quebec. Offer French. Polite and practical. Active last 30 days; offer French | X15: gabriel@scopia.tech | Y15: Scopia's next chapter | Z15: Hi Gabriel, Congrats on closing the pre-seed. In medtech, surgeons and partners check the founder before the product. Right now you post at milestones only. We build founder brands on LinkedIn, in English, French or both, aimed at clinicians and partners. Open to a quick call to see what that could look like for Scopia? Prabal Gliped | LinkedIn personal branding for founders Not relevant? Reply "no" and I won't follow up. | AA15: Verified | AB15: Prospeo BOUNCEBAN
A16: G015 | B16: 01 | C16: 2026-09-22 | D16: David Lighton | E16: Founder & CEO | F16: Diameter Pay | G16: US | I16: https://www.linkedin.com/in/david-lighton-b027a917 | J16: Yes | K16: $10M Series A, Sep 2026. The company was bootstrapped before this round, and processed $300M in payment volume in 2023. | L16: 2026-09 | N16: Went quiet | O16: 2023-07 | P16: went quiet. In 2023 he shared finance and policy articles (de-risking China, Citadel buying into Western Alliance, legacy admissions). Nothing indexed since mid-2023. | Q16: 50 | R16: =IF(Q16>=60,"Priority",IF(Q16>=40,"Warm","Nurture")) | S16: the bootstrapped-to-Series A story, and a credible voice on stablecoin infrastructure. | T16: Hi David, congrats on the Series A. Bootstrapping to that point in payments is rare. Following Diameter. Would be good to connect. | U16: Thanks for connecting, David. You used to share sharp finance and policy reads. Then it went quiet. Is getting your own view out there part of the plan now that the round is done? | V16: link shares with no commentary, a 3-year gap, and a content line on stablecoin payments for banks. | W16: confirm his location (assumed US). Direct and numbers-first. Confirm location | Y16: Bootstrapped to Series A | Z16: Hi David, Congrats on the Series A. Bootstrapping to that point in payments is rare. That's a story banks and platforms want to hear, but your LinkedIn has been quiet since 2023. We help founders turn their thinking into a steady LinkedIn presence, aimed at the partners they need. Worth 15 minutes to talk it through? Prabal Gliped | LinkedIn personal branding for founders Not relevant? Reply "no" and I won't follow up. | AA16: Not found
A17: G016 | B17: 01 | C17: 2026-09-22 | D17: Leo Crowe | E17: Co-founder & CEO | F17: Souk | G17: UK | I17: https://www.linkedin.com/in/leo-crowe-457815121 | J17: Yes | K17: $1.6M pre-seed led by Sure Valley Ventures, with Antler and Fuel Ventures, Sep 2026. London, "Coco", an AI partner manager. | L17: 2026-09 | N17: Emerging writer | O17: 2026-04 | P17: emerging writer. Original takes about every 3 months: the Souk launch (Aug 2025), "one consistent problem across every..." (Jan 2026), "I told Souk our own ICP..." (Apr 2026). | Q17: 40 | R17: =IF(Q17>=60,"Priority",IF(Q17>=40,"Warm","Nurture")) | S17: from quarterly to weekly, without it eating his week. | T17: Hi Leo, congrats on the pre-seed. Saw your post on running Souk against its own ICP. [one line on the takeaway] Would be good to connect. | U17: Thanks for connecting, Leo. Your partnership posts are good, they just come every few months. Is weekly something you'd do if it only took 30 minutes of your time? | V17: cadence, no featured link to Coco, and one recurring format (the partner-activation playbook). | W17: UK. Pre-seed budget, so offer a lighter plan or pilot. Pre-seed budget | Y17: Weekly, not quarterly | Z17: Hi Leo, Congrats on the pre-seed. You already write about partnerships on LinkedIn, and your buyers live there. The gap is rhythm: a post every few months instead of every week. We help founders keep a weekly cadence in their own voice without it eating their week. Open to a quick call? Prabal Gliped | LinkedIn personal branding for founders Not relevant? Reply "no" and I won't follow up. | AA17: Not found
A18: G017 | B18: 01 | C18: 2026-09-22 | D18: Alex Harland | E18: Co-founder & CEO | F18: AI Score | G18: UK | I18: https://www.linkedin.com/in/alex-harland-a110b0149 | J18: Yes | K18: €4.6M raise, Sep 2026. London, keeping AI agents under control. He was on the founding team at the UK's NCSC; co-founder Benita Tibb is a former City lawyer. | L18: 2026-09 | N18: Emerging writer | O18: 2026-02 | P18: emerging writer. Technical opinion posts about every 6 months: OPA/Rego (Aug 2025), "AI governance does not belong in .pdf" (Feb 2026). | Q18: 40 | R18: =IF(Q18>=60,"Priority",IF(Q18>=40,"Warm","Nurture")) | S18: category-creation thought leadership. | T18: Hi Alex, congrats on the round. "AI governance does not belong in a PDF" is a line more people need to hear. Would be good to connect. | U18: Thanks for connecting, Alex. You've got a clear point of view on AI governance. It shows up about twice a year. Is building that into a regular voice on the list for AI Score? | V18: cadence, NCSC credibility not front and centre, and a split between technical and board-level posts. | W18: UK. Precise and low-hype. Expect security-minded scepticism. | Y18: AI governance, out loud | Z18: Hi Alex, Congrats on the round. You have a clear point of view on AI governance, and CISOs and GCs need to hear it more than twice a year. We help founders turn that point of view into a steady LinkedIn presence that builds the category with them in it. Worth a 15-minute call next week? Prabal Gliped | LinkedIn personal branding for founders Not relevant? Reply "no" and I won't follow up. | AA18: Not found
A19: G018 | B19: 01 | C19: 2026-09-22 | D19: Shishir Bankapur | E19: CEO | F19: Helogen | G19: US | I19: https://www.linkedin.com/in/shishir-work | J19: Yes | K19: $7.1M seed co-led by RRE Ventures and Oceans, Sep 2026. NYC, space biotech and in-orbit manufacturing. | L19: 2026-09 | N19: Emerging writer | O19: 2026-06 | P19: emerging writer. Big-idea posts now and then: the AgResearch partnership (Apr 2025) and "The next industrial revolution isn't on earth" (Jun 2026). | Q19: 40 | R19: =IF(Q19>=60,"Priority",IF(Q19>=40,"Warm","Nurture")) | S19: an explainer-led founder voice. | T19: Hi Shishir, congrats on the seed. "The next industrial revolution isn't on earth" is a good way to put it. Would be good to connect. | U19: Thanks for connecting, Shishir. Space biomanufacturing needs a lot of explaining, and you do it well. Are you planning to make that a regular thing, or keep it to big moments? | V19: cadence, no plain-English line on what Helogen makes, and an explainer series. | W19: US East. Direct. | X19: shishir@helogen.com | Y19: Explaining Helogen | Z19: Hi Shishir, Congrats on the seed. Space biomanufacturing needs a lot of explaining to investors, talent and early customers. "The next industrial revolution isn't on earth" is a good frame, and it deserves a regular slot. We help frontier founders build an explainer-led presence on LinkedIn. Open to a quick call to see how? Prabal Gliped | LinkedIn personal branding for founders Not relevant? Reply "no" and I won't follow up. | AA19: Verified | AB19: Prospeo SMTP Prospeo profile linkedin.com/in/shishir-b-40ba0a126 (Helogen CEO)
A20: G019 | B20: 01 | C20: 2026-09-22 | D20: Shashank ND | E20: Founder MD & Exec Chairman | F20: Practo | G20: India | I20: https://www.linkedin.com/in/shashanknd | J20: Yes | K20: moved from CEO to MD and Executive Chairman on 1 Sep 2026. He'll lead capital strategy, inorganic growth and innovation. | L20: 2026-09 | N20: Company-news voice | O20: 2026-01 | P20: company-news voice with a big-moment cadence: annual letters (FY24, Jun 2024), market launches (UAE May 2025, US Jan 2026). Media covers him often (the AI transformation piece and the Cent launch, Mar 2026). | Q20: 40 | R20: =IF(Q20>=60,"Priority",IF(Q20>=40,"Warm","Nurture")) | S20: the chairman narrative. Fewer operations posts, more on long-term bets. | T20: Hi Shashank, congratulations on the new role at Practo. The move into the US and UAE has been interesting to follow. Would be good to connect. | U20: Thanks for connecting, Shashank. Moving from CEO to chairman usually changes what people expect to hear from you. Is that something you're thinking about for LinkedIn? | W20: only after lead 7 has been contacted and at least a week has passed. The likely route is through his comms or CoS. India, senior. Very respectful and short. Wait 1 week after Jagnoor | X20: shashank@centai.in | Y20: The chairman's voice | Z20: Hi Shashank, Congratulations on the new role at Practo. Moving from CEO to Executive Chairman changes what people expect to hear from you: capital, AI and the long-term bets, not operations. We help senior leaders shape that narrative on LinkedIn, with a light touch on their time. Would a short call be useful, with you or whoever runs your comms? Prabal Gliped | LinkedIn personal branding for founders Not relevant? Reply "no" and I won't follow up. | AA20: Verified | AB20: Prospeo SMTP Address is at Cent (his preventive-health company) not Practo
A21: G020 | B21: 01 | C21: 2026-09-22 | D21: Ilan Zerbib | E21: Founder & CEO | F21: Sapiom | G21: US | I21: https://www.linkedin.com/in/izerbib | J21: Yes | K21: $15.75M seed with Accel (Feb 2026), then a $35M Series A (Aug 2026). SF, AI agents and agentic payments. He spent nearly 5 years at Shopify. | L21: 2026-08 | N21: Already consistent | O21: 2026-08 | P21: already consistent, the most active in the batch. Roughly monthly original posts in 2026: the Shopify chapter (Oct 2025), the seed (Feb), Okta Ventures (Feb), "Building with Sapiom" (Jul), "Eleven months ago I founded Sapiom" (Aug). | Q21: 40 | R21: =IF(Q21>=60,"Priority",IF(Q21>=40,"Warm","Nurture")) | S21: go from monthly to weekly and turn big posts into series, so a CEO of a fast-growing company gets the hours back. | T21: Hi Ilan, congrats on the Series A. Saw your "eleven months ago I founded Sapiom" post. [one line on what stood out] Would be good to connect. | U21: Thanks for connecting, Ilan. You're one of the few founders who actually posts consistently. Curious, how much of your week does it take right now? | V21: go from monthly to weekly, reuse the long posts, and his agentic payments point of view for the buyers. | W21: US West. Numbers-first. He'll judge Gliped on its own profile, so make sure it's current. Pitch time and reach not starting | X21: ilan@sapiom.ai | Y21: Your weekly hours back | Z21: Hi Ilan, Congrats on the Series A. You're one of the few founders who posts consistently. That usually costs hours a week that a CEO of a fast-growing company doesn't have. We keep founders' voice and rhythm while taking the writing and repurposing off their plate. Worth 15 minutes to see what you'd get back? Prabal Gliped | LinkedIn personal branding for founders Not relevant? Reply "no" and I won't follow up. | AA21: Verified | AB21: Prospeo SMTP
A22: G021 | B22: 02 | C22: 2026-09-25 | D22: Aniket Shah | E22: Co-founder & CEO | F22: Swish | G22: India | H22: Bengaluru | I22: https://www.linkedin.com/in/aniketshah30 | J22: Yes | K22: $24M led by Bertelsmann India, with Accel and Bain Capital Ventures, to expand its 10-minute kitchen network | L22: 2026-09-10 | M22: https://entrackr.com/news/10-minute-food-delivery-startup-swish-raises-24-mn-led-by-bertelsmann-india-investments-12513814 | N22: Milestone-only | O22: 2025-03 | P22: Indexed own posts: Founder's Office hiring (Jan 2025) and the last raise (Mar 2025). Co-founder Ujjwal Sukheja wrote the founding story the same week. Nothing indexed since. | Q22: 60 | R22: =IF(Q22>=60,"Priority",IF(Q22>=40,"Warm","Nurture")) | S22: Quick commerce is crowded. The founder who explains why 10-minute fresh food works wins hires and press between rounds. | T22: Hi Aniket, congrats on the new round. Neighbourhood kitchens within a kilometre is a sharp way to make 10 minutes work. Would be good to connect. | U22: Thanks for connecting, Aniket. Quick one. With the kitchen network growing, do you want your own LinkedIn telling that story? Or is it mostly the brand account for now? | V22: Posts only at raises and hiring; no view of his own on hyperlocal food ops; featured section not pointing to Swish. | W22: Co-founders Ujjwal Sukheja and Saran S. also post. Pitch Aniket first. | X22: aniket@justswish.in | Y22: Swish's founder story | Z22: Hi Aniket, Congrats on the $24M round. Quick commerce is crowded, and Swish's story mostly shows up at raises and hiring posts. The founder who explains why 10-minute fresh food works wins the best hires and the press in between. We build founder brands on LinkedIn, from positioning to weekly posts. Open to a 15-minute call next week? Prabal Gliped | LinkedIn personal branding for founders Not relevant? Reply "no" and I won't follow up. | AA22: Verified | AB22: Prospeo SMTP
A23: G022 | B23: 02 | C23: 2026-09-25 | D23: Sunil Gupta | E23: Co-founder & CEO | F23: QNu Labs | G23: India | H23: Bengaluru | I23: https://www.linkedin.com/in/sunil-gupta-1733754 | J23: Yes | K23: Rs 200 Cr Series A1 co-led by National Quantum Mission and Speciale Invest, with Sony Innovation Fund | L23: 2026-09-09 | M23: https://startuptalky.com/news/daily-indian-funding-roundup-key-news-9-september-2026/ | N23: Company-news voice | O23: 2025-12 | P23: Posts company milestones one to three times a year since 2021: IMC 2022 (28 comments), India's first quantum telecom link, Tracxn ranking, a Dec 2025 breakthrough post. All announcements. | Q23: 50 | R23: =IF(Q23>=60,"Priority",IF(Q23>=40,"Warm","Nurture")) | S23: Quantum security needs explaining to CISOs and government buyers. A founder voice on why quantum-safe matters now turns announcements into trust. | T23: Hi Sunil, congrats on the Series A1. Quantum-safe security built out of India is a story more CISOs should hear. Would be good to connect. | U23: Thanks for connecting, Sunil. Your posts mostly announce QNu milestones. Have you thought about explaining the why behind quantum-safe for buyers who are still catching up? | V23: Announcement-only feed; no plain-language line on what QNu does; no cadence between milestones. | W23: Deep tech, government and defence buyers. Keep it formal. | X23: sunil@qnulabs.com | Y23: Quantum-safe, explained | Z23: Hi Sunil, Congrats on the Rs 200 Cr Series A1. Your LinkedIn announces QNu's milestones well. What most CISOs and government buyers still need is the why: why quantum-safe, why now. We help deep-tech founders build that voice on LinkedIn, steadily and credibly. Worth a 15-minute call to see how it could work for you? Prabal Gliped | LinkedIn personal branding for founders Not relevant? Reply "no" and I won't follow up. | AA23: Verified | AB23: Prospeo SMTP
A24: G023 | B24: 02 | C24: 2026-09-25 | D24: Prashant Shah | E24: Co-founder & CEO | F24: Definedge | G24: India | H24: Pune | I24: https://www.linkedin.com/in/prashant-shah-definedge | J24: Yes | K24: Rs 22 Cr pre-Series A; total raised Rs 30 Cr; 14+ trading and investing platforms (Opstra, Zone, Algostra) | L24: 2026-09-22 | M24: https://entrackr.com/snippets/fintech-and-brokerage-startup-definedge-raises-rs-22-cr-in-pre-series-a-12562400 | N24: Milestone-only | O24: 2025-12 | P24: One own post indexed (Dec 2025, a Definedge milestone). Holds CMT, CFTe, MFTA and MSTA, so he has deep technical-analysis credibility that barely shows on LinkedIn. | Q24: 50 | R24: =IF(Q24>=60,"Priority",IF(Q24>=40,"Warm","Nurture")) | S24: Retail traders follow people, not platforms. His chartered-technician credibility is the brand asset. | T24: Hi Prashant, congrats on the pre-Series A. Fourteen platforms for retail traders out of Pune is a lot of product. Would be good to connect. | U24: Thanks for connecting, Prashant. You carry more technical-analysis credentials than most people posting about markets. Is building a voice on LinkedIn part of the plan now? | V24: Credentials in headline but no educational posts; no link to Definedge platforms; posts only at milestones. | W24: Check whether he already posts on YouTube or X. If so, pitch repurposing onto LinkedIn. | X24: prashant.shah@definedge.com | Y24: Your credentials, visible | Z24: Hi Prashant, Congrats on the pre-Series A. You carry more technical-analysis credentials than most people posting about markets, yet they barely show on LinkedIn. Retail traders follow people, not platforms. We turn founders' expertise into a steady LinkedIn presence that pulls users to the product. Open to a quick call? Prabal Gliped | LinkedIn personal branding for founders Not relevant? Reply "no" and I won't follow up. | AA24: Verified | AB24: Prospeo SMTP Prospeo headline: Co-founder & CEO
A25: G024 | B25: 02 | C25: 2026-09-25 | D25: Abhijit (AB) Gupta | E25: Co-founder | F25: Popo Global (The Pizza Bakery, Paris Panini, Smash Guys) | G25: India | H25: Bengaluru | I25: https://www.linkedin.com/in/ab-gupta-9b1b8210 | J25: Yes | K25: Rs 532 Cr from Artal Asia to expand beyond Bengaluru | L25: 2026-09-11 | M25: https://entrackr.com/snippets/the-pizza-bakery-operator-popo-global-raises-rs-532-cr-from-artal-asia-12518089 | N25: Went quiet | O25: 2023-04 | P25: Posted 'Growth Stories: Lessons from The Pizza Bakery' (Apr 2023) and spoke on an investor panel about building F&B without growth capital (May 2023). The company page carries it since. | Q25: 60 | R25: =IF(Q25>=60,"Priority",IF(Q25>=40,"Warm","Nurture")) | S25: He built without outside capital and now has Rs 532 Cr. That's a founder story F&B operators and new-city hires will follow. | T25: Hi AB, congrats on the Artal round. Building The Pizza Bakery without growth capital first makes this one more interesting. Would be good to connect. | U25: Thanks for connecting, AB. Your growth-stories episode from 2023 was one of the few times you told the story yourself. With new cities coming, is that something you want to do more of? | V25: Three-year gap; profile doesn't show the three brands; expansion story is untold. | W25: Co-founder brother Nikhil Gupta. Pitch AB first. | Y25: Pizza Bakery, next cities | Z25: Hi AB, Congrats on the Rs 532 Cr round from Artal. You built The Pizza Bakery without growth capital. That's a founder story F&B operators, landlords and new-city hires will follow, and it hasn't been on your LinkedIn since 2023. We build founder brands on LinkedIn around stories like that. Worth 15 minutes to talk it through? Prabal Gliped | LinkedIn personal branding for founders Not relevant? Reply "no" and I won't follow up. | AA25: Not found
A26: G025 | B26: 02 | C26: 2026-09-25 | D26: Karan Jain | E26: Founder & CEO | F26: Carrum Mobility | G26: India | H26: Bengaluru | I26: https://www.linkedin.com/search/results/people/?keywords=Karan%20Jain%20Carrum%20Mobility | J26: No | K26: $10M Series B led by Uber at about $168M valuation; business nearly doubled since January; profitable since month one | L26: 2026-09-09 | M26: https://techcrunch.com/2026/09/09/uber-invests-10m-in-indian-fleet-operator-carrum-at-168m-valuation/ | N26: Not indexed | P26: No own posts indexed. Several people share the name, so confirm the profile first. He previously founded Revv (acquired by CarDekho). | Q26: 60 | R26: =IF(Q26>=60,"Priority",IF(Q26>=40,"Warm","Nurture")) | S26: Second-time founder, profitable from month one, backed twice by Uber. A rare story in mobility that he isn't telling. | T26: Hi Karan, congrats on the Uber round. Profitable from month one in fleet management is rare. Following Carrum. Would be good to connect. | U26: Thanks for connecting, Karan. Between Revv and Carrum you've got a founder story most people in mobility would want to hear. Is LinkedIn somewhere you want to tell it? | V26: Confirm profile; check headline mentions Revv exit; content line on profitable fleet ops and the EV and CNG shift. | W26: Confirm profile before sending. | Y26: Profitable from month one | Z26: Hi Karan, Congrats on the Uber-led round. A second-time founder, profitable from month one, backed twice by Uber. Very few people in mobility can tell that story, and right now you're not telling it on LinkedIn. We build founder brands on LinkedIn, from positioning to weekly posts. Open to a 15-minute call next week? Prabal Gliped | LinkedIn personal branding for founders Not relevant? Reply "no" and I won't follow up. | AA26: Not found
A27: G026 | B27: 02 | C27: 2026-09-25 | D27: Abhishek Murarka | E27: Co-founder & CEO | F27: Circolife | G27: India | I27: https://www.linkedin.com/in/abhishek-murarka-633b876 | J27: Yes | K27: $4.5M (Rs 40.45 Cr) pre-Series A anchored by Bharat Jaisinghani of Polycab, with Nitish Mittersain; target 40,000 cooling units | L27: 2026-09-08 | M27: https://www.exchange4media.com/industry-briefing-news/circolife-raises-45-mn-pre-series-a-158085.html | N27: Not indexed | P27: Indexed posts under this name are about investing and wealth (2021 to 2024) and may be a different person. The Circolife company page posts regularly. | Q27: 50 | R27: =IF(Q27>=60,"Priority",IF(Q27>=40,"Warm","Nurture")) | S27: Cooling-as-a-service is a new category. Businesses buying it want to trust the operator behind it. | T27: Hi Abhishek, congrats on the pre-Series A. Cooling as a subscription is a smart model for Indian offices. Would be good to connect. | U27: Thanks for connecting, Abhishek. The company page is doing the talking for Circolife right now. Is building your own voice around the category something you've thought about? | V27: Confirm profile; company page posts, founder silent; content line on energy savings and IoT maintenance. | W27: Profile confirmed via Prospeo (CEO & Co-Founder, Circolife). Indexed posts under this name were a different person. | X27: abhishek@circolife.com | Y27: Cooling as a category | Z27: Hi Abhishek, Congrats on the pre-Series A. Cooling-as-a-service is a new category, and businesses buying it want to trust the operator behind it. Right now Circolife's page does the talking. We help founders build their own voice on LinkedIn around the category they're creating. Worth a quick call to see if it fits? Prabal Gliped | LinkedIn personal branding for founders Not relevant? Reply "no" and I won't follow up. | AA27: Verified | AB27: Prospeo SMTP PROFILE https://www.linkedin.com/in/abhishek-murarka-633b876 (CEO & Co-Founder Circolife)
A28: G027 | B28: 02 | C28: 2026-09-25 | D28: Sneha Priya Reddy | E28: Co-founder | F28: UniqYou | G28: India | H28: Bengaluru | I28: https://www.linkedin.com/search/results/people/?keywords=Sneha%20Priya%20Reddy%20UniqYou | J28: No | K28: Rs 15.8 Cr seed led by Arkam Ventures and Antler; company founded 2026; angels include Myntra's co-founder and former CEO | L28: 2026-09-14 | M28: https://startuptalky.com/news/daily-indian-funding-roundup-key-news-14-september-2026/ | N28: Not indexed | P28: No own posts indexed. Brand-new company, so her founder presence is starting from zero. | Q28: 60 | R28: =IF(Q28>=60,"Priority",IF(Q28>=40,"Warm","Nurture")) | S28: Women's fashion is built on trust and taste. A founder-led feed at launch is cheaper than paid acquisition. | T28: Hi Sneha, congrats on the seed. A tech-first platform for women's fashion with the Myntra founders behind it is a strong start. Would be good to connect. | U28: Thanks for connecting, Sneha. In fashion, people buy into the founder's taste first. Is your own LinkedIn part of the launch plan for UniqYou? | V28: Confirm profile; launch story; build-in-public format for the first 90 days. | W28: Confirm profile. Co-founder Nishanth Jois. | Y28: UniqYou's launch voice | Z28: Hi Sneha, Congrats on the seed, and on backers like the Myntra founders. In fashion, people buy into the founder's taste first. A founder-led LinkedIn at launch often costs less than paid acquisition and brings hires with it. We build founder brands on LinkedIn from day one. Open to 15 minutes to plan your first 90 days? Prabal Gliped | LinkedIn personal branding for founders Not relevant? Reply "no" and I won't follow up. | AA28: Not found
A29: G028 | B29: 02 | C29: 2026-09-25 | D29: Ankit Joshi | E29: Co-founder | F29: TRUE ARTIS | G29: India | H29: Delhi NCR | I29: https://www.linkedin.com/search/results/people/?keywords=Ankit%20Joshi%20TRUE%20ARTIS | J29: No | K29: Rs 11.4 Cr seed led by Zeropearl VC, with Medanta co-founder's group Eleven; two aesthetic surgery centres in Delhi and Gurgaon | L29: 2026-09-16 | M29: https://startuptalky.com/news/daily-indian-funding-roundup-key-news-16-september-2026/ | N29: Not indexed | P29: No own posts indexed that clearly match. Many profiles share the name. | Q29: 50 | R29: =IF(Q29>=60,"Priority",IF(Q29>=40,"Warm","Nurture")) | S29: Aesthetic surgery is a trust purchase. A founder who explains safety and standards sets the brand apart from clinics. | T29: Hi Ankit, congrats on the seed. An integrated aesthetic surgery platform with Medanta-linked backing is a strong signal. Would be good to connect. | U29: Thanks for connecting, Ankit. In aesthetics, patients check who's behind the clinic before they book. Is founder content part of how you want to build TRUE ARTIS? | V29: Confirm profile; trust and safety content line; doctor partner features. | W29: Confirm profile. Co-founder Sandeep Upadhyay. Medical advertising rules apply to content. | Y29: TRUE ARTIS, trust first | Z29: Hi Ankit, Congrats on the seed. In aesthetic surgery, patients check who's behind the clinic before they book. A founder who talks openly about safety and standards sets TRUE ARTIS apart. We build founder brands on LinkedIn, carefully and within medical advertising norms. Worth a 15-minute call? Prabal Gliped | LinkedIn personal branding for founders Not relevant? Reply "no" and I won't follow up. | AA29: Not found
A30: G029 | B30: 02 | C30: 2026-09-25 | D30: Devang Kumar | E30: Founder & CEO | F30: Greenwave Circularity | G30: India | H30: Odisha | I30: https://www.linkedin.com/search/results/people/?keywords=Devang%20Kumar%20Greenwave%20Circularity | J30: No | K30: $31.5M financing from OeEB (Development Bank of Austria) for a closed-loop PET recycling plant; JV with a Coca-Cola bottler | L30: 2026-09-09 | M30: https://indianstartupnews.com/funding/greenwave-circularity-raises-315-million-from-oeeb-for-odisha-pet-recycling-plant-12516293 | N30: Not indexed | P30: No own posts indexed. | Q30: 50 | R30: =IF(Q30>=60,"Priority",IF(Q30>=40,"Warm","Nurture")) | S30: Circular economy buyers (brands, bottlers, ESG teams) look for credible operators. A founder voice on recycled PET fills that gap. | T30: Hi Devang, congrats on the OeEB financing. Closed-loop PET recycling at that scale is what brand ESG targets need. Would be good to connect. | U30: Thanks for connecting, Devang. Most brand sustainability leads are on LinkedIn. Is building a voice there part of how you plan to win offtake partners? | V30: Confirm profile; ESG buyer content line; plant progress series. | W30: Confirm profile. This is debt financing, not equity, so avoid calling it a round. | Y30: Greenwave and ESG buyers | Z30: Hi Devang, Congrats on the OeEB financing. The brand sustainability leads you'll want as offtake partners are on LinkedIn. A founder voice on closed-loop PET recycling gives them a reason to call you first. We build founder brands on LinkedIn, aimed at the buyers that matter. Open to a quick call? Prabal Gliped | LinkedIn personal branding for founders Not relevant? Reply "no" and I won't follow up. | AA30: Not found
A31: G030 | B31: 02 | C31: 2026-09-25 | D31: Avni Jain | E31: Founder | F31: Nuvah | G31: India | I31: https://www.linkedin.com/in/avni-jain-05b45448 | J31: Yes | K31: Rs 4 Cr pre-seed from Amit Jain (CarDekho), Shantanu Deshpande (Bombay Shaving Co) and Ishendra Agarwal (GIVA); comfort-engineered heels | L31: 2026-09-22 | M31: https://startuptalky.com/news/nuvah-raises-4-crore-pre-seed-comfort-heels/ | N31: Not indexed | P31: No own posts indexed that match. Ex-McKinsey, Goldman Sachs and VC; IIM Ahmedabad. | Q31: 50 | R31: =IF(Q31>=60,"Priority",IF(Q31>=40,"Warm","Nurture")) | S31: D2C founder with a product-obsession story (24 prototypes, 900 hours of wear testing). That's content. | T31: Hi Avni, congrats on the pre-seed. 24 prototypes to get a heel that doesn't hurt is the kind of detail that sells. Would be good to connect. | U31: Thanks for connecting, Avni. The build story behind Nuvah is strong content on its own. Is founder-led content part of the launch plan? | V31: Confirm profile; build-in-public series; headline from consulting to founder. | W31: Profile confirmed via Prospeo (Founder & CEO, Nuvah). Pre-seed budget. | X31: avni@nuvah.in | Y31: 24 prototypes is content | Z31: Hi Avni, Congrats on the pre-seed. 24 prototypes and 900 hours of wear testing to get a heel that doesn't hurt. That build story is content most D2C founders would kill for. We help founders turn stories like that into a steady LinkedIn presence, sized for an early-stage budget. Worth a 15-minute call? Prabal Gliped | LinkedIn personal branding for founders Not relevant? Reply "no" and I won't follow up. | AA31: Verified | AB31: Prospeo SMTP PROFILE https://www.linkedin.com/in/avni-jain-05b45448 (Founder & CEO Nuvah)
A32: G031 | B32: 02 | C32: 2026-09-25 | D32: Charlie Bullock | E32: Co-founder & CEO | F32: Scan.com | G32: UK | H32: London | I32: https://www.linkedin.com/in/charlie-bullock | J32: Yes | K32: $220M incl. $90M Series C equity led by Noteus Partners, to build the largest US imaging network | L32: 2026-08-31 | M32: https://www.businesswire.com/news/home/20260831019981/en/Scan.com-Raises-$220-Million-to-Build-the-Largest-Medical-Imaging-Network-in-the-US | N32: Milestone-only | O32: 2025-03 | P32: Forbes 30 Under 30 (Apr 2024), Deloitte recognition (Nov 2024), a healthtech diagnostics post with 59 comments (Mar 2025). Last own post indexed Mar 2025. | Q32: 60 | R32: =IF(Q32>=60,"Priority",IF(Q32>=40,"Warm","Nurture")) | S32: Moving the centre of gravity to the US. US health systems and partners don't know him yet. | T32: Hi Charlie, congrats on the Series C. Building a national imaging network in the US from a UK start is a big move. Would be good to connect. | U32: Thanks for connecting, Charlie. Your posts do well when you post. The last one I could find was March 2025. With the US push, is getting back to it on the list? | V32: 18-month gap; UK framing; US health-system audience content line. | W32: Likely has comms support. Ask who owns his LinkedIn. | X32: charlie@scan.com | Y32: Scan.com's US chapter | Z32: Hi Charlie, Congrats on the Series C and the US push. Your posts land well when you post, but the last one I could find was March 2025. US health systems and partners are meeting you for the first time now. We help founders keep a steady, credible LinkedIn presence, working with your comms team. Worth a 15-minute call? Prabal Gliped | LinkedIn personal branding for founders Not relevant? Reply "no" and I won't follow up. | AA32: Verified | AB32: Prospeo SMTP Based in Atlanta per Prospeo
A33: G032 | B33: 02 | C33: 2026-09-25 | D33: Charlie Cook | E33: Founder & CEO | F33: Rightcharge | G33: UK | H33: London | I33: https://www.linkedin.com/in/charlie-cook-2088922b | J33: Yes | K33: GBP 500k after 20x ARR growth, to scale fleet EV charging payments across Europe; Visa recommended partner (Jul 2026) | L33: 2026-09-03 | M33: https://tech.eu/2026/09/03/rightcharge-raises-ps500k-to-scale-fleet-ev-charging-payments-across-europe | N33: Emerging writer | O33: 2026-07 | P33: Posts a few times a year with some humour: an April Fools 'former CEO resigns' post (1 Apr 2025), how his team uses AI (Jun 2025), Visa partnership (Jul 2026). | Q33: 50 | R33: =IF(Q33>=60,"Priority",IF(Q33>=40,"Warm","Nurture")) | S33: Already has a voice and a sense of humour. The gap is cadence as he enters Europe. | T33: Hi Charlie, congrats on the raise and the Visa partnership. Fleet charging payments is a real headache for operators. Would be good to connect. | U33: Thanks for connecting, Charlie. You've got a voice on LinkedIn, it just shows up a few times a year. With Europe coming, is more regular posting worth it to you? | V33: Cadence; European fleet-manager audience; one recurring format. | W33: The 'resigns' post is an April Fools joke. He's still CEO. | X33: charlie.cook@rightcharge.co.uk | Y33: Rightcharge across Europe | Z33: Hi Charlie, Congrats on the raise and the Visa partnership. You've got a real voice on LinkedIn, humour included. It just shows up a few times a year, and European fleet managers don't know you yet. We help founders keep a weekly rhythm in their own voice without it eating their week. Open to a quick call? Prabal Gliped | LinkedIn personal branding for founders Not relevant? Reply "no" and I won't follow up. | AA33: Verified | AB33: Prospeo SMTP
A34: G033 | B34: 02 | C34: 2026-09-25 | D34: Koji Muto | E34: Co-founder & CEO | F34: Ki 13 (formerly Ki Hydrogen) | G34: UK | H34: London | I34: https://www.linkedin.com/in/kojimuto | J34: Yes | K34: $5M seed led by HICO, plus Innovate UK grants; rebranded to Ki 13 (Aug 2026) | L34: 2026-09 | M34: https://www.finsmes.com/2026/09/ki-13-raises-5m-in-seed-funding.html | N34: Milestone-only | O34: 2026-08 | P34: Business-plan competitions (2023), pitch video (21 comments), green hydrogen post (Apr 2024), rebrand (Aug 2026). Posts around milestones only. | Q34: 60 | R34: =IF(Q34>=60,"Priority",IF(Q34>=40,"Warm","Nurture")) | S34: Deep climate tech with a new name. The rebrand needs a founder narrative to stick. | T34: Hi Koji, congrats on the seed and the new Ki 13 name. Producing green hydrogen and biogenic CO2 together is a clever angle. Would be good to connect. | U34: Thanks for connecting, Koji. A rebrand plus a raise is a good moment to set the story. Is your own LinkedIn part of how you want to do that? | V34: Headline still reads Ki Hydrogen (check); milestone-only cadence; explainer series. | X34: koji@ki-hydrogen.com | Y34: Making Ki 13 stick | Z34: Hi Koji, Congrats on the seed and the new Ki 13 name. A rebrand only sticks when people hear the story behind it, and right now you post mainly at milestones. We help deep-tech founders build a steady LinkedIn presence that explains the science and the ambition. Worth 15 minutes to talk it through? Prabal Gliped | LinkedIn personal branding for founders Not relevant? Reply "no" and I won't follow up. | AA34: Verified | AB34: Prospeo BOUNCEBAN Domain is the old Ki Hydrogen name; still verified
A35: G034 | B35: 02 | C35: 2026-09-25 | D35: Francisco Vigo | E35: Co-founder & CEO | F35: geoSurge | G35: UK | H35: London | I35: https://www.linkedin.com/in/francisco-juan-vigo | J35: Yes | K35: $12M (EUR 10M) seed led by AlbionVC with Play Ventures | L35: 2026-07-03 | M35: https://www.uktech.news/ai/ai-search-visibility-startup-geosurge-scores-9-4m-round-20260703 | N35: Company-page voice | O35: 2025-12 | P35: One own post indexed (Dec 2025, launch). The company page and London Stock Exchange's The Stage feature him (Feb to Mar 2026). | Q35: 50 | R35: =IF(Q35>=60,"Priority",IF(Q35>=40,"Warm","Nurture")) | S35: geoSurge sells AI visibility. LinkedIn posts are one of the sources AI models cite, so his own visibility is on-message. | T35: Hi Francisco, congrats on the seed. Helping brands see how AI models describe them is a real new need. Would be good to connect. | U35: Thanks for connecting, Francisco. Odd question for someone in AI visibility. How visible do you want to be yourself? The company page is doing most of the talking. | V35: Company page vs founder feed; LinkedIn as an AI-citation source; weekly insight format. | X35: francisco@geosurge.ai | Y35: Your own AI visibility | Z35: Hi Francisco, Congrats on the seed. Odd one for someone in AI visibility: LinkedIn posts are one of the sources AI models draw on, and right now the geoSurge company page does most of the talking. We build founder brands on LinkedIn, so the founder shows up too. Open to a quick call? Prabal Gliped | LinkedIn personal branding for founders Not relevant? Reply "no" and I won't follow up. | AA35: Verified | AB35: Prospeo SMTP
A36: G035 | B36: 02 | C36: 2026-09-25 | D36: Callum Adamson | E36: Co-founder & CEO | F36: Applied Computing | G36: UK | H36: London | I36: https://www.linkedin.com/in/callumadamson | J36: Yes | K36: About EUR 17.4M led by KBR with Databricks Ventures; Orbital foundation model for energy operators | L36: 2026-07-15 | M36: https://techcrunch.com/2026/07/15/applied-computing-wants-to-give-oil-and-gas-operators-an-ai-model-for-the-entire-plant/ | N36: Went quiet | O36: 2025-05 | P36: Earlier career posts (Distributed, recruiting). A Fred Destin venture post (Nov 2024), an Applied Computing post (May 2025). The company page carries podcasts and Orbital since. | Q36: 50 | R36: =IF(Q36>=60,"Priority",IF(Q36>=40,"Warm","Nurture")) | S36: Energy operators buy from people they trust. A CEO voice on AI in refining is rare and credible. | T36: Hi Callum, congrats on the round with KBR and Databricks. A foundation model for a whole plant is a bold scope. Would be good to connect. | U36: Thanks for connecting, Callum. The Orbital story is mostly on the company page. Is building your own voice with energy operators on the list? | V36: 16-month gap; headline; operator-facing content line. | W36: Co-founder Dr Sam Tukra. | Y36: Orbital, in your words | Z36: Hi Callum, Congrats on the round with KBR and Databricks. Energy operators buy from people they trust, and a CEO voice on AI in refining is rare. Right now Orbital's story lives on the company page. We help founders build a steady LinkedIn presence aimed at operators. Worth a 15-minute call? Prabal Gliped | LinkedIn personal branding for founders Not relevant? Reply "no" and I won't follow up. | AA36: Not found
A37: G036 | B37: 02 | C37: 2026-09-25 | D37: Lestat McCree | E37: Co-founder & CEO | F37: Healf | G37: UK | H37: London | I37: https://www.linkedin.com/in/lestatmccree | J37: Yes | K37: Funding led by SEMCAP Beauty & Wellness; GBP 100M+ annualised revenue; expanding to Germany | L37: 2026-08-31 | M37: https://www.globenewswire.com/news-release/2026/08/31/3353334/0/en/semcap-beauty-wellness-leads-funding-round-for-healf.html | N37: Emerging writer | O37: 2026-01 | P37: Occasional essays (work-life balance, Jan 2026). A piece on AI adoption drew reaction posts from others (Jun 2026). Covered by The Times. Few own posts overall. | Q37: 50 | R37: =IF(Q37>=60,"Priority",IF(Q37>=40,"Warm","Nurture")) | S37: He writes well when he writes. International expansion plus press momentum is the moment to post weekly. | T37: Hi Lestat, congrats on the round and the Germany launch. GBP 100M with under 100 people is a remarkable ratio. Would be good to connect. | U37: Thanks for connecting, Lestat. Your AI adoption piece got people talking, but it's one of only a few posts. Is a steadier cadence worth it to you now? | V37: Cadence; German market framing; recurring founder essay. | W37: Co-founder Max Clarke. Big brand, so expect a comms team. | X37: lestat@healf.com | Y37: Healf, week by week | Z37: Hi Lestat, Congrats on the round and the Germany launch. Your AI adoption piece got people talking, but it's one of only a few posts. With international growth and press momentum, a steady rhythm compounds. We help founders keep a weekly LinkedIn presence in their own voice, alongside their comms team. Open to a quick call? Prabal Gliped | LinkedIn personal branding for founders Not relevant? Reply "no" and I won't follow up. | AA37: Verified | AB37: Prospeo SMTP
A38: G037 | B38: 02 | C38: 2026-09-25 | D38: Jon Steinback | E38: Co-founder & CEO | F38: Marker | G38: UK | H38: London | I38: https://www.linkedin.com/in/itsmejon | J38: Yes | K38: $13M seed led by Index Ventures with LocalGlobe; AI-native word processor | L38: 2026-07-09 | M38: https://tech.eu/2026/07/09/ai-writing-startup-co-founded-by-deepmind-creative-lead-raises-13m-seed-investment/ | N38: Already consistent | O38: 2026-07 | P38: Ex-DeepMind brand and creative lead. Launch posts (Apr and Jul 2026, 16 comments), 'AI writing app fighting AI slop' (Jul 2026). Writes his own posts. | Q38: 40 | R38: =IF(Q38>=60,"Priority",IF(Q38>=40,"Warm","Nurture")) | S38: He won't want a ghostwriter. Pitch strategy, distribution and time back, not writing. | T38: Hi Jon, congrats on the Marker launch. A word processor that writes with you, not for you, is a stance I agree with. Would be good to connect. | U38: Thanks for connecting, Jon. You clearly write your own posts, and should. Curious whether distribution and cadence are the harder part right now? | V38: Distribution not writing; cadence; audience of writers vs buyers. | W38: Low fit for ghostwriting. Only pitch strategy. | X38: jon@marker.page | Y38: Distribution, not writing | Z38: Hi Jon, Congrats on the Marker launch. You write your own posts and should. For most writer-founders the harder part is distribution: cadence, formats and reaching buyers, not only other writers. That's the part we can help with at Gliped, with you still doing the writing. Worth a 15-minute chat? Prabal Gliped | LinkedIn personal branding for founders Not relevant? Reply "no" and I won't follow up. | AA38: Verified | AB38: Prospeo SMTP
A39: G038 | B39: 02 | C39: 2026-09-25 | D39: Stephen Cowley | E39: Co-founder | F39: Pharosyn | G39: UK | H39: London | I39: https://www.linkedin.com/in/stephen-cowley-8960a0228 | J39: Yes | K39: $3M (EUR 2.5M) seed led by Moonfire Ventures, with Entrepreneurs First | L39: 2026-09-04 | M39: https://www.eu-startups.com/2026/09/uk-startup-pharosyn-raises-e2-5-million-for-pharma-competitive-intelligence-platform | N39: Emerging writer | O39: 2026-07 | P39: Two customer-story posts (Jun and Jul 2026) about onboarding calls and report quality. New to posting. | Q39: 40 | R39: =IF(Q39>=60,"Priority",IF(Q39>=40,"Warm","Nurture")) | S39: Pharma commercial teams are on LinkedIn. He's started posting customer stories; the gap is consistency. | T39: Hi Stephen, congrats on the seed. Competitive intelligence built into pharma commercial teams is an underserved corner. Would be good to connect. | U39: Thanks for connecting, Stephen. You've started posting customer stories, which is the right instinct. Is keeping that going every week realistic with everything else? | V39: Cadence; pharma buyer framing; customer-story series. | W39: Confirm who's CEO (Stephen or Joshua Hampson). | Y39: Keeping it weekly | Z39: Hi Stephen, Congrats on the seed. You've started posting customer stories on LinkedIn, which is the right instinct for reaching pharma commercial teams. The hard part is keeping it going every week. We help founders do exactly that, in their own voice. Open to a quick call? Prabal Gliped | LinkedIn personal branding for founders Not relevant? Reply "no" and I won't follow up. | AA39: Not found
A40: G039 | B40: 02 | C40: 2026-09-25 | D40: Steve Rimmer | E40: CEO | F40: Tickets for Good | G40: UK | I40: https://www.linkedin.com/search/results/people/?keywords=Steve%20Rimmer%20Tickets%20for%20Good | J40: No | K40: GBP 3.9M new funding; platform giving NHS workers, teachers and charity staff access to surplus event tickets | L40: 2026-09 | M40: https://www.finsmes.com/2026/09/tickets-for-good-raises-3-9m-in-new-funding.html | N40: Not indexed | P40: No confirmed own posts. A 2023 post about leaving a role may be his. The company page ran a founder interview (2025). | Q40: 50 | R40: =IF(Q40>=60,"Priority",IF(Q40>=40,"Warm","Nurture")) | S40: A social-impact brand with a feel-good story. Partners (venues, promoters) and members respond to the founder. | T40: Hi Steve, congrats on the new funding. Getting surplus tickets to key workers is a lovely model. Would be good to connect. | U40: Thanks for connecting, Steve. Tickets for Good has the kind of story people share. Is your own LinkedIn part of how you tell it to venues and promoters? | V40: Confirm profile; impact stories series; partner-facing content. | W40: Confirm profile and whether he's the founder. | Y40: Tickets for Good's story | Z40: Hi Steve, Congrats on the new funding. Getting surplus tickets to key workers is the kind of story people share, and venues and promoters respond to the person behind it. We build founder brands on LinkedIn around stories like yours. Worth a 15-minute call? Prabal Gliped | LinkedIn personal branding for founders Not relevant? Reply "no" and I won't follow up. | AA40: Not found
A41: G040 | B41: 02 | C41: 2026-09-25 | D41: Ismaeel Bashir | E41: Co-founder & CEO | F41: Expanse | G41: UK | H41: London / US | I41: https://www.linkedin.com/search/results/people/?keywords=Ismaeel%20Bashir%20Expanse | J41: No | K41: EUR 4.5M for a predictive AI infrastructure platform | L41: 2026-09 | M41: https://www.eu-startups.com/2026/09/u-s-and-u-k-based-expanse-raises-e4-5-million-for-predictive-ai-infrastructure-platform | N41: Not indexed | P41: No own posts indexed. | Q41: 50 | R41: =IF(Q41>=60,"Priority",IF(Q41>=40,"Warm","Nurture")) | S41: AI infrastructure is noisy. A founder with a clear point of view stands out to buyers and hires in both markets. | T41: Hi Ismaeel, congrats on the raise. Predictive AI infrastructure is a busy space. Following Expanse. Would be good to connect. | U41: Thanks for connecting, Ismaeel. With teams in the UK and US, is LinkedIn part of how you want buyers on both sides to know you? | V41: Confirm profile; point-of-view content line; dual-market framing. | W41: Confirm profile and base (UK or US). | Y41: Expanse on both sides | Z41: Hi Ismaeel, Congrats on the raise. AI infrastructure is noisy, and with teams in the UK and US you need buyers on both sides to recognise you. A clear founder point of view on LinkedIn does that. We build founder brands on LinkedIn, from positioning to weekly posts. Open to a quick call? Prabal Gliped | LinkedIn personal branding for founders Not relevant? Reply "no" and I won't follow up. | AA41: Not found
A42: G041 | B42: 02 | C42: 2026-09-25 | D42: Jason Liao | E42: Co-founder & CEO | F42: Mundo AI | G42: Canada | H42: Vancouver | I42: https://www.linkedin.com/search/results/people/?keywords=Jason%20Liao%20Mundo%20AI | J42: No | K42: $20M Series A led by GreatPoint Ventures plus a $4M seed; YC; data for AI perception (audio, video) | L42: 2026-09-02 | M42: https://betakit.com/mundo-announces-24-million-usd-to-help-tackle-ais-next-frontier/ | N42: Not indexed | P42: No own posts indexed. Co-founder Garreth Lee posted the founding news (Feb 2025). | Q42: 50 | R42: =IF(Q42>=60,"Priority",IF(Q42>=40,"Warm","Nurture")) | S42: AI data infrastructure buyers (labs, model teams) need to trust the team. A CEO voice on perception data is thin in the market. | T42: Hi Jason, congrats on the Series A. Training data for AI beyond text is where a lot of the next gains are. Would be good to connect. | U42: Thanks for connecting, Jason. Most of Mundo's story online comes from your co-founders or press. Is your own voice something you want to build now? | V42: Confirm profile; research-to-buyer content line; hiring angle. | W42: Confirm profile. | Y42: Mundo's founder voice | Z42: Hi Jason, Congrats on the Series A. Most of Mundo's story online comes from press and your co-founders. Model teams and top researchers want to hear from the CEO too. We build founder brands on LinkedIn for technical founders, aimed at buyers and hires. Worth a 15-minute call? Prabal Gliped | LinkedIn personal branding for founders Not relevant? Reply "no" and I won't follow up. | AA42: Not found
A43: G042 | B43: 02 | C43: 2026-09-25 | D43: David S. Bennahum | E43: Co-founder & CEO | F43: Onix | G43: Canada | H43: Montreal | I43: https://www.linkedin.com/in/dbennahum | J43: Yes | K43: $5M pre-seed led by Alpha Edison; AI versions of health and wellness experts | L43: 2026-09-10 | M43: https://betakit.com/onix-raises-5-million-usd-to-create-ai-library-of-health-and-wellness-experts/ | N43: Emerging writer | O43: 2025-09 | P43: Posts every few months (gaming, Web3, NotebookLM, a Delaware court post, Onix launch Sep 2025). Former WIRED contributing editor. | Q43: 40 | R43: =IF(Q43>=60,"Priority",IF(Q43>=40,"Warm","Nurture")) | S43: He can write. His product is built on experts' voices, so a strong founder voice fits. Pitch cadence and strategy. | T43: Hi David, congrats on the pre-seed. AI built on licensed expert knowledge instead of the average internet is a clear stance. Would be good to connect. | U43: Thanks for connecting, David. Onix is built on experts owning their voice. Yours shows up every few months. Is a steadier cadence worth it with the raise done? | V43: Cadence; Onix positioning in headline; expert-partner content. | W43: Writer himself, so pitch strategy over ghostwriting. | X43: david@onixai.ai | Y43: Onix and your voice | Z43: Hi David, Congrats on the pre-seed. Onix is built on experts owning their voice. Yours shows up on LinkedIn every few months. You can clearly write, so this isn't about ghostwriting. We help founders with cadence, formats and distribution. Open to a quick call? Prabal Gliped | LinkedIn personal branding for founders Not relevant? Reply "no" and I won't follow up. | AA43: Verified | AB43: Prospeo SMTP Prospeo lists Onix HQ as Montreal (sheet says Ottawa)
A44: G043 | B44: 02 | C44: 2026-09-25 | D44: Kyle Braatz | E44: Co-founder & CEO | F44: Fullscript | G44: Canada | H44: Ottawa | I44: https://www.linkedin.com/in/braatzy | J44: Yes | K44: Investment from L Catterton and Altas Partners | L44: 2026-09 | M44: https://www.finsmes.com/2026/09/fullscript-receives-investment.html | N44: Company-news voice | O44: 2026-02 | P44: Posts two to four times a year: labs launch, Fullscript Wrapped, engineering 'Builder's Corner' (Feb 2026), the $300M raise (2021, 43 comments). Ottawa CEO of the Year 2022. | Q44: 50 | R44: =IF(Q44>=60,"Priority",IF(Q44>=40,"Warm","Nurture")) | S44: Large company with a practitioner audience. A CEO point of view on integrative health would lift a company-news feed. | T44: Hi Kyle, congrats on the L Catterton and Altas investment. Fullscript's growth out of Ottawa has been fun to follow. Would be good to connect. | U44: Thanks for connecting, Kyle. Your feed is mostly Fullscript updates. Is a stronger personal point of view something you'd want now? | V44: Company-news only; practitioner-facing content line; cadence. | W44: Likely has an in-house comms team. Pitch executive content support. | X44: kyle.braatz@fullscript.com | Y44: Fullscript's CEO voice | Z44: Hi Kyle, Congrats on the L Catterton and Altas investment. Your LinkedIn is mostly Fullscript updates. Practitioners and partners would follow a stronger CEO point of view on where integrative health is going. We support executive LinkedIn presence alongside in-house comms teams. Worth a 15-minute call? Prabal Gliped | LinkedIn personal branding for founders Not relevant? Reply "no" and I won't follow up. | AA44: Verified | AB44: Prospeo BOUNCEBAN
A45: G044 | B45: 02 | C45: 2026-09-25 | D45: LP Maurice | E45: Co-founder & CEO | F45: Busbud / Terra Mobility | G45: Canada | H45: Montreal | I45: https://www.linkedin.com/in/lmaurice | J45: Yes | K45: US$40M financing from Vista Credit Partners and launch of parent company Terra Mobility | L45: 2026-08 | M45: https://www.finsmes.com/2026/08/busbud-raises-40m-in-funding.html | N45: Went quiet | O45: 2024-05 | P45: Strong engagement when he posts: $11M raise (60 comments), LatAm (64 comments), Betterez deal, Africa B2B (May 2024). Nothing indexed since. | Q45: 60 | R45: =IF(Q45>=60,"Priority",IF(Q45>=40,"Warm","Nurture")) | S45: He knows posting works. A new parent company is the moment to restart. | T45: Hi LP, congrats on the financing and the Terra Mobility launch. Busbud's reach into LatAm and Africa is impressive. Would be good to connect. | U45: Thanks for connecting, LP. Your LatAm and Africa posts got real engagement, then things went quiet. With Terra Mobility launching, is restarting on the list? | V45: Two-year gap; Terra Mobility not in headline (check); global mobility content line. | W45: Montreal. Offer French. | Y45: Terra Mobility, restarted | Z45: Hi LP, Congrats on the financing and the Terra Mobility launch. Your LatAm and Africa posts drew 60+ comments, then your LinkedIn went quiet in 2024. A new parent company is the moment to restart. We help founders get back to a steady rhythm without writing every post themselves. Open to a quick call? Prabal Gliped | LinkedIn personal branding for founders Not relevant? Reply "no" and I won't follow up. | AA45: Not found
A46: G045 | B46: 02 | C46: 2026-09-25 | D46: Stéphane Garneau | E46: President & CEO | F46: Micrologic | G46: Canada | H46: Québec City | I46: https://www.linkedin.com/in/sgarneau | J46: Yes | K46: $45M from Fonds de solidarité FTQ and Investissement Québec for sovereign cloud services | L46: 2026 | M46: https://betakit.com/micrologic-raises-45-million-for-sovereign-cloud-services/ | N46: Went quiet | O46: 2024-05 | P46: Posts in French on sovereign cloud, culture and HR (2022 to 2024), a 2023 year-in-review, CEO of the Year 2023. Nothing indexed since May 2024. | Q46: 50 | R46: =IF(Q46>=60,"Priority",IF(Q46>=40,"Warm","Nurture")) | S46: Sovereign cloud is a live policy topic. A CEO voice in French and English positions Micrologic with public-sector buyers. | T46: Bonjour Stéphane, félicitations pour le financement. Le cloud souverain est un sujet de plus en plus important. Au plaisir d'échanger. | U46: Merci pour la connexion, Stéphane. Vous publiiez régulièrement sur le cloud souverain, puis plus rien depuis 2024. Est-ce que reprendre fait partie des plans? | V46: Two-year gap; bilingual content; public-sector buyer framing. | W46: Confirm the funding date before sending. Write in French. | X46: sgarneau@micrologic.ca | Y46: Micrologic et le cloud souverain | Z46: Bonjour Stéphane, Félicitations pour le financement. Le cloud souverain est un sujet d'actualité, et vous publiiez régulièrement là-dessus jusqu'en 2024. Une voix de PDG, en français et en anglais, positionne Micrologic auprès des acheteurs publics. Chez Gliped, nous bâtissons la présence LinkedIn des dirigeants. Un appel de 15 minutes la semaine prochaine? Prabal Gliped | Personal branding LinkedIn pour dirigeants Pas pertinent? Répondez « non » et je ne vous relancerai pas. | AA46: Verified | AB46: Prospeo SMTP Prospeo places Micrologic in Québec City (sheet says Montreal)
A47: G046 | B47: 02 | C47: 2026-09-25 | D47: Sanja Fidler | E47: Co-founder & CEO | F47: Veeda AI | G47: Canada | H47: Toronto | I47: https://www.linkedin.com/in/sanja-fidler-2846a1a | J47: Yes | K47: $90M+ seed from Khosla Ventures and Radical Ventures; left NVIDIA (VP AI research) to found Veeda | L47: 2026-08 | M47: https://www.finsmes.com/2026/08/veeda-innovation-raises-over-90m-in-seed-funding.html | N47: Research voice | O47: 2025-12 | P47: Posts research releases from NVIDIA a few times a year (40 comments on one in Sep 2025). Last indexed Dec 2025, before Veeda. | Q47: 50 | R47: =IF(Q47>=60,"Priority",IF(Q47>=40,"Warm","Nurture")) | S47: From NVIDIA researcher to founder. Hiring world-class researchers depends on her voice. | T47: Hi Sanja, congrats on launching Veeda. World models for physical reality is a big bet with the right team behind it. Would be good to connect. | U47: Thanks for connecting, Sanja. Your feed has been NVIDIA research. Veeda is a new story. Is your LinkedIn part of how you want to recruit for it? | V47: Headline and feed still NVIDIA (check); founder narrative; research hiring content. | W47: High profile. Low odds, high value. | Y47: Veeda, from NVIDIA | Z47: Hi Sanja, Congrats on launching Veeda. Your LinkedIn has been NVIDIA research. Veeda is a new story, and the researchers you want to hire will look for it in your feed. We help technical founders build a founder narrative on LinkedIn without pulling them away from the work. Worth a short call? Prabal Gliped | LinkedIn personal branding for founders Not relevant? Reply "no" and I won't follow up. | AA47: Not found
A48: G047 | B48: 02 | C48: 2026-09-25 | D48: Kimia Hamidi | E48: Co-founder & CEO | F48: NationGraph | G48: Canada | H48: Toronto / SF | I48: https://www.linkedin.com/in/hkimia | J48: Yes | K48: $18M Series A led by Menlo Ventures (announced Feb 2026; older than 90 days) | L48: 2026-02-25 | M48: https://www.axios.com/pro/enterprise-software-deals/2026/02/25/govtech-nationgraph-18-million-menlo | N48: Emerging writer | O48: 2026-04 | P48: Product and fundraise posts: Feb 2025 launch (82 comments), $4.5M (Aug 2025), product post (Apr 2026). | Q48: 20 | R48: =IF(Q48>=60,"Priority",IF(Q48>=40,"Warm","Nurture")) | S48: Govtech sales need trust with public-sector buyers. His posts do well but come a few times a year. | T48: Hi Kimia, NationGraph's public-sector data work is interesting to follow. Would be good to connect. | U48: Thanks for connecting, Kimia. Your launch post drew a lot of discussion. Is a regular cadence worth building now? | V48: Cadence; public-sector buyer content. | W48: Nurture. Trigger is older than 90 days. Revisit on the next trigger. | X48: kimia@nationgraph.com | Y48: NationGraph, steadily | Z48: Hi Kimia, Your NationGraph launch post drew a lot of discussion. Since then you post a few times a year. Public-sector buyers take time to trust a vendor, and a steady founder voice shortens that. We help founders keep a regular LinkedIn rhythm in their own voice. Open to a quick call when timing suits? Prabal Gliped | LinkedIn personal branding for founders Not relevant? Reply "no" and I won't follow up. | AA48: Verified | AB48: Prospeo SMTP
A49: G048 | B49: 02 | C49: 2026-09-25 | D49: Darren Hill | E49: CEO | F49: Legio | G49: Canada | H49: Toronto | I49: https://www.linkedin.com/search/results/people/?keywords=Darren%20Hill%20Legio | J49: No | K49: $5M seed from Klass Capital; AI safety and security operations for higher education | L49: 2026-08 | M49: https://www.finsmes.com/2026/08/legio-raises-5m-in-seed-funding.html | N49: Not indexed | P49: Several profiles share the name. One 'co-founder' Darren Hill posts on tech adoption, but it's not confirmed. | Q49: 50 | R49: =IF(Q49>=60,"Priority",IF(Q49>=40,"Warm","Nurture")) | S49: University safety leaders buy on trust. A founder voice on campus safety sets Legio apart. | T49: Hi Darren, congrats on the seed. Safety operations built for campuses is a focused bet. Would be good to connect. | U49: Thanks for connecting, Darren. Campus safety leaders are a tight community. Is LinkedIn part of how you want to reach them? | V49: Confirm profile; higher-ed buyer content line. | W49: Confirm profile. | Y49: Legio and campus leaders | Z49: Hi Darren, Congrats on the seed. Campus safety leaders are a tight community, and they buy on trust. A founder voice on LinkedIn about safety operations sets Legio apart. We build founder brands on LinkedIn aimed at the buyers that matter. Worth a 15-minute call? Prabal Gliped | LinkedIn personal branding for founders Not relevant? Reply "no" and I won't follow up. | AA49: Not found
A50: G049 | B50: 02 | C50: 2026-09-25 | D50: Kelvin Cui | E50: Co-founder & CEO | F50: Peripheral | G50: Canada | H50: Toronto | I50: https://www.linkedin.com/search/results/people/?keywords=Kelvin%20Cui%20Peripheral | J50: No | K50: $8.7M seed led by Inovia Capital and Deloitte Ventures, with Khosla Ventures; AI spatial intelligence for live sports media | L50: 2026-08 | M50: https://www.finsmes.com/2026/08/peripheral-raises-8-7m-in-seed-funding.html | N50: Not indexed | P50: No recent own posts indexed. | Q50: 50 | R50: =IF(Q50>=60,"Priority",IF(Q50>=40,"Warm","Nurture")) | S50: Sports media is a visual, shareable space. A founder feed with product clips does double duty as marketing. | T50: Hi Kelvin, congrats on the seed. Spatial intelligence for live sports is a fun problem. Would be good to connect. | U50: Thanks for connecting, Kelvin. Your product is very visual, which suits LinkedIn. Is founder content part of the go-to-market? | V50: Confirm profile; product-clip content series. | W50: Confirm profile. Co-founder Mustafa Khan. | Y50: Peripheral on LinkedIn | Z50: Hi Kelvin, Congrats on the seed. Your product is very visual, which suits LinkedIn. Founder posts with product clips double as marketing to sports media buyers. We build founder brands on LinkedIn, from positioning to weekly posts. Open to a quick call? Prabal Gliped | LinkedIn personal branding for founders Not relevant? Reply "no" and I won't follow up. | AA50: Not found
A51: G050 | B51: 02 | C51: 2026-09-25 | D51: Sumit Ajwani | E51: Founder & CEO | F51: MakeOS (Makers) | G51: Canada | H51: Toronto | I51: https://www.linkedin.com/in/sumitproducer | J51: Yes | K51: Launched MakeOS, an AI workspace for producers | L51: 2026-08-17 | M51: https://lbbonline.com/news/sumit-ajwani-makeos-ai-workspace-producers | N51: Not indexed | P51: Profile found, but no own posts indexed. The Makers company page announced MakeOS. | Q51: 50 | R51: =IF(Q51>=60,"Priority",IF(Q51>=40,"Warm","Nurture")) | S51: Producers and agencies are a LinkedIn-native audience. A founder voice on AI in production fits. | T51: Hi Sumit, congrats on launching MakeOS. An AI workspace built for producers is overdue. Would be good to connect. | U51: Thanks for connecting, Sumit. The launch is on the Makers page. Your own feed is quiet. Is that something you want to change for MakeOS? | V51: Founder feed silent; producer-audience content line. | W51: Launch, not a funding round. Check whether there was a raise. | X51: sumit@getmakeos.com | Y51: MakeOS, founder-led | Z51: Hi Sumit, Congrats on launching MakeOS. The launch is on the Makers page, but your own feed is quiet. Producers and agencies live on LinkedIn, and they follow people. We build founder brands on LinkedIn around launches like this one. Worth a 15-minute call? Prabal Gliped | LinkedIn personal branding for founders Not relevant? Reply "no" and I won't follow up. | AA51: Verified | AB51: Prospeo SMTP
A52: G051 | B52: 02 | C52: 2026-09-25 | D52: Baker Shogry | E52: Co-founder & CEO | F52: Light | G52: US | I52: https://www.linkedin.com/in/bakershogry | J52: Yes | K52: $46M Series A; white-label retail electricity platform | L52: 2026-09 | M52: https://www.finsmes.com/2026/09/light-raises-46m-in-series-a-funding.html | N52: Near-silent | O52: 2021-12 | P52: One own post indexed (Plaid FinRise, Dec 2021). Co-launched a heat pump project with Calvin French-Owen (2022). | Q52: 50 | R52: =IF(Q52>=60,"Priority",IF(Q52>=40,"Warm","Nurture")) | S52: Energy is a trust category. A $46M Series A with a near-silent founder is a clear gap. | T52: Hi Baker, congrats on the Series A. Letting any brand launch its own electricity plan is a clever wedge. Would be good to connect. | U52: Thanks for connecting, Baker. You've been pretty quiet on here. With the Series A done, is building a voice in energy something you'd want? | V52: Near-silent feed; headline; energy-transition content line. | Y52: Light's founder voice | Z52: Hi Baker, Congrats on the $46M Series A. Energy is a trust category, and your LinkedIn has been nearly silent. Brands deciding whether to launch their own electricity plan will look you up. We build founder brands on LinkedIn, from positioning to weekly posts. Open to a quick call next week? Prabal Gliped | LinkedIn personal branding for founders Not relevant? Reply "no" and I won't follow up. | AA52: Not checked
A53: G052 | B53: 02 | C53: 2026-09-25 | D53: Guy Shahar | E53: Co-founder & CEO | F53: Blee | G53: US | I53: https://www.linkedin.com/in/guy-shahar | J53: Yes | K53: $20M Series A; AI marketing compliance; grew 10x in 2025 | L53: 2026-09-08 | M53: https://www.finsmes.com/2026/09/blee-raises-20m-in-series-a-funding.html | N53: Already consistent | O53: 2026-09 | P53: Roughly monthly since 2025: NerdWallet partnership, Figma plugin, 10x growth hiring post, case studies, Series A (8 Sep 2026). | Q53: 40 | R53: =IF(Q53>=60,"Priority",IF(Q53>=40,"Warm","Nurture")) | S53: Already posting. Pitch reach and time back as the company scales. | T53: Hi Guy, congrats on the Series A. The NerdWallet partnership was a strong proof point for Blee. Would be good to connect. | U53: Thanks for connecting, Guy. You post more consistently than most founders. How much of your week does it take right now? | V53: Reach vs frequency; repurposing; compliance-leader audience. | W53: Active in the last 30 days. | Y53: Your weekly hours back | Z53: Hi Guy, Congrats on the Series A. You post more consistently than most founders. That usually costs hours a week, right when Blee is scaling. We keep founders' voice and rhythm while taking the writing and repurposing off their plate. Worth 15 minutes to see what you'd get back? Prabal Gliped | LinkedIn personal branding for founders Not relevant? Reply "no" and I won't follow up. | AA53: Not checked
A54: G053 | B54: 02 | C54: 2026-09-25 | D54: Michael LaFramboise | E54: Co-founder & CEO | F54: Aurelius Systems | G54: US | H54: San Francisco | I54: https://www.linkedin.com/in/michael-laframboise | J54: Yes | K54: $40M Series A; directed-energy counter-drone systems | L54: 2026-08-05 | M54: https://www.finsmes.com/2026/08/aurelius-systems-raises-40m-in-series-a-funding.html | N54: Emerging writer | O54: 2026-04 | P54: Posts every one to three months: 'our startup shoots down drones with lasers' (Feb 2025), DragonFire (Jul 2025), careers, Archimedes manufacturing (Apr 2026). | Q54: 40 | R54: =IF(Q54>=60,"Priority",IF(Q54>=40,"Warm","Nurture")) | S54: Defence tech buyers and recruits follow founders. He has the voice; cadence and reach are the gap. | T54: Hi Michael, congrats on the Series A. US-made directed energy for counter-drone is a timely bet. Would be good to connect. | U54: Thanks for connecting, Michael. Your posts on defence tech get attention when they land. Is going weekly worth it for hiring and customers? | V54: Cadence; defence buyer content; hiring series. | W54: Defence content has rules. Check export and ITAR boundaries. | Y54: Aurelius, every week | Z54: Hi Michael, Congrats on the $40M Series A. Your defence-tech posts get attention when they land, every month or two. Weekly would help both hiring and customers. We help founders keep that rhythm in their own voice, with care around what defence content can say. Open to a quick call? Prabal Gliped | LinkedIn personal branding for founders Not relevant? Reply "no" and I won't follow up. | AA54: Not checked
A55: G054 | B55: 02 | C55: 2026-09-25 | D55: Noah Schochet | E55: Co-founder & CEO | F55: TerraFirma | G55: US | H55: Austin | I55: https://www.linkedin.com/in/noahschochet | J55: Yes | K55: $100M+ Series A led by Kleiner Perkins; tech-enabled construction | L55: 2026-07-14 | M55: https://www.finsmes.com/2026/07/terrafirma-raises-100m-in-series-a-funding.html | N55: Emerging writer | O55: 2026-07 | P55: Opinion posts every two to three months in 2026: 'stop shipping software' (Feb), 'the future is already here' (Apr), Series A (Jul). | Q55: 40 | R55: =IF(Q55>=60,"Priority",IF(Q55>=40,"Warm","Nurture")) | S55: A strong contrarian point of view on construction. More frequency turns it into a category voice. | T55: Hi Noah, congrats on the Series A. Saw your 'stop shipping software' post. Not a line I expected from a construction company. Would be good to connect. | U55: Thanks for connecting, Noah. Your posts have a clear point of view. They come every couple of months. Would going weekly change anything for hiring or deals? | V55: Cadence; construction-buyer framing; recurring format. | Y55: TerraFirma, weekly | Z55: Hi Noah, Congrats on the Series A. You post with a clear point of view every couple of months. Weekly turns that into a category voice for construction. We help founders keep a weekly rhythm in their own voice without it eating their week. Worth a 15-minute call? Prabal Gliped | LinkedIn personal branding for founders Not relevant? Reply "no" and I won't follow up. | AA55: Not checked
A56: G055 | B56: 02 | C56: 2026-09-25 | D56: Christian Bhatia Ondaatje | E56: CEO | F56: Aranya | G56: US | I56: https://www.linkedin.com/in/christianondaatje | J56: Yes | K56: $11M; clusterdOS turns bare metal into production clusters in under 48 hours | L56: 2026-09 | M56: https://www.finsmes.com/2026/09/aranya-raises-11m-in-funding.html | N56: Near-silent | O56: 2024-12 | P56: One own post indexed (Dec 2024). Company announced 'out of stealth' (Apr 2026). Co-founder Aryamika posts more. | Q56: 50 | R56: =IF(Q56>=60,"Priority",IF(Q56>=40,"Warm","Nurture")) | S56: AI infrastructure buyers need to trust the CEO. Coming out of stealth plus a raise is the moment. | T56: Hi Christian, congrats on the raise. Bare metal to production clusters in 48 hours is a strong claim. Would be good to connect. | U56: Thanks for connecting, Christian. Aranya's story is mostly on the company page and your co-founder's feed. Is your own voice something you want to build now? | V56: Near-silent; headline; infra-buyer content. | W56: Co-founders Aryamika Bhatia Ondaatje and Sasivarnan K S. | Y56: Aranya out of stealth | Z56: Hi Christian, Congrats on the raise. Aranya's story is on the company page and your co-founder's feed. Infrastructure buyers want to hear from the CEO, and yours has been quiet since 2024. We build founder brands on LinkedIn for technical founders. Open to a quick call? Prabal Gliped | LinkedIn personal branding for founders Not relevant? Reply "no" and I won't follow up. | AA56: Not checked
A57: G056 | B57: 02 | C57: 2026-09-25 | D57: Kaitlyn Albertoli | E57: Co-founder & CEO | F57: Buzz Solutions | G57: US | H57: Palo Alto | I57: https://www.linkedin.com/in/kaitlyn-claire-albertoli | J57: Yes | K57: $20M Series A led by S3 Ventures; grid inspection AI | L57: 2026-08-04 | M57: https://www.finsmes.com/2026/08/buzz-solutions-raises-20m-in-series-a-funding.html | N57: Milestone-only | O57: 2026-08 | P57: Posts at milestones and awards: $3.3M round (2022), AI trends (Jan 2024), women in STEM, grid edge (Jan 2025), Series A (Aug 2026). Media interviews (Schwab, Jul 2026). | Q57: 40 | R57: =IF(Q57>=60,"Priority",IF(Q57>=40,"Warm","Nurture")) | S57: Utilities are a conservative buyer. A steady CEO voice on grid reliability builds the trust that press alone doesn't. | T57: Hi Kaitlyn, congrats on the Series A. AI for grid inspection matters more every summer. Would be good to connect. | U57: Thanks for connecting, Kaitlyn. You post at big moments and do interviews well. Is a steadier cadence for utility buyers worth it now? | V57: Cadence; utility-buyer content line; interview repurposing. | W57: Forbes 30 Under 30 with co-founder Vikhyat Chaudhry. | Y57: Buzz and utility buyers | Z57: Hi Kaitlyn, Congrats on the Series A. You post at big moments and do interviews well. Utilities are conservative buyers, and a steady CEO voice on grid reliability builds trust that press alone doesn't. We help founders turn interviews and milestones into a weekly LinkedIn rhythm. Worth a 15-minute call? Prabal Gliped | LinkedIn personal branding for founders Not relevant? Reply "no" and I won't follow up. | AA57: Not checked
A58: G057 | B58: 02 | C58: 2026-09-25 | D58: Oscar Levy | E58: Co-founder & CEO | F58: River Markets | G58: US | I58: https://www.linkedin.com/in/oscar-levy | J58: Yes | K58: $8.5M seed led by Haun Ventures with YC and Coinbase Ventures; prediction market prime brokerage | L58: 2026-08-11 | M58: https://fortune.com/2026/08/11/exclusive-river-markets-seed-round-prediction-market-trading-tools-institutions/ | N58: Emerging writer | O58: 2026-06 | P58: New to posting: launch story (May 2026), a SpaceX bets post (Jun 2026, 10 comments). Interviews on prediction-market infrastructure. | Q58: 40 | R58: =IF(Q58>=60,"Priority",IF(Q58>=40,"Warm","Nurture")) | S58: Prediction markets are a hot topic. An early, steady voice for institutions sets the category leader. | T58: Hi Oscar, congrats on the seed. Prime brokerage for prediction markets is early and interesting. Would be good to connect. | U58: Thanks for connecting, Oscar. You've just started posting. Is keeping it weekly realistic with a new raise to deploy? | V58: Cadence; institutional audience framing; market-commentary series. | W58: Co-founder CTO Antonin Parrot. | Y58: River Markets, weekly | Z58: Hi Oscar, Congrats on the seed. You've just started posting about prediction markets. The founder who shows up every week for institutions becomes the category voice. We help founders keep that rhythm while they deploy a new round. Open to a quick call? Prabal Gliped | LinkedIn personal branding for founders Not relevant? Reply "no" and I won't follow up. | AA58: Not checked
A59: G058 | B59: 02 | C59: 2026-09-25 | D59: Adel Badiri | E59: CEO | F59: Foundational Industries | G59: US | I59: https://www.linkedin.com/search/results/people/?keywords=Adel%20Badiri%20Foundational%20Industries | J59: No | K59: $25M seed led by BoxGroup and Zigg Ventures; AI-native US factories for data centre hardware | L59: 2026-08-05 | M59: https://www.finsmes.com/2026/08/foundational-industries-raises-25m-in-seed-funding.html | N59: Not indexed | P59: No own posts indexed. | Q59: 50 | R59: =IF(Q59>=60,"Priority",IF(Q59>=40,"Warm","Nurture")) | S59: American reshoring plus AI manufacturing is a strong narrative. A quiet founder is leaving it on the table. | T59: Hi Adel, congrats on the seed. AI-native factories for data centre hardware in the US is a timely bet. Would be good to connect. | U59: Thanks for connecting, Adel. Reshoring and AI manufacturing is a story people want to follow. Is your own LinkedIn part of how you tell it? | V59: Confirm profile; build-in-public factory series; hiring. | W59: Confirm profile. | Y59: Foundational's story | Z59: Hi Adel, Congrats on the $25M seed. American reshoring plus AI-native factories is a story people want to follow, and right now you're not telling it on LinkedIn. We build founder brands on LinkedIn, from positioning to weekly posts, including build-in-public. Worth a 15-minute call? Prabal Gliped | LinkedIn personal branding for founders Not relevant? Reply "no" and I won't follow up. | AA59: Not checked
A60: G059 | B60: 02 | C60: 2026-09-25 | D60: David Lawrence | E60: Co-founder & CEO | F60: Blue Voice | G60: US | H60: Boston | I60: https://www.linkedin.com/search/results/people/?keywords=David%20Lawrence%20Blue%20Voice | J60: No | K60: $6M led by SignalFire and Las Olas VC; AI policy guidance for police officers in 225 agencies | L60: 2026-08-31 | M60: https://techcrunch.com/2026/08/31/harvard-law-dropout-raises-6m-for-blue-voice-to-build-a-harvey-for-police-officers/ | N60: Not indexed | P60: No own posts indexed. TechCrunch framed him as a Harvard Law dropout. | Q60: 50 | R60: =IF(Q60>=60,"Priority",IF(Q60>=40,"Warm","Nurture")) | S60: Public-safety buyers are cautious. A founder who explains why he left law school to build this earns trust with chiefs and councils. | T60: Hi David, congrats on the raise. Real-time policy guidance for officers is a thoughtful use of AI. Would be good to connect. | U60: Thanks for connecting, David. Your reason for starting Blue Voice is a story police leaders would read. Is LinkedIn part of how you want to reach them? | V60: Confirm profile; origin story; agency-leader content line. | W60: Confirm profile. Sensitive topic, so keep it measured. | Y60: Blue Voice's why | Z60: Hi David, Congrats on the raise. Why you left law school to build Blue Voice is a story police leaders and councils would read, and it builds the trust public-safety buyers need. We build founder brands on LinkedIn, carefully and in a measured tone. Open to a quick call? Prabal Gliped | LinkedIn personal branding for founders Not relevant? Reply "no" and I won't follow up. | AA60: Not checked
A61: G060 | B61: 02 | C61: 2026-09-25 | D61: Ian McInnis | E61: Co-founder | F61: Multiplier | G61: US | H61: New York | I61: https://www.linkedin.com/search/results/people/?keywords=Ian%20McInnis%20Multiplier | J61: No | K61: $6M seed; moved HQ to Midtown East, New York | L61: 2026-08 | M61: https://www.finsmes.com/2026/08/multiplier-raises-usd6m-in-seed-funding.html | N61: Not indexed | P61: No own posts indexed. Co-founder Ryan Winkler posted the launch (May 2026). | Q61: 50 | R61: =IF(Q61>=60,"Priority",IF(Q61>=40,"Warm","Nurture")) | S61: New York seed-stage team. The founder who posts gets the first hires and the first customers' attention. | T61: Hi Ian, congrats on the seed and the move to New York. Following what Multiplier is building. Would be good to connect. | U61: Thanks for connecting, Ian. Ryan's been the voice of the launch so far. Is building your own presence part of the plan? | V61: Confirm profile and role; founder-voice split between co-founders. | W61: Confirm profile and who the CEO is. Co-founders Ben Finch and Ryan Winkler. | Y61: Multiplier in New York | Z61: Hi Ian, Congrats on the seed and the move to New York. Ryan has been the voice of the launch so far. At seed stage, the founder who posts gets the first hires' and first customers' attention. We build founder brands on LinkedIn, from positioning to weekly posts. Worth a 15-minute call? Prabal Gliped | LinkedIn personal branding for founders Not relevant? Reply "no" and I won't follow up. | AA61: Not checked
A62: G061 | B62: 03 | C62: 2026-10-02 | D62: Salem Abu-Hammour | E62: Co-founder & CEO | F62: erad | G62: MENA | H62: Riyadh | I62: https://www.linkedin.com/in/salem-abu-hammour-8717a6100 | J62: Yes | K62: $22M Series A led by MEVP with 500 Global, SVC (SME working-capital fintech) | L62: 2026-09 | M62: https://www.wamda.com/2026/09/saudi-fintech-erad-raises-22-million-series-led-mevp | N62: Went quiet | O62: 2022-09 | P62: One own post indexed: the erad pre-seed announcement (Sep 2022). Nothing indexed from the seed or this Series A. | Q62: 50 | R62: =IF(Q62>=60,"Priority",IF(Q62>=40,"Warm","Nurture")) | S62: SME lending runs on trust. A CEO who explains how erad underwrites Saudi SMEs gives founders and banks a reason to call. | T62: Hi Salem, congrats on the Series A. Working capital for Saudi SMEs is a gap a lot of founders feel. Would be good to connect. | U62: Thanks for connecting, Salem. The last post I could find from you is the pre-seed in 2022. With the Series A done, is LinkedIn part of how you want to reach SME owners? | V62: Quiet since 2022; no view on SME credit in KSA; headline and featured section not selling erad. | W62: Co-founder posts may carry the story; check before sending. | X62: salem@erad.co | Y62: erad after the Series A | Z62: Hi Salem, Congrats on the $22M Series A. The last post I could find from you is the pre-seed in 2022. SME owners and bank partners now look you up before they look at erad. We build founder brands on LinkedIn, from positioning to weekly posts. Worth a 15-minute call next week? Prabal Gliped | LinkedIn personal branding for founders Not relevant? Reply "no" and I won't follow up. | AA62: Verified | AB62: Prospeo SMTP Co-Founder & CEO
A63: G062 | B63: 03 | C63: 2026-10-02 | D63: Mohammad Raafi Hossain | E63: Co-founder & CEO | F63: Fasset | G63: MENA | H63: Dubai | I63: https://www.linkedin.com/in/raafihossain | J63: Yes | K63: $68M Series C at $1B valuation led by SBI Group (stablecoin neobank) | L63: 2026-08 | M63: https://www.finsmes.com/2026/08/fasset-raises-68m-in-series-c-funding.html | N63: Went quiet | O63: 2021-05 | P63: One own post indexed, from May 2021. The Series C and unicorn valuation were covered by press, not on the founder's own LinkedIn as far as indexing shows. | Q63: 50 | R63: =IF(Q63>=60,"Priority",IF(Q63>=40,"Warm","Nurture")) | S63: A $1B stablecoin neobank needs regulators, partners and users to trust the person behind it. A founder voice is the cheapest trust signal Fasset has. | T63: Hi Raafi, congrats on the Series C. A licensed stablecoin neobank out of Dubai is a story worth following. Would be good to connect. | U63: Thanks for connecting, Raafi. Press covered the round well, but I couldn't find much from you on LinkedIn since 2021. Is building your own voice there on the list this year? | V63: Last indexed own post 2021; no view on stablecoin regulation; profile not reflecting unicorn stage. | W63: No verified email. LinkedIn first. | Y63: Fasset's founder voice | Z63: Hi Raafi, Congrats on the Series C and the $1B valuation. Press covered the round well, but your own LinkedIn has been quiet since 2021. For a stablecoin neobank, the founder's voice is the cheapest trust signal with regulators and users. We build founder brands on LinkedIn, steadily and credibly. Open to a quick call? Prabal Gliped | LinkedIn personal branding for founders Not relevant? Reply "no" and I won't follow up. | AA63: Not found
A64: G063 | B64: 03 | C64: 2026-10-02 | D64: Baraa Koshak | E64: Founder & CEO | F64: Abwab.ai | G64: MENA | H64: Saudi Arabia | I64: https://www.linkedin.com/in/baraakoshak | J64: Yes | K64: $4M seed led by Speedinvest | L64: 2026-09 | M64: https://www.arabnews.com/startups/saudi-fintech-abwabai-raises-4m-in-seed-round-led-by-speedinvest-3002549 | N64: Not indexed | P64: No own posts indexed. Profile confirmed via Prospeo: ex-Revolut and McKinsey. | Q64: 40 | R64: =IF(Q64>=60,"Priority",IF(Q64>=40,"Warm","Nurture")) | S64: Revolut and McKinsey on a CV is a strong hook for Saudi fintech buyers and hires. Right now nobody sees it unless they open the profile. | T64: Hi Baraa, congrats on the seed with Speedinvest. Revolut to building Abwab in Saudi is an interesting path. Would be good to connect. | U64: Thanks for connecting, Baraa. I couldn't find any posts from you yet. At seed, is LinkedIn something you want working for hiring and partnerships? | V64: No posts; Revolut and McKinsey story untold; headline generic. | X64: baraa@abwab.ai | Y64: Abwab's founder story | Z64: Hi Baraa, Congrats on the seed with Speedinvest. Revolut and McKinsey before Abwab is a story Saudi buyers and hires would follow. Right now it only shows if someone opens your profile. We turn founder backgrounds into a steady LinkedIn presence. Want the 3-point teardown of your profile? Prabal Gliped | LinkedIn personal branding for founders Not relevant? Reply "no" and I won't follow up. | AA64: Verified | AB64: Prospeo SMTP Founder & CEO; ex-Revolut, McKinsey
A65: G064 | B65: 03 | C65: 2026-10-02 | D65: Mohammad El Mougi | E65: Co-founder | F65: Keep Converting | G65: MENA | H65: UAE | I65: https://www.linkedin.com/search/results/people/?keywords=Mohammad%20El%20Mougi%20Keep%20Converting | J65: No | K65: $2M pre-seed led by Nuwa Capital and COTU Ventures; exits stealth (AI product pages) | L65: 2026-09 | M65: https://www.wamda.com/2026/09/converting-closes-2-million-pre-seed-led-nuwa-capital-cotu-ventures | N65: Not indexed | P65: No own posts or confirmed profile found. Company just exited stealth. | Q65: 40 | R65: =IF(Q65>=60,"Priority",IF(Q65>=40,"Warm","Nurture")) | S65: Coming out of stealth is the moment a founder's profile gets the most visits. Keep Converting sells conversion, so the founder's own page should convert too. | T65: Hi Mohammad, congrats on the pre-seed and the launch. AI product pages that convert is a clear pitch. Would be good to connect. | U65: Thanks for connecting, Mohammad. You've just come out of stealth, so people are checking your profile now. Is LinkedIn part of the launch plan? | V65: Confirm profile; launch story; profile as a landing page. | W65: VERIFY PROFILE. No email found. | Y65: Out of stealth | Z65: Hi Mohammad, Congrats on the $2M pre-seed and the launch. Right after stealth is when your profile gets the most visits. Keep Converting sells conversion, so your own LinkedIn should convert too. We build founder brands on LinkedIn, from positioning to weekly posts. Want the 3-point teardown instead? Prabal Gliped | LinkedIn personal branding for founders Not relevant? Reply "no" and I won't follow up. | AA65: Not found
A66: G065 | B66: 03 | C66: 2026-10-02 | D66: Hamad Al-Thunayan | E66: Co-founder | F66: Dawraty | G66: MENA | H66: Kuwait | I66: https://www.linkedin.com/search/results/people/?keywords=Hamad%20Al-Thunayan%20Dawraty | J66: No | K66: $2M seed with Qatar Development Bank, $10M valuation (edtech) | L66: 2026-09 | M66: https://www.arabnews.com/startups/startup-wrap-funding-momentum-continues-in-mena-despite-regional-headwinds-3002904 | N66: Not indexed | P66: No own posts or confirmed profile found. | Q66: 40 | R66: =IF(Q66>=60,"Priority",IF(Q66>=40,"Warm","Nurture")) | S66: Edtech in Kuwait sells to parents and schools. A founder voice on learning outcomes builds trust faster than ads. | T66: Hi Hamad, congrats on the seed round. Backing from Qatar Development Bank is a strong signal for Dawraty. Would be good to connect. | U66: Thanks for connecting, Hamad. I couldn't find much from you on LinkedIn. With the round done, is building your own voice there something you're thinking about? | V66: Confirm profile; parent and school trust content; Gulf expansion story. | W66: VERIFY PROFILE. No email found. Check co-founders. | Y66: Dawraty's next chapter | Z66: Hi Hamad, Congrats on the seed with Qatar Development Bank. Parents and schools pick edtech they trust, and trust starts with the founder. I couldn't find much from you on LinkedIn yet. We help founders build that voice, without it eating their week. Open to a quick call? Prabal Gliped | LinkedIn personal branding for founders Not relevant? Reply "no" and I won't follow up. | AA66: Not found
A67: G066 | B67: 03 | C67: 2026-10-02 | D67: Purvi Munot | E67: Co-founder & CEO | F67: Sav | G67: MENA | H67: UAE | I67: https://www.linkedin.com/in/purvi-munot | J67: Yes | K67: $3.5M pre-Series A led by Phoenix Venture Partners; 100k users; Saudi expansion | L67: 2026-09 | M67: https://www.wamda.com/2026/09/phoenix-venture-partners-leads-3-5-million-round-uae-fintech-sav | N67: Went quiet | O67: 2022-09 | P67: Three own posts indexed, Jul to Sep 2022, around Sav's launch. Nothing indexed since. | Q67: 50 | R67: =IF(Q67>=60,"Priority",IF(Q67>=40,"Warm","Nurture")) | S67: Sav has 100k users and is entering Saudi. A founder who talks about money habits in the Gulf can be the face of the category. | T67: Hi Purvi, congrats on the pre-Series A. 100k users and a Saudi launch is real momentum for Sav. Would be good to connect. | U67: Thanks for connecting, Purvi. You posted a lot around Sav's launch in 2022, then it went quiet. With Saudi coming, would you want that voice back? | V67: Quiet since 2022; ex-Citi and Mastercard story; Saudi launch content. | W67: Female founder in Gulf fintech: a strong story angle. | X67: purvi@sav.money | Y67: Sav's Saudi launch | Z67: Hi Purvi, Congrats on the pre-Series A and 100k users. You posted a lot around Sav's launch in 2022, then it went quiet. The Saudi launch is a good moment to bring that voice back. We build founder brands on LinkedIn, from positioning to weekly posts. Worth a 15-minute call next week? Prabal Gliped | LinkedIn personal branding for founders Not relevant? Reply "no" and I won't follow up. | AA67: Verified | AB67: Prospeo SMTP Co-founder & CEO; ex-Citi, Mastercard
A68: G067 | B68: 03 | C68: 2026-10-02 | D68: Hossam Hosny | E68: Co-founder | F68: 3C Coding School | G68: MENA | H68: Egypt | I68: https://www.linkedin.com/search/results/people/?keywords=Hossam%20Hosny%203C%20Coding%20School | J68: No | K68: $3M seed led by MRG Economic Group; Saudi expansion | L68: 2026-09 | M68: https://www.finsmes.com/2026/09/3c-coding-school-raises-3m-in-seed-funding.html | N68: Not indexed | P68: No own posts or confirmed profile found. | Q68: 40 | R68: =IF(Q68>=60,"Priority",IF(Q68>=40,"Warm","Nurture")) | S68: Coding schools sell to parents. A founder who explains how kids learn to code builds trust in Egypt and the Saudi market 3C is entering. | T68: Hi Hossam, congrats on the seed and the Saudi expansion. Teaching kids to code at scale is good work. Would be good to connect. | U68: Thanks for connecting, Hossam. I couldn't find much from you on LinkedIn. Is a founder voice part of the Saudi launch plan? | V68: Confirm profile; parent trust content; Saudi expansion story. | W68: VERIFY PROFILE. No email found. | Y68: 3C in Saudi | Z68: Hi Hossam, Congrats on the $3M seed and the Saudi expansion. Parents choose a coding school they trust, and in a new market that trust starts with the founder. I couldn't find much from you on LinkedIn. We help founders build a steady voice there. Open to a quick call? Prabal Gliped | LinkedIn personal branding for founders Not relevant? Reply "no" and I won't follow up. | AA68: Not found
A69: G068 | B69: 03 | C69: 2026-10-02 | D69: Alaa Afifi | E69: Founder | F69: Bekia | G69: MENA | H69: Cairo | I69: https://www.linkedin.com/search/results/people/?keywords=Alaa%20Afifi%20Bekia | J69: No | K69: $765k seed led by Madica (recycling platform) | L69: 2026-09 | M69: https://disruptafrica.com/2026/09/21/egypts-bekia-raises-765k-to-scale-recycling-economy-tech/ | N69: Not indexed | P69: Only posts about the founder indexed (Forbes Middle East 30 Under 30, 2023). No own posts found. | Q69: 40 | R69: =IF(Q69>=60,"Priority",IF(Q69>=40,"Warm","Nurture")) | S69: Others already tell Alaa's story. Recycling in Cairo is a mission people want to follow, so a voice of their own would travel. | T69: Hi Alaa, congrats on the seed led by Madica. Turning recycling into an app people use is a smart idea. Would be good to connect. | U69: Thanks for connecting, Alaa. Others post about Bekia more than you do. Would you want to tell the story yourself on LinkedIn? | V69: Confirm profile; recognition not converted into own posts; impact story. | W69: VERIFY PROFILE. No email found. | Y69: Bekia, in your words | Z69: Hi Alaa, Congrats on the seed led by Madica. Others post about Bekia more than you do, from Forbes Middle East to partners. Recycling in Cairo is a mission people want to hear from the founder. We build founder brands on LinkedIn around stories like yours. Want the 3-point teardown instead? Prabal Gliped | LinkedIn personal branding for founders Not relevant? Reply "no" and I won't follow up. | AA69: Not found
A70: G069 | B70: 03 | C70: 2026-10-02 | D70: Taher Alblowe | E70: Founder & CEO | F70: Rwaj | G70: MENA | H70: Saudi Arabia | I70: https://www.linkedin.com/in/alblowe | J70: Yes | K70: $1.2M pre-seed (live shopping and auction marketplace) | L70: 2026-09 | M70: https://entarabi.com/en/2026/09/saudi-startup-rwaj-raises-1-2-million-in-pre-seed-round/ | N70: Not indexed | P70: Profile confirmed, no posts indexed. Serial founder: ran Geeks Valley for ten years before Rwaj. | Q70: 40 | R70: =IF(Q70>=60,"Priority",IF(Q70>=40,"Warm","Nurture")) | S70: Live shopping depends on sellers trusting the platform. A second-time founder with ten years of experience is a story sellers will listen to. | T70: Hi Taher, congrats on the pre-seed. Live auctions for the region is a bold bet after Geeks Valley. Would be good to connect. | U70: Thanks for connecting, Taher. You have ten years of founder lessons, and none of them are on your LinkedIn yet. Worth putting them to work for Rwaj? | V70: No posts; serial founder story untold; seller recruitment content. | W70: Rwaj is hiring a growth and content lead, so content is already a priority. | X70: taher@rwaj.co | Y70: Ten years, one profile | Z70: Hi Taher, Congrats on Rwaj's pre-seed. You ran Geeks Valley for a decade, and none of those lessons are on your LinkedIn yet. Sellers on a live auction platform want to trust the person behind it. We turn founder experience into a steady LinkedIn presence. Want the 3-point teardown instead? Prabal Gliped | LinkedIn personal branding for founders Not relevant? Reply "no" and I won't follow up. | AA70: Verified | AB70: Prospeo SMTP Founder & CEO Rwaj; ex Geeks Valley founder; Riyadh
A71: G070 | B71: 03 | C71: 2026-10-02 | D71: Wassim Mourad | E71: CEO | F71: FMSi | G71: MENA | H71: UAE | I71: https://www.linkedin.com/search/results/people/?keywords=Wassim%20Mourad%20FMSi | J71: No | K71: Growth investment from Shorooq and Emirates Growth Fund; Saudi expansion and Gulf M&A | L71: 2026-09 | M71: https://enterpriseam.com/uae/2026/09/16/fmsi-targets-saudi-expansion-gulf-ma-following-shorooq-and-egf-investment/ | N71: Not indexed | P71: No own posts or confirmed profile found. | Q71: 50 | R71: =IF(Q71>=60,"Priority",IF(Q71>=40,"Warm","Nurture")) | S71: Gulf M&A and a Saudi push mean bankers, targets and hires will look the CEO up. A CEO voice makes those conversations warmer. | T71: Hi Wassim, congrats on the investment from Shorooq and Emirates Growth Fund. The Saudi expansion sounds like a big step for FMSi. Would be good to connect. | U71: Thanks for connecting, Wassim. With M&A on the table, targets and partners will be checking your profile. Is LinkedIn something you want working for you there? | V71: Confirm profile; M&A and expansion narrative; CEO visibility. | W71: VERIFY PROFILE. No email found. | Y71: FMSi's Gulf expansion | Z71: Hi Wassim, Congrats on the investment from Shorooq and Emirates Growth Fund. With Saudi expansion and M&A ahead, targets, bankers and hires will look you up. I couldn't find much from you on LinkedIn. We build CEO profiles that make those conversations warmer. Worth a 15-minute call? Prabal Gliped | LinkedIn personal branding for founders Not relevant? Reply "no" and I won't follow up. | AA71: Not found
A72: G071 | B72: 03 | C72: 2026-10-02 | D72: Mohammed Almarshidi | E72: Co-founder | F72: RIME | G72: MENA | H72: Saudi Arabia | I72: https://www.linkedin.com/search/results/people/?keywords=Mohammed%20Almarshidi%20RIME | J72: No | K72: $2M+ seed led by SEEDRA Ventures (edge AI agents) | L72: 2026-08 | M72: https://www.wamda.com/2026/08/saudi-startup-rime-raises-2-million-seed-round | N72: Not indexed | P72: No own posts or confirmed profile found. | Q72: 40 | R72: =IF(Q72>=60,"Priority",IF(Q72>=40,"Warm","Nurture")) | S72: Edge AI agents are hard to explain. A founder who explains them clearly wins enterprise pilots in Saudi. | T72: Hi Mohammed, congrats on the seed with SEEDRA. Edge AI agents out of Saudi is a strong niche. Would be good to connect. | U72: Thanks for connecting, Mohammed. I couldn't find posts from you yet. Is a founder voice on LinkedIn part of how you plan to win enterprise pilots? | V72: Confirm profile; explain edge AI simply; pilot and customer stories. | W72: VERIFY PROFILE. No email found. | Y72: RIME, explained | Z72: Hi Mohammed, Congrats on the seed with SEEDRA. Edge AI agents are hard to explain, and enterprise buyers pick founders who explain them clearly. I couldn't find posts from you yet. We help technical founders build that voice on LinkedIn. Want the 3-point teardown instead? Prabal Gliped | LinkedIn personal branding for founders Not relevant? Reply "no" and I won't follow up. | AA72: Not found
A73: G072 | B73: 03 | C73: 2026-10-02 | D73: Ahmed Abaza | E73: Co-founder & CEO | F73: Synapse Analytics | G73: MENA | H73: Cairo | I73: https://www.linkedin.com/in/ahmed-fouad-abaza | J73: Yes | K73: $13M Series A led by Partech (AI decisioning for lenders) | L73: 2026-09 | M73: https://www.wamda.com/en/2026/09/synapse-analytics-secures-13-million-series-led-partech | N73: Research voice | O73: 2024-01 | P73: Nine own posts indexed, 2022 to Jan 2024: MLOps, dimensionality reduction, Egypt's AI sector, COP28 AI, an Al Arabiya interview and a 2023 wrap-up. Nothing indexed after Jan 2024. | Q73: 50 | R73: =IF(Q73>=60,"Priority",IF(Q73>=40,"Warm","Nurture")) | S73: Already writes about AI with authority. The Series A is the moment to turn that into a steady voice that lenders across the region read. | T73: Hi Ahmed, congrats on the Series A led by Partech. AI decisioning for lenders is where Synapse fits well. Would be good to connect. | U73: Thanks for connecting, Ahmed. You've written on MLOps and Egypt's AI sector before. The last post I found is from Jan 2024. Would you want help making that steady again? | V73: Technical posts with no cadence; lender-facing content; Series A story. | W73: Writes their own posts. Pitch cadence and distribution, not writing. No verified email. | Y73: Your AI posts, steady | Z73: Hi Ahmed, Congrats on the Series A led by Partech. You've written about MLOps and Egypt's AI sector, but the last post I found is from Jan 2024. Lenders across the region would read you weekly. We handle cadence, editing and distribution for founders who already write. Worth a 15-minute call? Prabal Gliped | LinkedIn personal branding for founders Not relevant? Reply "no" and I won't follow up. | AA73: Not found
A74: G073 | B74: 03 | C74: 2026-10-02 | D74: Ahmed AlSharif | E74: Co-founder | F74: Think | G74: MENA | H74: Saudi Arabia | I74: https://www.linkedin.com/search/results/people/?keywords=Ahmed%20AlSharif%20Think | J74: No | K74: $8M pre-seed co-led by RAED and Wa'ed (AI infrastructure) | L74: 2026-07 | M74: https://www.wamda.com/en/2026/07/think-gears-gcc-expansion-8-million-pre-seed-funding | N74: Not indexed | P74: No own posts or confirmed profile found. | Q74: 50 | R74: =IF(Q74>=60,"Priority",IF(Q74>=40,"Warm","Nurture")) | S74: An $8M pre-seed for AI infrastructure gets attention. The founder who explains the bet becomes the go-to name in GCC AI. | T74: Hi Ahmed, congrats on the $8M pre-seed. AI infrastructure built for the GCC is a big bet. Would be good to connect. | U74: Thanks for connecting, Ahmed. A round that size gets people asking who's behind Think. Is LinkedIn part of how you want to answer that? | V74: Confirm profile; thesis post; GCC AI commentary. | W74: VERIFY PROFILE. No email found. Common name: match company carefully. | Y74: Think's $8M bet | Z74: Hi Ahmed, Congrats on the $8M pre-seed. A round that size gets people asking who's behind Think. The founder who explains the bet becomes the go-to name in GCC AI. We build founder brands on LinkedIn, from positioning to weekly posts. Open to a quick call? Prabal Gliped | LinkedIn personal branding for founders Not relevant? Reply "no" and I won't follow up. | AA74: Not found
A75: G074 | B75: 03 | C75: 2026-10-02 | D75: Bader Kalooti | E75: Founder | F75: Bundle | G75: MENA | H75: UAE | I75: https://www.linkedin.com/search/results/people/?keywords=Bader%20Kalooti%20Bundle | J75: No | K75: $5.5M pre-seed led by Ethereal Ventures and Further (Web3 rewards) | L75: 2026-07 | M75: https://www.wamda.com/2026/07/web3-startup-bundle-launches-5-5-million-pre-seed-round | N75: Not indexed | P75: Only event-page posts indexed (spoke at Global Blockchain Show as a Binance regional lead). No own posts found. | Q75: 50 | R75: =IF(Q75>=60,"Priority",IF(Q75>=40,"Warm","Nurture")) | S75: Ex-Binance credibility is a hook in Web3. Bundle needs users and partners, and a founder voice is the fastest way to reach them. | T75: Hi Bader, congrats on the pre-seed for Bundle. Web3 rewards after your Binance years makes sense. Would be good to connect. | U75: Thanks for connecting, Bader. Event pages post about you more than you do. Would you want your own LinkedIn doing that work for Bundle? | V75: Confirm profile; Binance to founder story; Web3 rewards explainer. | W75: VERIFY PROFILE. No email found. | Y75: Bundle's founder voice | Z75: Hi Bader, Congrats on the $5.5M pre-seed. Event pages post about you more than you do. In Web3, users and partners follow people, and your Binance years are a strong hook. We build founder brands on LinkedIn, from positioning to weekly posts. Worth a 15-minute call? Prabal Gliped | LinkedIn personal branding for founders Not relevant? Reply "no" and I won't follow up. | AA75: Not found
A76: G075 | B76: 03 | C76: 2026-10-02 | D76: Samer Gharaibeh | E76: Founder & CEO | F76: Mylerz | G76: MENA | H76: Egypt | I76: https://www.linkedin.com/search/results/people/?keywords=Samer%20Gharaibeh%20Mylerz | J76: No | K76: EGP 100M+ (about $2M) for domestic expansion (last-mile logistics) | L76: 2026-07 | M76: https://enterpriseam.com/egypt/2026/07/15/mylerz-raises-over-egp-100-mn-to-fund-domestic-expansion/ | N76: Not indexed | P76: Only posts about the founder indexed (described as a logistics veteran turned tech founder). No own posts found. | Q76: 50 | R76: =IF(Q76>=60,"Priority",IF(Q76>=40,"Warm","Nurture")) | S76: A logistics veteran with a large fleet. E-commerce brands in Egypt would follow that view on last-mile delivery. | T76: Hi Samer, congrats on the new funding for Mylerz. Same-day delivery across Egypt is hard to do well. Would be good to connect. | U76: Thanks for connecting, Samer. Others call you a logistics veteran, but your own LinkedIn is quiet. Would you want that experience working for Mylerz? | V76: Confirm profile; last-mile insights; merchant-facing content. | W76: VERIFY PROFILE. No email found. Trigger is Jul 2026. | Y76: Mylerz, from the founder | Z76: Hi Samer, Congrats on the new funding for Mylerz. Others call you a logistics veteran, but your own LinkedIn is quiet. Merchants in Egypt would follow your view on last-mile delivery. We turn founder experience into a steady LinkedIn presence. Open to a quick call? Prabal Gliped | LinkedIn personal branding for founders Not relevant? Reply "no" and I won't follow up. | AA76: Not found
A77: G076 | B77: 03 | C77: 2026-10-02 | D77: Osama AlRaee | E77: Co-founder | F77: Lendo | G77: MENA | H77: Riyadh | I77: https://www.linkedin.com/search/results/people/?keywords=Osama%20AlRaee%20Lendo | J77: No | K77: Up to SAR 750M ($200M) SME financing programme with Quantic | L77: 2026-09 | M77: https://www.wamda.com/2026/09/lendo-quantic-launch-200-million-sme-financing-programme-saudi-arabia | N77: Not indexed | P77: Only others' posts about Lendo indexed (co-founder Mohamed Jawabri's Series B post, Dec 2023). No own posts found. | Q77: 50 | R77: =IF(Q77>=60,"Priority",IF(Q77>=40,"Warm","Nurture")) | S77: Lendo is a licensed SME lender heading toward an IPO. A CEO voice builds trust with SMEs and investors. | T77: Hi Osama, congrats on the SME financing programme with Quantic. SAR 750M for Saudi SMEs is a big commitment. Would be good to connect. | U77: Thanks for connecting, Osama. Your co-founder posts Lendo's news more than you do. With an IPO on the horizon, is your own voice worth building? | V77: Confirm profile; IPO-track CEO visibility; SME credit commentary. | W77: VERIFY PROFILE. No email found. Co-founder Mohamed Jawabri posts; check who leads comms. | Y77: Lendo's CEO voice | Z77: Hi Osama, Congrats on the SAR 750M programme with Quantic. Your co-founder posts Lendo's news more than you do. On the road to an IPO, investors and SMEs will want to hear from the CEO. We build CEO brands on LinkedIn, steadily and credibly. Worth a 15-minute call? Prabal Gliped | LinkedIn personal branding for founders Not relevant? Reply "no" and I won't follow up. | AA77: Not found
A78: G077 | B78: 03 | C78: 2026-10-02 | D78: Ladi Delano | E78: Co-founder & CEO | F78: Moove | G78: MENA | H78: UAE | I78: https://www.linkedin.com/in/ladidelano | J78: Yes | K78: $250M Series C at $2.1B valuation led by Mubadala (autonomous mobility) | L78: 2026-08 | M78: https://www.connectingafrica.com/investment/moove-raises-250m-in-series-c-round-valuation-hits-2-1b | N78: Company-page voice | P78: No own posts indexed. Moove's company page and press carry the story. | Q78: 50 | R78: =IF(Q78>=60,"Priority",IF(Q78>=40,"Warm","Nurture")) | S78: Moove is a $2.1B company moving into autonomous fleets. Large company: offer to work alongside the comms team on Ladi's own voice. | T78: Hi Ladi, congrats on the Series C. Moving Moove into autonomous fleets is a bold next chapter. Would be good to connect. | U78: Thanks for connecting, Ladi. Moove's page tells the company story well, but your own feed is quiet. Would your comms team want support on a founder voice? | V78: Company page does the talking; founder story from JCDecaux to Moove; autonomy thesis. | W78: Large company. Offer to work alongside comms. Prospeo lists the role as Co-founder and CEO; press says Co-CEO. | X78: ladi.delano@moove.io | Y78: Your voice, alongside Moove's | Z78: Hi Ladi, Congrats on the $250M Series C. Moove's page tells the company story well, but your own feed is quiet. The move into autonomous fleets is a founder story people want from you. We work alongside comms teams to build founder voices on LinkedIn. Open to a quick call? Prabal Gliped | LinkedIn personal branding for founders Not relevant? Reply "no" and I won't follow up. | AA78: Verified | AB78: Prospeo SMTP Co-Founder and CEO Moove; Dubai; ex-CEO JCDecaux (Africa)
A79: G078 | B79: 03 | C79: 2026-10-02 | D79: Omar Abu Innab | E79: Co-founder & CEO | F79: Keyper | G79: MENA | H79: Dubai | I79: https://www.linkedin.com/search/results/people/?keywords=Omar%20Abu%20Innab%20Keyper | J79: No | K79: $11M Series A (monthly rent payments) | L79: 2026-07 | M79: https://www.finsmes.com/2026/07/keyper-raises-11m-in-series-a-funding.html | N79: Not indexed | P79: Only a media page post about Keyper indexed (2022). No own posts found. | Q79: 50 | R79: =IF(Q79>=60,"Priority",IF(Q79>=40,"Warm","Nurture")) | S79: Monthly rent is a change landlords resist. A founder who explains it well wins landlords and tenants. | T79: Hi Omar, congrats on the Series A. Monthly rent in the UAE is a change a lot of tenants want. Would be good to connect. | U79: Thanks for connecting, Omar. I couldn't find much from you on LinkedIn. Is your own voice part of how you want to win landlords over? | V79: Confirm profile; landlord and tenant education; Series A story. | W79: VERIFY PROFILE. No email found. Trigger is Jul 2026. | Y79: Keyper's founder story | Z79: Hi Omar, Congrats on the $11M Series A. Monthly rent is a change landlords need convincing on, and they trust people more than apps. I couldn't find much from you on LinkedIn. We build founder brands on LinkedIn, from positioning to weekly posts. Worth a 15-minute call? Prabal Gliped | LinkedIn personal branding for founders Not relevant? Reply "no" and I won't follow up. | AA79: Not found
A80: G079 | B80: 03 | C80: 2026-10-02 | D80: Tareq Dalbah | E80: Co-founder & CEO | F80: Arab Therapy | G80: MENA | H80: Berlin / MENA | I80: https://www.linkedin.com/search/results/people/?keywords=Tareq%20Dalbah%20Arab%20Therapy | J80: No | K80: $2M pre-Series A led by Manara Ventures (Arabic online therapy) | L80: 2026-08 | M80: https://entarabi.com/en/2026/08/arab-therapy-raises-2-million-in-pre-ser/ | N80: Not indexed | P80: No own posts indexed. | Q80: 40 | R80: =IF(Q80>=60,"Priority",IF(Q80>=40,"Warm","Nurture")) | S80: Mental health in Arabic is a sensitive and personal topic. A founder voice that is careful and human builds trust. | T80: Hi Tareq, congrats on the pre-Series A. Online therapy in Arabic fills a real gap. Would be good to connect. | U80: Thanks for connecting, Tareq. I couldn't find much from you on LinkedIn. Would a careful founder voice help Arab Therapy reach more people? | V80: Confirm profile; why Arab Therapy exists; measured tone. | W80: VERIFY PROFILE. No email found. Sensitive topic, keep it measured. Based between Berlin and Amman. | Y80: Arab Therapy's story | Z80: Hi Tareq, Congrats on the pre-Series A. Online therapy in Arabic is personal, and people trust a founder they can hear from. I couldn't find much from you on LinkedIn. We build founder voices carefully and in a measured tone. Open to a quick call? Prabal Gliped | LinkedIn personal branding for founders Not relevant? Reply "no" and I won't follow up. | AA80: Not found
A81: G080 | B81: 03 | C81: 2026-10-02 | D81: Mohammed Al-Mubayed | E81: Founder & CEO | F81: Fitting | G81: MENA | H81: Saudi Arabia | I81: https://www.linkedin.com/search/results/people/?keywords=Mohammed%20Al-Mubayed%20Fitting | J81: No | K81: $1.1M second seed (construction materials platform) | L81: 2026-08 | M81: https://www.wamda.com/2026/08/saudi-contech-fitting-raises-1-1-million-seed-fuel-expansion | N81: Not indexed | P81: No own posts or confirmed profile found. | Q81: 40 | R81: =IF(Q81>=60,"Priority",IF(Q81>=40,"Warm","Nurture")) | S81: Construction buyers trust people they know. A founder voice on materials sourcing builds that trust. | T81: Hi Mohammed, congrats on the new seed round. A materials platform for Saudi construction is well timed. Would be good to connect. | U81: Thanks for connecting, Mohammed. I couldn't find posts from you yet. Is LinkedIn part of how you want to reach contractors? | V81: Confirm profile; contractor-facing content; expansion story. | W81: VERIFY PROFILE. No email found. | Y81: Fitting's next stage | Z81: Hi Mohammed, Congrats on the new seed round. Contractors buy from people they know. A founder voice on materials sourcing is how Fitting gets known before the sales call. We build founder brands on LinkedIn, from positioning to weekly posts. Want the 3-point teardown instead? Prabal Gliped | LinkedIn personal branding for founders Not relevant? Reply "no" and I won't follow up. | AA81: Not found
A82: G081 | B82: 03 | C82: 2026-10-02 | D82: Matt Wilson | E82: Co-founder & CEO | F82: Jack & Jill | G82: UK | H82: London | I82: https://www.linkedin.com/in/matthew-wilson-671a757a | J82: Yes | K82: $40M Series A led by Air Street Capital (AI hiring agents) | L82: 2026-09 | M82: https://www.eu-startups.com/2026/09/london-based-jack-jill-raises-e34-68-million-series-a-to-scale-its-ai-agents-for-jobseekers-and-employers | N82: Milestone-only | O82: 2025-10 | P82: One own post indexed: the $20M seed announcement (Oct 2025). Second-time founder (co-founded Omnipresent). | Q82: 50 | R82: =IF(Q82>=60,"Priority",IF(Q82>=40,"Warm","Nurture")) | S82: Jack & Jill sells AI agents that replace parts of recruiting, so candidates and hiring managers look at the founder. A steady voice turns those visits into users. | T82: Hi Matt, congrats on the Series A. Two AI agents, one for candidates and one for companies, is a neat design. Would be good to connect. | U82: Thanks for connecting, Matt. The last post I found from you is the seed in Oct 2025. With the Series A out, do you want a steadier voice there? | V82: Posts at raises only; Omnipresent lessons; hiring market views. | W82: Prospeo shows a US (New York) location; company is London-based. | X82: matthew@jackandjill.ai | Y82: Jack & Jill's Series A | Z82: Hi Matt, Congrats on the $40M Series A. The last post I found from you is the seed in Oct 2025. Candidates and hiring managers check the founder before they trust an AI recruiter. We build founder brands on LinkedIn, from positioning to weekly posts. Worth a 15-minute call next week? Prabal Gliped | LinkedIn personal branding for founders Not relevant? Reply "no" and I won't follow up. | AA82: Verified | AB82: Prospeo SMTP Co-founder & CEO; ex co-founder/co-CEO Omnipresent; Prospeo location shows US (NY timezone)
A83: G082 | B83: 03 | C83: 2026-10-02 | D83: Alex Higginbottom | E83: Founder & CEO | F83: Zenithon | G83: UK | H83: London | I83: https://www.linkedin.com/in/alex-higginbottom-049056141 | J83: Yes | K83: $10M led by BACKED with Seraphim, Lunar, MMC (world models for extreme physics) | L83: 2026-09 | M83: https://tech.eu/2026/09/30/zenithon-raises-10m-to-build-world-models-for-extreme-physics | N83: Not indexed | P83: Profile confirmed, no own posts indexed. Left a Cambridge and Manchester PhD to start Zenithon. | Q83: 50 | R83: =IF(Q83>=60,"Priority",IF(Q83>=40,"Warm","Nurture")) | S83: World models for fusion, rockets and chips is a story engineers and investors want explained. The founder is the person to explain it. | T83: Hi Alex, congrats on the $10M round. World models for extreme physics is a big idea. Would be good to connect. | U83: Thanks for connecting, Alex. I couldn't find posts from you yet. With hiring from 11 to 17, would a founder voice help you find the right people? | V83: No posts; PhD dropout story; explain world models for engineers. | W83: Raise announced 30 Sep 2026, so this is very fresh. | X83: alex@zenithon.ai | Y83: Zenithon's story | Z83: Hi Alex, Congrats on the $10M round. You're growing from 11 to 17 people, and the engineers you want will look you up first. I couldn't find posts from you yet. We help technical founders explain big ideas on LinkedIn, steadily. Worth a 15-minute call? Prabal Gliped | LinkedIn personal branding for founders Not relevant? Reply "no" and I won't follow up. | AA83: Verified | AB83: Prospeo SMTP Founder & CEO; London; PhD dropout (Cambridge/Manchester); prior co-founder 2Body
A84: G083 | B84: 03 | C84: 2026-10-02 | D84: Umaima Ahmad | E84: Co-founder & CEO | F84: 52North | G84: UK | H84: Cambridge | I84: https://www.linkedin.com/in/umaima-ahmad | J84: Yes | K84: GBP 3.2M co-led by Macmillan and Hargreave Hale AIM VCT (Neutrocheck cancer test) | L84: 2026-09 | M84: https://ifamagazine.com/52north-raises-3-2-million-to-transform-urgent-cancer-care-with-funding-co-led-by-macmillan-cancer-support-and-hargreave-hale-aim-vct/ | N84: Went quiet | O84: 2023-01 | P84: One own post indexed: welcoming Prof Sir Leszek Borysiewicz to the board (Jan 2023). Cambridge and Innovate UK post about the founder. | Q84: 40 | R84: =IF(Q84>=60,"Priority",IF(Q84>=40,"Warm","Nurture")) | S84: A home blood test for chemo patients is a story clinicians and patients care about. A founder voice can carry it into the NHS. | T84: Hi Umaima, congrats on the round co-led by Macmillan. Neutrocheck could change urgent cancer care. Would be good to connect. | U84: Thanks for connecting, Umaima. Others post about 52North more than you do. The last post I found from you is from 2023. Would you want that voice back? | V84: Quiet since 2023; patient-first story; NHS adoption content. | W84: No verified email. LinkedIn first. | Y84: Neutrocheck, from you | Z84: Hi Umaima, Congrats on the round co-led by Macmillan. Cambridge and Innovate UK post about 52North more than you do, and your last post I found is from 2023. Clinicians and patients would follow your voice. We build founder brands on LinkedIn around stories like this. Open to a quick call? Prabal Gliped | LinkedIn personal branding for founders Not relevant? Reply "no" and I won't follow up. | AA84: Not found
A85: G084 | B85: 03 | C85: 2026-10-02 | D85: Daniel Park | E85: Founder | F85: InTouchNow | G85: UK | H85: UK | I85: https://www.linkedin.com/search/results/people/?keywords=Daniel%20Park%20InTouchNow | J85: No | K85: GBP 2.3M seed led by Ada Ventures (AI voice agent for GP surgeries) | L85: 2026-09 | M85: https://www.resultsense.com/news/2026-09-23-intouchnow-seed-gp-ai-voice-agent/ | N85: Not indexed | P85: Common name; no own posts matched to InTouchNow. | Q85: 40 | R85: =IF(Q85>=60,"Priority",IF(Q85>=40,"Warm","Nurture")) | S85: GP surgeries are cautious buyers. A founder who explains how an AI voice agent helps patients and staff earns trust. | T85: Hi Daniel, congrats on the seed led by Ada Ventures. An AI voice agent for GP surgeries tackles a real pain. Would be good to connect. | U85: Thanks for connecting, Daniel. Practice managers will look you up before they trust an AI on their phones. Is LinkedIn part of how you want to reach them? | V85: Confirm profile; practice manager content; patient safety. | W85: VERIFY PROFILE. Common name. No email found. | Y85: InTouchNow and GP practices | Z85: Hi Daniel, Congrats on the seed led by Ada Ventures. Practice managers will look you up before they trust an AI voice agent with their patients. A founder voice on LinkedIn makes that easier. We build founder brands, from positioning to weekly posts. Want the 3-point teardown instead? Prabal Gliped | LinkedIn personal branding for founders Not relevant? Reply "no" and I won't follow up. | AA85: Not found
A86: G085 | B86: 03 | C86: 2026-10-02 | D86: Guy Levy-Yurista | E86: CEO | F86: Imperagen | G86: UK | H86: Manchester | I86: https://www.linkedin.com/search/results/people/?keywords=Guy%20Levy-Yurista%20Imperagen | J86: No | K86: GBP 5M seed; appointed CEO (AI enzyme engineering) | L86: 2026-09 | M86: https://businesscloud.co.uk/news/spin-out-imperagen-raises-5m-and-announces-new-ceo/ | N86: Not indexed | P86: No own posts indexed. Appointed CEO at the same time as the seed round. | Q86: 60 | R86: =IF(Q86>=60,"Priority",IF(Q86>=40,"Warm","Nurture")) | S86: New CEO and new money at once. The first 90 days on LinkedIn set how partners and hires see Imperagen. | T86: Hi Guy, congrats on the CEO role and the £5M seed. AI enzyme engineering out of Manchester is a strong story. Would be good to connect. | U86: Thanks for connecting, Guy. New CEO plus a fresh round is when people check your profile most. Would you want a plan for your first months there? | V86: Confirm profile; new CEO intro; enzyme engineering explained. | W86: VERIFY PROFILE. Two triggers (new CEO and raise). No email found. | Y86: Your first 90 days | Z86: Hi Guy, Congrats on the CEO role and the £5M seed. A new CEO and fresh money is when partners and hires check your profile most. The first 90 days set how they see Imperagen. We build CEO brands on LinkedIn, from positioning to weekly posts. Worth a 15-minute call next week? Prabal Gliped | LinkedIn personal branding for founders Not relevant? Reply "no" and I won't follow up. | AA86: Not found
A87: G086 | B87: 03 | C87: 2026-10-02 | D87: Andrea Romano | E87: CEO | F87: DriveSimple | G87: UK | H87: London | I87: https://www.linkedin.com/search/results/people/?keywords=Andrea%20Romano%20DriveSimple | J87: No | K87: GBP 1.5M from Calm Media Investments; appointed CEO (van subscriptions) | L87: 2026-09 | M87: https://fleetworld.co.uk/drivesimple-raises-1-5m-to-scale-flexible-van-subscription-model/ | N87: Not indexed | P87: No own posts indexed. Appointed CEO alongside the raise. | Q87: 50 | R87: =IF(Q87>=60,"Priority",IF(Q87>=40,"Warm","Nurture")) | S87: A new CEO at a van subscription business needs fleet buyers to know who's in charge. LinkedIn is where they look. | T87: Hi Andrea, congrats on the new role and the round. Van subscriptions fit how small businesses buy now. Would be good to connect. | U87: Thanks for connecting, Andrea. As the new CEO, people will be checking your profile. Is LinkedIn part of your plan for the first months? | V87: Confirm profile; new CEO intro; small-business fleet content. | W87: VERIFY PROFILE. Common name. No email found. | Y87: New CEO at DriveSimple | Z87: Hi Andrea, Congrats on the new role and the £1.5M round. Fleet buyers will want to know who's running DriveSimple now. LinkedIn is where they look. We build CEO brands on LinkedIn, from positioning to weekly posts. Open to a quick call? Prabal Gliped | LinkedIn personal branding for founders Not relevant? Reply "no" and I won't follow up. | AA87: Not found
A88: G087 | B88: 03 | C88: 2026-10-02 | D88: Danyal Akarca | E88: Co-founder & CEO | F88: Callosum | G88: UK | H88: London | I88: https://www.linkedin.com/search/results/people/?keywords=Danyal%20Akarca%20Callosum | J88: No | K88: $100M (GBP 73.5M) seed led by Atomico; first UK Sovereign AI Fund investment | L88: 2026-08 | M88: https://www.uktech.news/ai/callosum-raises-73-5m-to-redefine-how-humanity-computes-20260820 | N88: Not indexed | P88: No own posts indexed. | Q88: 50 | R88: =IF(Q88>=60,"Priority",IF(Q88>=40,"Warm","Nurture")) | S88: A $100M seed and the first Sovereign AI Fund cheque make Callosum a national story. The founder who explains it becomes the voice of UK compute. | T88: Hi Danyal, congrats on the seed led by Atomico. Being the first Sovereign AI Fund investment is a big moment. Would be good to connect. | U88: Thanks for connecting, Danyal. A round like that puts you in front of researchers, hires and government. Would you want help with your own voice on LinkedIn? | V88: Confirm profile; thesis on new computing; research to company story. | W88: VERIFY PROFILE. No email found. Likely research background: pitch distribution and cadence. | Y88: Callosum's voice | Z88: Hi Danyal, Congrats on the seed led by Atomico. Being the first Sovereign AI Fund investment puts you in front of researchers, hires and government. Your own LinkedIn could carry that story. We help research founders with cadence and distribution, not just writing. Worth a 15-minute call? Prabal Gliped | LinkedIn personal branding for founders Not relevant? Reply "no" and I won't follow up. | AA88: Not found
A89: G088 | B89: 03 | C89: 2026-10-02 | D89: Ilya Drozdov | E89: Co-founder & CEO | F89: Dwelly | G89: UK | H89: London | I89: https://www.linkedin.com/search/results/people/?keywords=Ilya%20Drozdov%20Dwelly | J89: No | K89: GBP 128M Series B (AI roll-up of letting agencies) | L89: 2026-07 | M89: https://businesscloud.co.uk/news/proptech-dwelly-raises-128m-in-series-b-funding/ | N89: Not indexed | P89: No own posts matched to Dwelly (search returned a different Ilia Drozdov). | Q89: 50 | R89: =IF(Q89>=60,"Priority",IF(Q89>=40,"Warm","Nurture")) | S89: An AI roll-up of letting agencies needs agency owners to want to sell to Dwelly. A founder voice makes that pitch first. | T89: Hi Ilya, congrats on the Series B. Rolling up letting agencies with AI is a bold model. Would be good to connect. | U89: Thanks for connecting, Ilya. Agency owners you want to acquire will look you up. Is LinkedIn part of how you want to reach them? | V89: Confirm profile; seller-facing content; roll-up thesis. | W89: VERIFY PROFILE. No email found. Trigger is Jul 2026. | Y89: Dwelly and agency owners | Z89: Hi Ilya, Congrats on the £128M Series B. The agency owners you want to acquire will look you up first. A founder voice makes that pitch before you call. We build founder brands on LinkedIn, from positioning to weekly posts. Worth a 15-minute call? Prabal Gliped | LinkedIn personal branding for founders Not relevant? Reply "no" and I won't follow up. | AA89: Not found
A90: G089 | B90: 03 | C90: 2026-10-02 | D90: Max Buchan | E90: Founder & CEO | F90: Valarian | G90: UK | H90: London | I90: https://www.linkedin.com/in/maxbuchan | J90: Yes | K90: $50M (GBP 37M) Series A (sovereign AI infrastructure) | L90: 2026-07 | M90: https://ventureburn.com/valarian-raises-50-million-sovereign-ai-infrastructure/ | N90: Went quiet | O90: 2023-05 | P90: Own posts indexed from Mar 2020 (Worldr) and May 2023 (first exec hire). Forbes 30 Under 30 2024. Nothing indexed for the Valarian rebrand or the Series A. | Q90: 50 | R90: =IF(Q90>=60,"Priority",IF(Q90>=40,"Warm","Nurture")) | S90: Sovereign AI infrastructure is a policy topic as much as a product. A CEO who comments on it gets invited into those rooms. | T90: Hi Max, congrats on the Series A. Sovereign AI infrastructure is a timely space for Valarian. Would be good to connect. | U90: Thanks for connecting, Max. The last post I found from you is from 2023, before the Valarian rebrand. Would you want your voice to catch up with the company? | V90: Quiet since 2023; sovereignty commentary; defence and government buyers. | W90: Defence buyers. Keep it formal. Trigger is Jul 2026. | X90: max@valarian.com | Y90: Valarian, in your voice | Z90: Hi Max, Congrats on the $50M Series A. The last post I found from you is from 2023, before the rebrand. Sovereign AI is a policy topic, and CEOs who comment on it get invited into those rooms. We build CEO brands on LinkedIn, steadily and credibly. Worth a 15-minute call? Prabal Gliped | LinkedIn personal branding for founders Not relevant? Reply "no" and I won't follow up. | AA90: Verified | AB90: Prospeo SMTP Founder & CEO since 2020 (Worldr rebrand); Forbes 30u30 2024; ex-CoinShares
A91: G090 | B91: 03 | C91: 2026-10-02 | D91: Arthur Fordham | E91: Co-founder | F91: AcouBatt | G91: UK | H91: London | I91: https://www.linkedin.com/search/results/people/?keywords=Arthur%20Fordham%20AcouBatt | J91: No | K91: GBP 1.1M pre-seed led by Creator Fund with Ada Ventures (battery diagnostics, UCL spinout) | L91: 2026-09 | M91: https://tech.eu/2026/09/16/acoubatt-raises-ps11m-to-improve-battery-manufacturing-safety-and-reliability | N91: Not indexed | P91: No own posts or confirmed profile found. | Q91: 40 | R91: =IF(Q91>=60,"Priority",IF(Q91>=40,"Warm","Nurture")) | S91: Battery safety matters to every gigafactory. A UCL spinout founder who explains it simply gets noticed by manufacturers. | T91: Hi Arthur, congrats on the pre-seed. Acoustic battery diagnostics is a clever idea. Would be good to connect. | U91: Thanks for connecting, Arthur. I couldn't find posts from you yet. Is LinkedIn part of how you want to reach battery makers? | V91: Confirm profile; spinout story; manufacturer-facing content. | W91: VERIFY PROFILE. No email found. | Y91: AcouBatt's story | Z91: Hi Arthur, Congrats on the pre-seed. Battery makers will want to understand acoustic diagnostics, and a founder who explains it simply gets noticed. I couldn't find posts from you yet. We build founder brands on LinkedIn. Want the 3-point teardown instead? Prabal Gliped | LinkedIn personal branding for founders Not relevant? Reply "no" and I won't follow up. | AA91: Not found
A92: G091 | B92: 03 | C92: 2026-10-02 | D92: David Dobrin | E92: Founder | F92: OriginalVoices | G92: UK | H92: London | I92: https://www.linkedin.com/search/results/people/?keywords=David%20Dobrin%20OriginalVoices | J92: No | K92: GBP 1M pre-seed led by Iona Star (human data for AI) | L92: 2026-09 | M92: https://tech.eu/2026/09/15/originalvoices-raises-ps1m-pre-seed-round-led-by-iona-star | N92: Not indexed | P92: No own posts or confirmed profile found. | Q92: 40 | R92: =IF(Q92>=60,"Priority",IF(Q92>=40,"Warm","Nurture")) | S92: Human data for AI is a hot and debated topic. A founder with a clear view gets heard by AI labs. | T92: Hi David, congrats on the pre-seed. Human data for AI is a timely problem to solve. Would be good to connect. | U92: Thanks for connecting, David. I couldn't find posts from you yet. Would a founder voice help OriginalVoices reach AI teams? | V92: Confirm profile; point of view on AI data; customer stories. | W92: VERIFY PROFILE. No email found. | Y92: OriginalVoices, your voice | Z92: Hi David, Congrats on the pre-seed. Human data for AI is debated, and AI teams listen to founders with a clear view. I couldn't find posts from you yet. We build founder brands on LinkedIn, from positioning to weekly posts. Want the 3-point teardown instead? Prabal Gliped | LinkedIn personal branding for founders Not relevant? Reply "no" and I won't follow up. | AA92: Not found
A93: G092 | B93: 03 | C93: 2026-10-02 | D93: Koye Sodipo | E93: Founder | F93: Anemo Labs | G93: UK | H93: UK | I93: https://www.linkedin.com/search/results/people/?keywords=Koye%20Sodipo%20Anemo%20Labs | J93: No | K93: GBP 700k pre-seed co-led by Zinc and SFC Capital (AI e-nose) | L93: 2026-09 | M93: https://tech.eu/2026/09/09/anemo-labs-lands-ps700k-to-give-ai-a-sense-of-smell | N93: Not indexed | P93: No own posts or confirmed profile found. | Q93: 40 | R93: =IF(Q93>=60,"Priority",IF(Q93>=40,"Warm","Nurture")) | S93: Giving AI a sense of smell is the kind of idea people share. A founder voice would carry it further than press. | T93: Hi Koye, congrats on the pre-seed. An AI e-nose is a memorable idea. Would be good to connect. | U93: Thanks for connecting, Koye. Anemo is the kind of story people share. Would you want your own LinkedIn telling it? | V93: Confirm profile; explain the e-nose simply; use cases. | W93: VERIFY PROFILE. No email found. | Y93: Anemo's story | Z93: Hi Koye, Congrats on the pre-seed. An AI that can smell is the kind of story people share. Your own LinkedIn could carry it further than the press did. We build founder brands on LinkedIn around ideas like this. Want the 3-point teardown instead? Prabal Gliped | LinkedIn personal branding for founders Not relevant? Reply "no" and I won't follow up. | AA93: Not found
A94: G093 | B94: 03 | C94: 2026-10-02 | D94: Anahita Laverack | E94: Co-founder & CEO | F94: Oshen | G94: UK | H94: Plymouth | I94: https://www.linkedin.com/in/anahita-laverack | J94: Yes | K94: $5M (GBP 3.65M) to scale ocean robot fleet | L94: 2026-08 | M94: https://www.uktech.news/deep-tech/oshen-raises-3-65m-to-scale-ocean-sensing-robot-fleet-20260821 | N94: Went quiet | O94: 2024-02 | P94: Own posts indexed from Aug 2022 (sea trial) and Feb 2024, titled "I've been pretty quiet on LinkedIn recently". Nothing indexed since. | Q94: 50 | R94: =IF(Q94>=60,"Priority",IF(Q94>=40,"Warm","Nurture")) | S94: Ocean robots are visual and easy to share. The founder's own post title admits to being quiet on LinkedIn. | T94: Hi Anahita, congrats on the new round. A fleet of ocean robots out of Plymouth is great to see. Would be good to connect. | U94: Thanks for connecting, Anahita. Your last post I found was titled "I've been pretty quiet on LinkedIn recently", from Feb 2024. Want help so that doesn't happen again? | V94: Quiet since 2024; field footage content; defence and science buyers. | W94: Cite only the post title; text not read. | X94: anahita.laverack@oshensail.com | Y94: Not quiet this time | Z94: Hi Anahita, Congrats on the new round. Your last post I found was titled "I've been pretty quiet on LinkedIn recently", from Feb 2024. Ocean robots are easy to share, and the fleet story deserves a steady voice. We build founder brands, from positioning to weekly posts. Worth a 15-minute call? Prabal Gliped | LinkedIn personal branding for founders Not relevant? Reply "no" and I won't follow up. | AA94: Verified | AB94: Prospeo SMTP CEO since Jan 2024, co-founder 2022; Plymouth; ex-Rolls-Royce
A95: G094 | B95: 03 | C95: 2026-10-02 | D95: Ilan Adler | E95: Founder & CEO | F95: EcoNomad Solutions | G95: UK | H95: UK | I95: https://www.linkedin.com/in/ilan-adler-31226a72 | J95: Yes | K95: GBP 400k round incl. British Design Fund (farm waste-to-energy) | L95: 2026-08 | M95: https://tech.eu/2026/08/19/economad-raises-ps400k-to-bring-waste-to-energy-tech-to-small-livestock-farms/ | N95: Not indexed | P95: Profile confirmed, no own posts indexed. Also an associate professor at UCL. | Q95: 40 | R95: =IF(Q95>=60,"Priority",IF(Q95>=40,"Warm","Nurture")) | S95: An academic founder in agritech has credibility farmers and funders respect. It isn't visible on LinkedIn. | T95: Hi Ilan, congrats on the new round. Waste-to-energy for small livestock farms fills a real gap. Would be good to connect. | U95: Thanks for connecting, Ilan. I couldn't find posts from you. Would a steady voice help EcoNomad reach farmers and funders? | V95: No posts; academic credibility; farmer case studies. | W95: Academic: pitch time saved and distribution. | X95: ilan@economad.co.uk | Y95: EcoNomad's next round | Z95: Hi Ilan, Congrats on the new round. A UCL academic building for small farms has credibility farmers and funders respect. It isn't visible on LinkedIn yet. We build founder voices without it eating your teaching or build time. Open to a quick call? Prabal Gliped | LinkedIn personal branding for founders Not relevant? Reply "no" and I won't follow up. | AA95: Verified | AB95: Prospeo BOUNCEBAN CEO/Founder since 2018; also Associate Professor at UCL
A96: G095 | B96: 03 | C96: 2026-10-02 | D96: Fozia Saleem | E96: CEO | F96: Magnitude Biosciences | G96: UK | H96: Durham | I96: https://www.linkedin.com/in/dr-fozia-saleem-b7762718 | J96: Yes | K96: GBP 1.3M to scale in vivo drug discovery platform | L96: 2026-09 | M96: https://www.uktech.news/funding/magnitude-biosciences-raises-1-3m-to-scale-drug-discovery-platform-20260915 | N96: Company-page voice | P96: Only posts about the CEO indexed: the CEO welcome, Northern Power Women Future List, a funding talk. No own posts found. | Q96: 50 | R96: =IF(Q96>=60,"Priority",IF(Q96>=40,"Warm","Nurture")) | S96: Recognised by others but not posting. Pharma buyers in the US market Magnitude is targeting would follow a CEO voice. | T96: Hi Fozia, congrats on the £1.3M round. In vivo testing that cuts mammal studies is a strong pitch. Would be good to connect. | U96: Thanks for connecting, Fozia. Others post about you, from Northern Power Women to Magnitude's page. Would you want your own voice doing that work? | V96: Recognition without own posts; US market content; drug discovery explained. | X96: fozia@magnitudebiosciences.com | Y96: Your own voice, Fozia | Z96: Hi Fozia, Congrats on the £1.3M round. Others post about you, from Northern Power Women to Magnitude's page. Pharma buyers in the US would follow you directly. We build CEO brands on LinkedIn, from positioning to weekly posts. Worth a 15-minute call? Prabal Gliped | LinkedIn personal branding for founders Not relevant? Reply "no" and I won't follow up. | AA96: Verified | AB96: Prospeo BOUNCEBAN CEO since Oct 2022; Newcastle; Northern Power Women Future List; ex-Broughton director
A97: G096 | B97: 03 | C97: 2026-10-02 | D97: Natasha Jones | E97: Co-founder & CEO | F97: Metris Energy | G97: UK | H97: London | I97: https://www.linkedin.com/in/natasha-jones-url | J97: Yes | K97: $5M seed (AI platform for energy assets) | L97: 2026-09 | M97: https://www.finsmes.com/2026/09/metris-energy-raises-5m-in-seed-funding.html | N97: Went quiet | O97: 2024-03 | P97: One own post indexed, from Mar 2024 (Metris green building). Ex-Octopus Ventures investor, Forbes 30 Under 30. | Q97: 50 | R97: =IF(Q97>=60,"Priority",IF(Q97>=40,"Warm","Nurture")) | S97: An ex-VC founder knows what investors read. Solar asset managers would follow that voice on the energy transition. | T97: Hi Natasha, congrats on the seed. AI for solar asset managers is a smart wedge. Would be good to connect. | U97: Thanks for connecting, Natasha. The last post I found from you is from Mar 2024. With the seed out, would you want a steadier voice? | V97: Quiet since 2024; ex-VC lens; asset manager content. | X97: natasha@metrisenergy.com | Y97: Metris after the seed | Z97: Hi Natasha, Congrats on the $5M seed. The last post I found from you is from Mar 2024. You know from Octopus what investors read, and asset managers would follow your view too. We build founder brands on LinkedIn, from positioning to weekly posts. Worth a 15-minute call? Prabal Gliped | LinkedIn personal branding for founders Not relevant? Reply "no" and I won't follow up. | AA97: Verified | AB97: Prospeo SMTP Co-Founder & CEO; Forbes 30u30; ex-Octopus Ventures investor, Credit Suisse
A98: G097 | B98: 03 | C98: 2026-10-02 | D98: John Daley | E98: Co-founder & CEO | F98: HelmGuard | G98: UK | H98: London | I98: https://www.linkedin.com/search/results/people/?keywords=John%20Daley%20HelmGuard | J98: No | K98: $7.3M seed (agentic GRC and security) | L98: 2026-09 | M98: https://www.finsmes.com/2026/09/helmguard-raises-7-3m-in-seed-funding.html | N98: Not indexed | P98: Common name; no own posts matched to HelmGuard. | Q98: 50 | R98: =IF(Q98>=60,"Priority",IF(Q98>=40,"Warm","Nurture")) | S98: Agentic GRC is new, and CISOs buy from people they trust. A founder voice explains the category. | T98: Hi John, congrats on the seed. Agentic GRC is a timely space. Would be good to connect. | U98: Thanks for connecting, John. CISOs will look you up before a demo. Is LinkedIn part of how you want to reach them? | V98: Confirm profile; explain agentic GRC; security leader content. | W98: VERIFY PROFILE. Common name. No email found. | Y98: HelmGuard and CISOs | Z98: Hi John, Congrats on the $7.3M seed. Agentic GRC is new, and CISOs buy from people they trust. A founder voice explains the category before the demo. We build founder brands on LinkedIn, from positioning to weekly posts. Open to a quick call? Prabal Gliped | LinkedIn personal branding for founders Not relevant? Reply "no" and I won't follow up. | AA98: Not found
A99: G098 | B99: 03 | C99: 2026-10-02 | D99: Khaled Eissa | E99: Co-founder & CEO | F99: Eterna Regeneratives | G99: UK | H99: London | I99: https://www.linkedin.com/search/results/people/?keywords=Khaled%20Eissa%20Eterna%20Regeneratives | J99: No | K99: $4M seed (biomaterials for tissue regeneration) | L99: 2026-09 | M99: https://www.finsmes.com/2026/09/eterna-regeneratives-closes-seed-funding.html | N99: Not indexed | P99: No own posts or confirmed profile found. | Q99: 40 | R99: =IF(Q99>=60,"Priority",IF(Q99>=40,"Warm","Nurture")) | S99: Biomaterials for tissue regeneration is a hopeful story. A founder voice helps with partners and later rounds. | T99: Hi Khaled, congrats on the seed. Biomaterials for tissue regeneration is exciting work. Would be good to connect. | U99: Thanks for connecting, Khaled. I couldn't find posts from you yet. Would a founder voice help Eterna with partners? | V99: Confirm profile; science explained; partner content. | W99: VERIFY PROFILE. No email found. | Y99: Eterna's story | Z99: Hi Khaled, Congrats on the $4M seed. Tissue regeneration is a hopeful story, and partners and investors listen to founders who explain it clearly. I couldn't find posts from you yet. We build founder brands on LinkedIn. Want the 3-point teardown instead? Prabal Gliped | LinkedIn personal branding for founders Not relevant? Reply "no" and I won't follow up. | AA99: Not found
A100: G099 | B100: 03 | C100: 2026-10-02 | D100: Alex Packham | E100: Co-founder | F100: AcademyAI | G100: UK | H100: UK | I100: https://www.linkedin.com/search/results/people/?keywords=Alex%20Packham%20AcademyAI | J100: No | K100: GBP 1.65M pre-seed (workplace AI skills) | L100: 2026-09 | M100: https://tech.eu/2026/09/15/academyai-raises-ps165m-to-close-the-workplace-ai-skills-gap/ | N100: Not indexed | P100: No own posts or confirmed profile found. | Q100: 40 | R100: =IF(Q100>=60,"Priority",IF(Q100>=40,"Warm","Nurture")) | S100: AcademyAI sells AI skills to workplaces. The founder's LinkedIn is the first demo HR buyers see. | T100: Hi Alex, congrats on the pre-seed. The workplace AI skills gap is real. Would be good to connect. | U100: Thanks for connecting, Alex. HR and L&D buyers will look you up first. Is LinkedIn part of how you want to reach them? | V100: Confirm profile; AI skills content; L&D buyer content. | W100: VERIFY PROFILE. No email found. | Y100: AcademyAI's first demo | Z100: Hi Alex, Congrats on the £1.65M pre-seed. You sell AI skills to workplaces, and HR buyers will check your LinkedIn first. Your profile is the first demo. We build founder brands on LinkedIn, from positioning to weekly posts. Want the 3-point teardown instead? Prabal Gliped | LinkedIn personal branding for founders Not relevant? Reply "no" and I won't follow up. | AA100: Not found
...

Sheet Tracker
A1: ID | B1: Name | C1: Company | D1: Region | E1: Tier | F1: Activity pattern | G1: Profile confirmed | H1: Status | I1: Warm-up started | J1: Connection sent | K1: Accepted | L1: First DM sent | M1: FU1 due | N1: FU1 sent | O1: FU2 due | P1: FU2 sent | Q1: Replied | R1: Teardown sent | S1: Call booked | T1: Call held (Y/N) | U1: Outcome | V1: Next action | W1: Next action date | X1: Days since last touch | Y1: Notes | Z1: Email address | AA1: Email sent | AB1: Email FU due | AC1: Email FU sent
A2: G001 | B2: =IFERROR(INDEX(Leads!$D:$D,MATCH($A2,Leads!$A:$A,0)),"") | C2: =IFERROR(INDEX(Leads!$F:$F,MATCH($A2,Leads!$A:$A,0)),"") | D2: =IFERROR(INDEX(Leads!$G:$G,MATCH($A2,Leads!$A:$A,0)),"") | E2: =IFERROR(INDEX(Leads!$R:$R,MATCH($A2,Leads!$A:$A,0)),"") | F2: =IFERROR(INDEX(Leads!$N:$N,MATCH($A2,Leads!$A:$A,0)),"") | G2: =IFERROR(INDEX(Leads!$J:$J,MATCH($A2,Leads!$A:$A,0)),"") | H2: Not started | M2: =IF(L2="","",L2+4) | O2: =IF(N2="","",N2+6) | X2: =IF(MAX(I2:L2,N2,P2:S2,AA2,AC2)=0,"",TODAY()-MAX(I2:L2,N2,P2:S2,AA2,AC2)) | Z2: =IFERROR(IF(INDEX(Leads!$X:$X,MATCH($A2,Leads!$A:$A,0))="","",INDEX(Leads!$X:$X,MATCH($A2,Leads!$A:$A,0))),"") | AB2: =IF(AA2="","",AA2+5)
A3: G002 | B3: =IFERROR(INDEX(Leads!$D:$D,MATCH($A3,Leads!$A:$A,0)),"") | C3: =IFERROR(INDEX(Leads!$F:$F,MATCH($A3,Leads!$A:$A,0)),"") | D3: =IFERROR(INDEX(Leads!$G:$G,MATCH($A3,Leads!$A:$A,0)),"") | E3: =IFERROR(INDEX(Leads!$R:$R,MATCH($A3,Leads!$A:$A,0)),"") | F3: =IFERROR(INDEX(Leads!$N:$N,MATCH($A3,Leads!$A:$A,0)),"") | G3: =IFERROR(INDEX(Leads!$J:$J,MATCH($A3,Leads!$A:$A,0)),"") | H3: Not started | M3: =IF(L3="","",L3+4) | O3: =IF(N3="","",N3+6) | X3: =IF(MAX(I3:L3,N3,P3:S3,AA3,AC3)=0,"",TODAY()-MAX(I3:L3,N3,P3:S3,AA3,AC3)) | Z3: =IFERROR(IF(INDEX(Leads!$X:$X,MATCH($A3,Leads!$A:$A,0))="","",INDEX(Leads!$X:$X,MATCH($A3,Leads!$A:$A,0))),"") | AB3: =IF(AA3="","",AA3+5)
A4: G003 | B4: =IFERROR(INDEX(Leads!$D:$D,MATCH($A4,Leads!$A:$A,0)),"") | C4: =IFERROR(INDEX(Leads!$F:$F,MATCH($A4,Leads!$A:$A,0)),"") | D4: =IFERROR(INDEX(Leads!$G:$G,MATCH($A4,Leads!$A:$A,0)),"") | E4: =IFERROR(INDEX(Leads!$R:$R,MATCH($A4,Leads!$A:$A,0)),"") | F4: =IFERROR(INDEX(Leads!$N:$N,MATCH($A4,Leads!$A:$A,0)),"") | G4: =IFERROR(INDEX(Leads!$J:$J,MATCH($A4,Leads!$A:$A,0)),"") | H4: Not started | M4: =IF(L4="","",L4+4) | O4: =IF(N4="","",N4+6) | X4: =IF(MAX(I4:L4,N4,P4:S4,AA4,AC4)=0,"",TODAY()-MAX(I4:L4,N4,P4:S4,AA4,AC4)) | Z4: =IFERROR(IF(INDEX(Leads!$X:$X,MATCH($A4,Leads!$A:$A,0))="","",INDEX(Leads!$X:$X,MATCH($A4,Leads!$A:$A,0))),"") | AB4: =IF(AA4="","",AA4+5)
A5: G004 | B5: =IFERROR(INDEX(Leads!$D:$D,MATCH($A5,Leads!$A:$A,0)),"") | C5: =IFERROR(INDEX(Leads!$F:$F,MATCH($A5,Leads!$A:$A,0)),"") | D5: =IFERROR(INDEX(Leads!$G:$G,MATCH($A5,Leads!$A:$A,0)),"") | E5: =IFERROR(INDEX(Leads!$R:$R,MATCH($A5,Leads!$A:$A,0)),"") | F5: =IFERROR(INDEX(Leads!$N:$N,MATCH($A5,Leads!$A:$A,0)),"") | G5: =IFERROR(INDEX(Leads!$J:$J,MATCH($A5,Leads!$A:$A,0)),"") | H5: Not started | M5: =IF(L5="","",L5+4) | O5: =IF(N5="","",N5+6) | X5: =IF(MAX(I5:L5,N5,P5:S5,AA5,AC5)=0,"",TODAY()-MAX(I5:L5,N5,P5:S5,AA5,AC5)) | Z5: =IFERROR(IF(INDEX(Leads!$X:$X,MATCH($A5,Leads!$A:$A,0))="","",INDEX(Leads!$X:$X,MATCH($A5,Leads!$A:$A,0))),"") | AB5: =IF(AA5="","",AA5+5)
A6: G005 | B6: =IFERROR(INDEX(Leads!$D:$D,MATCH($A6,Leads!$A:$A,0)),"") | C6: =IFERROR(INDEX(Leads!$F:$F,MATCH($A6,Leads!$A:$A,0)),"") | D6: =IFERROR(INDEX(Leads!$G:$G,MATCH($A6,Leads!$A:$A,0)),"") | E6: =IFERROR(INDEX(Leads!$R:$R,MATCH($A6,Leads!$A:$A,0)),"") | F6: =IFERROR(INDEX(Leads!$N:$N,MATCH($A6,Leads!$A:$A,0)),"") | G6: =IFERROR(INDEX(Leads!$J:$J,MATCH($A6,Leads!$A:$A,0)),"") | H6: Not started | M6: =IF(L6="","",L6+4) | O6: =IF(N6="","",N6+6) | X6: =IF(MAX(I6:L6,N6,P6:S6,AA6,AC6)=0,"",TODAY()-MAX(I6:L6,N6,P6:S6,AA6,AC6)) | Z6: =IFERROR(IF(INDEX(Leads!$X:$X,MATCH($A6,Leads!$A:$A,0))="","",INDEX(Leads!$X:$X,MATCH($A6,Leads!$A:$A,0))),"") | AB6: =IF(AA6="","",AA6+5)
A7: G006 | B7: =IFERROR(INDEX(Leads!$D:$D,MATCH($A7,Leads!$A:$A,0)),"") | C7: =IFERROR(INDEX(Leads!$F:$F,MATCH($A7,Leads!$A:$A,0)),"") | D7: =IFERROR(INDEX(Leads!$G:$G,MATCH($A7,Leads!$A:$A,0)),"") | E7: =IFERROR(INDEX(Leads!$R:$R,MATCH($A7,Leads!$A:$A,0)),"") | F7: =IFERROR(INDEX(Leads!$N:$N,MATCH($A7,Leads!$A:$A,0)),"") | G7: =IFERROR(INDEX(Leads!$J:$J,MATCH($A7,Leads!$A:$A,0)),"") | H7: Not started | M7: =IF(L7="","",L7+4) | O7: =IF(N7="","",N7+6) | X7: =IF(MAX(I7:L7,N7,P7:S7,AA7,AC7)=0,"",TODAY()-MAX(I7:L7,N7,P7:S7,AA7,AC7)) | Z7: =IFERROR(IF(INDEX(Leads!$X:$X,MATCH($A7,Leads!$A:$A,0))="","",INDEX(Leads!$X:$X,MATCH($A7,Leads!$A:$A,0))),"") | AB7: =IF(AA7="","",AA7+5)
A8: G007 | B8: =IFERROR(INDEX(Leads!$D:$D,MATCH($A8,Leads!$A:$A,0)),"") | C8: =IFERROR(INDEX(Leads!$F:$F,MATCH($A8,Leads!$A:$A,0)),"") | D8: =IFERROR(INDEX(Leads!$G:$G,MATCH($A8,Leads!$A:$A,0)),"") | E8: =IFERROR(INDEX(Leads!$R:$R,MATCH($A8,Leads!$A:$A,0)),"") | F8: =IFERROR(INDEX(Leads!$N:$N,MATCH($A8,Leads!$A:$A,0)),"") | G8: =IFERROR(INDEX(Leads!$J:$J,MATCH($A8,Leads!$A:$A,0)),"") | H8: Not started | M8: =IF(L8="","",L8+4) | O8: =IF(N8="","",N8+6) | X8: =IF(MAX(I8:L8,N8,P8:S8,AA8,AC8)=0,"",TODAY()-MAX(I8:L8,N8,P8:S8,AA8,AC8)) | Z8: =IFERROR(IF(INDEX(Leads!$X:$X,MATCH($A8,Leads!$A:$A,0))="","",INDEX(Leads!$X:$X,MATCH($A8,Leads!$A:$A,0))),"") | AB8: =IF(AA8="","",AA8+5)
A9: G008 | B9: =IFERROR(INDEX(Leads!$D:$D,MATCH($A9,Leads!$A:$A,0)),"") | C9: =IFERROR(INDEX(Leads!$F:$F,MATCH($A9,Leads!$A:$A,0)),"") | D9: =IFERROR(INDEX(Leads!$G:$G,MATCH($A9,Leads!$A:$A,0)),"") | E9: =IFERROR(INDEX(Leads!$R:$R,MATCH($A9,Leads!$A:$A,0)),"") | F9: =IFERROR(INDEX(Leads!$N:$N,MATCH($A9,Leads!$A:$A,0)),"") | G9: =IFERROR(INDEX(Leads!$J:$J,MATCH($A9,Leads!$A:$A,0)),"") | H9: Not started | M9: =IF(L9="","",L9+4) | O9: =IF(N9="","",N9+6) | X9: =IF(MAX(I9:L9,N9,P9:S9,AA9,AC9)=0,"",TODAY()-MAX(I9:L9,N9,P9:S9,AA9,AC9)) | Z9: =IFERROR(IF(INDEX(Leads!$X:$X,MATCH($A9,Leads!$A:$A,0))="","",INDEX(Leads!$X:$X,MATCH($A9,Leads!$A:$A,0))),"") | AB9: =IF(AA9="","",AA9+5)
A10: G009 | B10: =IFERROR(INDEX(Leads!$D:$D,MATCH($A10,Leads!$A:$A,0)),"") | C10: =IFERROR(INDEX(Leads!$F:$F,MATCH($A10,Leads!$A:$A,0)),"") | D10: =IFERROR(INDEX(Leads!$G:$G,MATCH($A10,Leads!$A:$A,0)),"") | E10: =IFERROR(INDEX(Leads!$R:$R,MATCH($A10,Leads!$A:$A,0)),"") | F10: =IFERROR(INDEX(Leads!$N:$N,MATCH($A10,Leads!$A:$A,0)),"") | G10: =IFERROR(INDEX(Leads!$J:$J,MATCH($A10,Leads!$A:$A,0)),"") | H10: Not started | M10: =IF(L10="","",L10+4) | O10: =IF(N10="","",N10+6) | X10: =IF(MAX(I10:L10,N10,P10:S10,AA10,AC10)=0,"",TODAY()-MAX(I10:L10,N10,P10:S10,AA10,AC10)) | Z10: =IFERROR(IF(INDEX(Leads!$X:$X,MATCH($A10,Leads!$A:$A,0))="","",INDEX(Leads!$X:$X,MATCH($A10,Leads!$A:$A,0))),"") | AB10: =IF(AA10="","",AA10+5)
A11: G010 | B11: =IFERROR(INDEX(Leads!$D:$D,MATCH($A11,Leads!$A:$A,0)),"") | C11: =IFERROR(INDEX(Leads!$F:$F,MATCH($A11,Leads!$A:$A,0)),"") | D11: =IFERROR(INDEX(Leads!$G:$G,MATCH($A11,Leads!$A:$A,0)),"") | E11: =IFERROR(INDEX(Leads!$R:$R,MATCH($A11,Leads!$A:$A,0)),"") | F11: =IFERROR(INDEX(Leads!$N:$N,MATCH($A11,Leads!$A:$A,0)),"") | G11: =IFERROR(INDEX(Leads!$J:$J,MATCH($A11,Leads!$A:$A,0)),"") | H11: Not started | M11: =IF(L11="","",L11+4) | O11: =IF(N11="","",N11+6) | X11: =IF(MAX(I11:L11,N11,P11:S11,AA11,AC11)=0,"",TODAY()-MAX(I11:L11,N11,P11:S11,AA11,AC11)) | Z11: =IFERROR(IF(INDEX(Leads!$X:$X,MATCH($A11,Leads!$A:$A,0))="","",INDEX(Leads!$X:$X,MATCH($A11,Leads!$A:$A,0))),"") | AB11: =IF(AA11="","",AA11+5)
A12: G011 | B12: =IFERROR(INDEX(Leads!$D:$D,MATCH($A12,Leads!$A:$A,0)),"") | C12: =IFERROR(INDEX(Leads!$F:$F,MATCH($A12,Leads!$A:$A,0)),"") | D12: =IFERROR(INDEX(Leads!$G:$G,MATCH($A12,Leads!$A:$A,0)),"") | E12: =IFERROR(INDEX(Leads!$R:$R,MATCH($A12,Leads!$A:$A,0)),"") | F12: =IFERROR(INDEX(Leads!$N:$N,MATCH($A12,Leads!$A:$A,0)),"") | G12: =IFERROR(INDEX(Leads!$J:$J,MATCH($A12,Leads!$A:$A,0)),"") | H12: Not started | M12: =IF(L12="","",L12+4) | O12: =IF(N12="","",N12+6) | X12: =IF(MAX(I12:L12,N12,P12:S12,AA12,AC12)=0,"",TODAY()-MAX(I12:L12,N12,P12:S12,AA12,AC12)) | Z12: =IFERROR(IF(INDEX(Leads!$X:$X,MATCH($A12,Leads!$A:$A,0))="","",INDEX(Leads!$X:$X,MATCH($A12,Leads!$A:$A,0))),"") | AB12: =IF(AA12="","",AA12+5)
A13: G012 | B13: =IFERROR(INDEX(Leads!$D:$D,MATCH($A13,Leads!$A:$A,0)),"") | C13: =IFERROR(INDEX(Leads!$F:$F,MATCH($A13,Leads!$A:$A,0)),"") | D13: =IFERROR(INDEX(Leads!$G:$G,MATCH($A13,Leads!$A:$A,0)),"") | E13: =IFERROR(INDEX(Leads!$R:$R,MATCH($A13,Leads!$A:$A,0)),"") | F13: =IFERROR(INDEX(Leads!$N:$N,MATCH($A13,Leads!$A:$A,0)),"") | G13: =IFERROR(INDEX(Leads!$J:$J,MATCH($A13,Leads!$A:$A,0)),"") | H13: Not started | M13: =IF(L13="","",L13+4) | O13: =IF(N13="","",N13+6) | X13: =IF(MAX(I13:L13,N13,P13:S13,AA13,AC13)=0,"",TODAY()-MAX(I13:L13,N13,P13:S13,AA13,AC13)) | Z13: =IFERROR(IF(INDEX(Leads!$X:$X,MATCH($A13,Leads!$A:$A,0))="","",INDEX(Leads!$X:$X,MATCH($A13,Leads!$A:$A,0))),"") | AB13: =IF(AA13="","",AA13+5)
... A121: G120 | B121: =IFERROR(INDEX(Leads!$D:$D,MATCH($A121,Leads!$A:$A,0)),"") | C121: =IFERROR(INDEX(Leads!$F:$F,MATCH($A121,Leads!$A:$A,0)),"") | D121: =IFERROR(INDEX(Leads!$G:$G,MATCH($A121,Leads!$A:$A,0)),"") | E121: =IFERROR(INDEX(Leads!$R:$R,MATCH($A121,Leads!$A:$A,0)),"") | F121: =IFERROR(INDEX(Leads!$N:$N,MATCH($A121,Leads!$A:$A,0)),"") | G121: =IFERROR(INDEX(Leads!$J:$J,MATCH($A121,Leads!$A:$A,0)),"") | H121: Not started | M121: =IF(L121="","",L121+4) | O121: =IF(N121="","",N121+6) | X121: =IF(MAX(I121:L121,N121,P121:S121,AA121,AC121)=0,"",TODAY()-MAX(I121:L121,N121,P121:S121,AA121,AC121)) | Z121: =IFERROR(IF(INDEX(Leads!$X:$X,MATCH($A121,Leads!$A:$A,0))="","",INDEX(Leads!$X:$X,MATCH($A121,Leads!$A:$A,0))),"") | AB121: =IF(AA121="","",AA121+5)

Sheet Dashboard
A1: Pipeline dashboard
A2: Updates from the Tracker tab. Rates divide by leads contacted (status past Not started / Warming up / Nurture).
A4: Status | B4: Leads
A5: Not started | B5: =COUNTIF(Tracker!$H$2:$H$321,A5)
A6: Warming up | B6: =COUNTIF(Tracker!$H$2:$H$321,A6)
A7: Connection sent | B7: =COUNTIF(Tracker!$H$2:$H$321,A7)
A8: Connected | B8: =COUNTIF(Tracker!$H$2:$H$321,A8)
A9: DM sent | B9: =COUNTIF(Tracker!$H$2:$H$321,A9)
A10: Follow-up 1 sent | B10: =COUNTIF(Tracker!$H$2:$H$321,A10)
A11: Follow-up 2 sent | B11: =COUNTIF(Tracker!$H$2:$H$321,A11)
A12: Replied | B12: =COUNTIF(Tracker!$H$2:$H$321,A12)
A13: Teardown sent | B13: =COUNTIF(Tracker!$H$2:$H$321,A13)
A14: Call booked | B14: =COUNTIF(Tracker!$H$2:$H$321,A14)
A15: Call held | B15: =COUNTIF(Tracker!$H$2:$H$321,A15)
A16: Proposal sent | B16: =COUNTIF(Tracker!$H$2:$H$321,A16)
... A20: Nurture | B20: =COUNTIF(Tracker!$H$2:$H$321,A20)
A21: Total | B21: =SUM(B5:B20)
A23: Funnel
A24: Stage | B24: Leads | C24: Rate vs contacted
A25: Contacted | B25: =COUNTIF(Tracker!$H$2:$H$321,"Connection sent")+COUNTIF(Tracker!$H$2:$H$321,"Connected")+COUNTIF(Tracker!$H$2:$H$321,"DM sent")+COUNTIF(Tracker!$H$2:$H$321,"Follow-up 1 sent")+COUNTIF(Tracker!$H$2:$H$321,"Follow-up 2 sent")+COUNTIF(Tracker!$H$2:$H$321,"Replied")+COUNTIF(Tracker!$H$2:$H$321,"Teardown sent")+COUNTIF(Tracker!$H$2:$H$321,"Call booked")+COUNTIF(Tracker!$H$2:$H$321,"Call held")+COUNTIF(Tracker!$H$2:$H$321,"Proposal sent")+COUNTIF(Tracker!$H$2:$H$321,"Won")+COUNTIF(Tracker!$H$2:$H$321,"Lost")+COUNTIF(Tracker!$H$2:$H$321,"No response") | C25: =IFERROR(B25/$B$25,0)
A26: Connected | B26: =COUNTIF(Tracker!$H$2:$H$321,"Connected")+COUNTIF(Tracker!$H$2:$H$321,"DM sent")+COUNTIF(Tracker!$H$2:$H$321,"Follow-up 1 sent")+COUNTIF(Tracker!$H$2:$H$321,"Follow-up 2 sent")+COUNTIF(Tracker!$H$2:$H$321,"Replied")+COUNTIF(Tracker!$H$2:$H$321,"Teardown sent")+COUNTIF(Tracker!$H$2:$H$321,"Call booked")+COUNTIF(Tracker!$H$2:$H$321,"Call held")+COUNTIF(Tracker!$H$2:$H$321,"Proposal sent")+COUNTIF(Tracker!$H$2:$H$321,"Won")+COUNTIF(Tracker!$H$2:$H$321,"Lost") | C26: =IFERROR(B26/$B$25,0)
A27: Replied | B27: =COUNTIF(Tracker!$H$2:$H$321,"Replied")+COUNTIF(Tracker!$H$2:$H$321,"Teardown sent")+COUNTIF(Tracker!$H$2:$H$321,"Call booked")+COUNTIF(Tracker!$H$2:$H$321,"Call held")+COUNTIF(Tracker!$H$2:$H$321,"Proposal sent")+COUNTIF(Tracker!$H$2:$H$321,"Won")+COUNTIF(Tracker!$H$2:$H$321,"Lost") | C27: =IFERROR(B27/$B$25,0)
A28: Call booked | B28: =COUNTIF(Tracker!$H$2:$H$321,"Call booked")+COUNTIF(Tracker!$H$2:$H$321,"Call held")+COUNTIF(Tracker!$H$2:$H$321,"Proposal sent")+COUNTIF(Tracker!$H$2:$H$321,"Won")+COUNTIF(Tracker!$H$2:$H$321,"Lost") | C28: =IFERROR(B28/$B$25,0)
A29: Won | B29: =COUNTIF(Tracker!$H$2:$H$321,"Won") | C29: =IFERROR(B29/$B$25,0)
A32: Leads by region
A33: Region | B33: Leads | C33: Contacted | D33: Replied | E33: Calls | F33: Reply rate | G33: Call rate
A34: India | B34: =COUNTIF(Tracker!$D$2:$D$321,$A34) | C34: =COUNTIFS(Tracker!$D$2:$D$321,$A34,Tracker!$H$2:$H$321,"Connection sent")+COUNTIFS(Tracker!$D$2:$D$321,$A34,Tracker!$H$2:$H$321,"Connected")+COUNTIFS(Tracker!$D$2:$D$321,$A34,Tracker!$H$2:$H$321,"DM sent")+COUNTIFS(Tracker!$D$2:$D$321,$A34,Tracker!$H$2:$H$321,"Follow-up 1 sent")+COUNTIFS(Tracker!$D$2:$D$321,$A34,Tracker!$H$2:$H$321,"Follow-up 2 sent")+COUNTIFS(Tracker!$D$2:$D$321,$A34,Tracker!$H$2:$H$321,"Replied")+COUNTIFS(Tracker!$D$2:$D$321,$A34,Tracker!$H$2:$H$321,"Teardown sent")+COUNTIFS(Tracker!$D$2:$D$321,$A34,Tracker!$H$2:$H$321,"Call booked")+COUNTIFS(Tracker!$D$2:$D$321,$A34,Tracker!$H$2:$H$321,"Call held")+COUNTIFS(Tracker!$D$2:$D$321,$A34,Tracker!$H$2:$H$321,"Proposal sent")+COUNTIFS(Tracker!$D$2:$D$321,$A34,Tracker!$H$2:$H$321,"Won")+COUNTIFS(Tracker!$D$2:$D$321,$A34,Tracker!$H$2:$H$321,"Lost")+COUNTIFS(Tracker!$D$2:$D$321,$A34,Tracker!$H$2:$H$321,"No response") | D34: =COUNTIFS(Tracker!$D$2:$D$321,$A34,Tracker!$H$2:$H$321,"Replied")+COUNTIFS(Tracker!$D$2:$D$321,$A34,Tracker!$H$2:$H$321,"Teardown sent")+COUNTIFS(Tracker!$D$2:$D$321,$A34,Tracker!$H$2:$H$321,"Call booked")+COUNTIFS(Tracker!$D$2:$D$321,$A34,Tracker!$H$2:$H$321,"Call held")+COUNTIFS(Tracker!$D$2:$D$321,$A34,Tracker!$H$2:$H$321,"Proposal sent")+COUNTIFS(Tracker!$D$2:$D$321,$A34,Tracker!$H$2:$H$321,"Won")+COUNTIFS(Tracker!$D$2:$D$321,$A34,Tracker!$H$2:$H$321,"Lost") | E34: =COUNTIFS(Tracker!$D$2:$D$321,$A34,Tracker!$H$2:$H$321,"Call booked")+COUNTIFS(Tracker!$D$2:$D$321,$A34,Tracker!$H$2:$H$321,"Call held")+COUNTIFS(Tracker!$D$2:$D$321,$A34,Tracker!$H$2:$H$321,"Proposal sent")+COUNTIFS(Tracker!$D$2:$D$321,$A34,Tracker!$H$2:$H$321,"Won")+COUNTIFS(Tracker!$D$2:$D$321,$A34,Tracker!$H$2:$H$321,"Lost") | F34: =IFERROR(D34/C34,0) | G34: =IFERROR(E34/C34,0)
A35: UK | B35: =COUNTIF(Tracker!$D$2:$D$321,$A35) | C35: =COUNTIFS(Tracker!$D$2:$D$321,$A35,Tracker!$H$2:$H$321,"Connection sent")+COUNTIFS(Tracker!$D$2:$D$321,$A35,Tracker!$H$2:$H$321,"Connected")+COUNTIFS(Tracker!$D$2:$D$321,$A35,Tracker!$H$2:$H$321,"DM sent")+COUNTIFS(Tracker!$D$2:$D$321,$A35,Tracker!$H$2:$H$321,"Follow-up 1 sent")+COUNTIFS(Tracker!$D$2:$D$321,$A35,Tracker!$H$2:$H$321,"Follow-up 2 sent")+COUNTIFS(Tracker!$D$2:$D$321,$A35,Tracker!$H$2:$H$321,"Replied")+COUNTIFS(Tracker!$D$2:$D$321,$A35,Tracker!$H$2:$H$321,"Teardown sent")+COUNTIFS(Tracker!$D$2:$D$321,$A35,Tracker!$H$2:$H$321,"Call booked")+COUNTIFS(Tracker!$D$2:$D$321,$A35,Tracker!$H$2:$H$321,"Call held")+COUNTIFS(Tracker!$D$2:$D$321,$A35,Tracker!$H$2:$H$321,"Proposal sent")+COUNTIFS(Tracker!$D$2:$D$321,$A35,Tracker!$H$2:$H$321,"Won")+COUNTIFS(Tracker!$D$2:$D$321,$A35,Tracker!$H$2:$H$321,"Lost")+COUNTIFS(Tracker!$D$2:$D$321,$A35,Tracker!$H$2:$H$321,"No response") | D35: =COUNTIFS(Tracker!$D$2:$D$321,$A35,Tracker!$H$2:$H$321,"Replied")+COUNTIFS(Tracker!$D$2:$D$321,$A35,Tracker!$H$2:$H$321,"Teardown sent")+COUNTIFS(Tracker!$D$2:$D$321,$A35,Tracker!$H$2:$H$321,"Call booked")+COUNTIFS(Tracker!$D$2:$D$321,$A35,Tracker!$H$2:$H$321,"Call held")+COUNTIFS(Tracker!$D$2:$D$321,$A35,Tracker!$H$2:$H$321,"Proposal sent")+COUNTIFS(Tracker!$D$2:$D$321,$A35,Tracker!$H$2:$H$321,"Won")+COUNTIFS(Tracker!$D$2:$D$321,$A35,Tracker!$H$2:$H$321,"Lost") | E35: =COUNTIFS(Tracker!$D$2:$D$321,$A35,Tracker!$H$2:$H$321,"Call booked")+COUNTIFS(Tracker!$D$2:$D$321,$A35,Tracker!$H$2:$H$321,"Call held")+COUNTIFS(Tracker!$D$2:$D$321,$A35,Tracker!$H$2:$H$321,"Proposal sent")+COUNTIFS(Tracker!$D$2:$D$321,$A35,Tracker!$H$2:$H$321,"Won")+COUNTIFS(Tracker!$D$2:$D$321,$A35,Tracker!$H$2:$H$321,"Lost") | F35: =IFERROR(D35/C35,0) | G35: =IFERROR(E35/C35,0)
A36: Canada | B36: =COUNTIF(Tracker!$D$2:$D$321,$A36) | C36: =COUNTIFS(Tracker!$D$2:$D$321,$A36,Tracker!$H$2:$H$321,"Connection sent")+COUNTIFS(Tracker!$D$2:$D$321,$A36,Tracker!$H$2:$H$321,"Connected")+COUNTIFS(Tracker!$D$2:$D$321,$A36,Tracker!$H$2:$H$321,"DM sent")+COUNTIFS(Tracker!$D$2:$D$321,$A36,Tracker!$H$2:$H$321,"Follow-up 1 sent")+COUNTIFS(Tracker!$D$2:$D$321,$A36,Tracker!$H$2:$H$321,"Follow-up 2 sent")+COUNTIFS(Tracker!$D$2:$D$321,$A36,Tracker!$H$2:$H$321,"Replied")+COUNTIFS(Tracker!$D$2:$D$321,$A36,Tracker!$H$2:$H$321,"Teardown sent")+COUNTIFS(Tracker!$D$2:$D$321,$A36,Tracker!$H$2:$H$321,"Call booked")+COUNTIFS(Tracker!$D$2:$D$321,$A36,Tracker!$H$2:$H$321,"Call held")+COUNTIFS(Tracker!$D$2:$D$321,$A36,Tracker!$H$2:$H$321,"Proposal sent")+COUNTIFS(Tracker!$D$2:$D$321,$A36,Tracker!$H$2:$H$321,"Won")+COUNTIFS(Tracker!$D$2:$D$321,$A36,Tracker!$H$2:$H$321,"Lost")+COUNTIFS(Tracker!$D$2:$D$321,$A36,Tracker!$H$2:$H$321,"No response") | D36: =COUNTIFS(Tracker!$D$2:$D$321,$A36,Tracker!$H$2:$H$321,"Replied")+COUNTIFS(Tracker!$D$2:$D$321,$A36,Tracker!$H$2:$H$321,"Teardown sent")+COUNTIFS(Tracker!$D$2:$D$321,$A36,Tracker!$H$2:$H$321,"Call booked")+COUNTIFS(Tracker!$D$2:$D$321,$A36,Tracker!$H$2:$H$321,"Call held")+COUNTIFS(Tracker!$D$2:$D$321,$A36,Tracker!$H$2:$H$321,"Proposal sent")+COUNTIFS(Tracker!$D$2:$D$321,$A36,Tracker!$H$2:$H$321,"Won")+COUNTIFS(Tracker!$D$2:$D$321,$A36,Tracker!$H$2:$H$321,"Lost") | E36: =COUNTIFS(Tracker!$D$2:$D$321,$A36,Tracker!$H$2:$H$321,"Call booked")+COUNTIFS(Tracker!$D$2:$D$321,$A36,Tracker!$H$2:$H$321,"Call held")+COUNTIFS(Tracker!$D$2:$D$321,$A36,Tracker!$H$2:$H$321,"Proposal sent")+COUNTIFS(Tracker!$D$2:$D$321,$A36,Tracker!$H$2:$H$321,"Won")+COUNTIFS(Tracker!$D$2:$D$321,$A36,Tracker!$H$2:$H$321,"Lost") | F36: =IFERROR(D36/C36,0) | G36: =IFERROR(E36/C36,0)
A37: US | B37: =COUNTIF(Tracker!$D$2:$D$321,$A37) | C37: =COUNTIFS(Tracker!$D$2:$D$321,$A37,Tracker!$H$2:$H$321,"Connection sent")+COUNTIFS(Tracker!$D$2:$D$321,$A37,Tracker!$H$2:$H$321,"Connected")+COUNTIFS(Tracker!$D$2:$D$321,$A37,Tracker!$H$2:$H$321,"DM sent")+COUNTIFS(Tracker!$D$2:$D$321,$A37,Tracker!$H$2:$H$321,"Follow-up 1 sent")+COUNTIFS(Tracker!$D$2:$D$321,$A37,Tracker!$H$2:$H$321,"Follow-up 2 sent")+COUNTIFS(Tracker!$D$2:$D$321,$A37,Tracker!$H$2:$H$321,"Replied")+COUNTIFS(Tracker!$D$2:$D$321,$A37,Tracker!$H$2:$H$321,"Teardown sent")+COUNTIFS(Tracker!$D$2:$D$321,$A37,Tracker!$H$2:$H$321,"Call booked")+COUNTIFS(Tracker!$D$2:$D$321,$A37,Tracker!$H$2:$H$321,"Call held")+COUNTIFS(Tracker!$D$2:$D$321,$A37,Tracker!$H$2:$H$321,"Proposal sent")+COUNTIFS(Tracker!$D$2:$D$321,$A37,Tracker!$H$2:$H$321,"Won")+COUNTIFS(Tracker!$D$2:$D$321,$A37,Tracker!$H$2:$H$321,"Lost")+COUNTIFS(Tracker!$D$2:$D$321,$A37,Tracker!$H$2:$H$321,"No response") | D37: =COUNTIFS(Tracker!$D$2:$D$321,$A37,Tracker!$H$2:$H$321,"Replied")+COUNTIFS(Tracker!$D$2:$D$321,$A37,Tracker!$H$2:$H$321,"Teardown sent")+COUNTIFS(Tracker!$D$2:$D$321,$A37,Tracker!$H$2:$H$321,"Call booked")+COUNTIFS(Tracker!$D$2:$D$321,$A37,Tracker!$H$2:$H$321,"Call held")+COUNTIFS(Tracker!$D$2:$D$321,$A37,Tracker!$H$2:$H$321,"Proposal sent")+COUNTIFS(Tracker!$D$2:$D$321,$A37,Tracker!$H$2:$H$321,"Won")+COUNTIFS(Tracker!$D$2:$D$321,$A37,Tracker!$H$2:$H$321,"Lost") | E37: =COUNTIFS(Tracker!$D$2:$D$321,$A37,Tracker!$H$2:$H$321,"Call booked")+COUNTIFS(Tracker!$D$2:$D$321,$A37,Tracker!$H$2:$H$321,"Call held")+COUNTIFS(Tracker!$D$2:$D$321,$A37,Tracker!$H$2:$H$321,"Proposal sent")+COUNTIFS(Tracker!$D$2:$D$321,$A37,Tracker!$H$2:$H$321,"Won")+COUNTIFS(Tracker!$D$2:$D$321,$A37,Tracker!$H$2:$H$321,"Lost") | F37: =IFERROR(D37/C37,0) | G37: =IFERROR(E37/C37,0)
A38: MENA | B38: =COUNTIF(Tracker!$D$2:$D$321,$A38) | C38: =COUNTIFS(Tracker!$D$2:$D$321,$A38,Tracker!$H$2:$H$321,"Connection sent")+COUNTIFS(Tracker!$D$2:$D$321,$A38,Tracker!$H$2:$H$321,"Connected")+COUNTIFS(Tracker!$D$2:$D$321,$A38,Tracker!$H$2:$H$321,"DM sent")+COUNTIFS(Tracker!$D$2:$D$321,$A38,Tracker!$H$2:$H$321,"Follow-up 1 sent")+COUNTIFS(Tracker!$D$2:$D$321,$A38,Tracker!$H$2:$H$321,"Follow-up 2 sent")+COUNTIFS(Tracker!$D$2:$D$321,$A38,Tracker!$H$2:$H$321,"Replied")+COUNTIFS(Tracker!$D$2:$D$321,$A38,Tracker!$H$2:$H$321,"Teardown sent")+COUNTIFS(Tracker!$D$2:$D$321,$A38,Tracker!$H$2:$H$321,"Call booked")+COUNTIFS(Tracker!$D$2:$D$321,$A38,Tracker!$H$2:$H$321,"Call held")+COUNTIFS(Tracker!$D$2:$D$321,$A38,Tracker!$H$2:$H$321,"Proposal sent")+COUNTIFS(Tracker!$D$2:$D$321,$A38,Tracker!$H$2:$H$321,"Won")+COUNTIFS(Tracker!$D$2:$D$321,$A38,Tracker!$H$2:$H$321,"Lost")+COUNTIFS(Tracker!$D$2:$D$321,$A38,Tracker!$H$2:$H$321,"No response") | D38: =COUNTIFS(Tracker!$D$2:$D$321,$A38,Tracker!$H$2:$H$321,"Replied")+COUNTIFS(Tracker!$D$2:$D$321,$A38,Tracker!$H$2:$H$321,"Teardown sent")+COUNTIFS(Tracker!$D$2:$D$321,$A38,Tracker!$H$2:$H$321,"Call booked")+COUNTIFS(Tracker!$D$2:$D$321,$A38,Tracker!$H$2:$H$321,"Call held")+COUNTIFS(Tracker!$D$2:$D$321,$A38,Tracker!$H$2:$H$321,"Proposal sent")+COUNTIFS(Tracker!$D$2:$D$321,$A38,Tracker!$H$2:$H$321,"Won")+COUNTIFS(Tracker!$D$2:$D$321,$A38,Tracker!$H$2:$H$321,"Lost") | E38: =COUNTIFS(Tracker!$D$2:$D$321,$A38,Tracker!$H$2:$H$321,"Call booked")+COUNTIFS(Tracker!$D$2:$D$321,$A38,Tracker!$H$2:$H$321,"Call held")+COUNTIFS(Tracker!$D$2:$D$321,$A38,Tracker!$H$2:$H$321,"Proposal sent")+COUNTIFS(Tracker!$D$2:$D$321,$A38,Tracker!$H$2:$H$321,"Won")+COUNTIFS(Tracker!$D$2:$D$321,$A38,Tracker!$H$2:$H$321,"Lost") | F38: =IFERROR(D38/C38,0) | G38: =IFERROR(E38/C38,0)
A40: Leads by activity pattern
A41: Activity pattern | B41: Leads | C41: Contacted | D41: Replied | E41: Calls | F41: Reply rate | G41: Call rate
A42: Already consistent | B42: =COUNTIF(Tracker!$F$2:$F$321,$A42) | C42: =COUNTIFS(Tracker!$F$2:$F$321,$A42,Tracker!$H$2:$H$321,"Connection sent")+COUNTIFS(Tracker!$F$2:$F$321,$A42,Tracker!$H$2:$H$321,"Connected")+COUNTIFS(Tracker!$F$2:$F$321,$A42,Tracker!$H$2:$H$321,"DM sent")+COUNTIFS(Tracker!$F$2:$F$321,$A42,Tracker!$H$2:$H$321,"Follow-up 1 sent")+COUNTIFS(Tracker!$F$2:$F$321,$A42,Tracker!$H$2:$H$321,"Follow-up 2 sent")+COUNTIFS(Tracker!$F$2:$F$321,$A42,Tracker!$H$2:$H$321,"Replied")+COUNTIFS(Tracker!$F$2:$F$321,$A42,Tracker!$H$2:$H$321,"Teardown sent")+COUNTIFS(Tracker!$F$2:$F$321,$A42,Tracker!$H$2:$H$321,"Call booked")+COUNTIFS(Tracker!$F$2:$F$321,$A42,Tracker!$H$2:$H$321,"Call held")+COUNTIFS(Tracker!$F$2:$F$321,$A42,Tracker!$H$2:$H$321,"Proposal sent")+COUNTIFS(Tracker!$F$2:$F$321,$A42,Tracker!$H$2:$H$321,"Won")+COUNTIFS(Tracker!$F$2:$F$321,$A42,Tracker!$H$2:$H$321,"Lost")+COUNTIFS(Tracker!$F$2:$F$321,$A42,Tracker!$H$2:$H$321,"No response") | D42: =COUNTIFS(Tracker!$F$2:$F$321,$A42,Tracker!$H$2:$H$321,"Replied")+COUNTIFS(Tracker!$F$2:$F$321,$A42,Tracker!$H$2:$H$321,"Teardown sent")+COUNTIFS(Tracker!$F$2:$F$321,$A42,Tracker!$H$2:$H$321,"Call booked")+COUNTIFS(Tracker!$F$2:$F$321,$A42,Tracker!$H$2:$H$321,"Call held")+COUNTIFS(Tracker!$F$2:$F$321,$A42,Tracker!$H$2:$H$321,"Proposal sent")+COUNTIFS(Tracker!$F$2:$F$321,$A42,Tracker!$H$2:$H$321,"Won")+COUNTIFS(Tracker!$F$2:$F$321,$A42,Tracker!$H$2:$H$321,"Lost") | E42: =COUNTIFS(Tracker!$F$2:$F$321,$A42,Tracker!$H$2:$H$321,"Call booked")+COUNTIFS(Tracker!$F$2:$F$321,$A42,Tracker!$H$2:$H$321,"Call held")+COUNTIFS(Tracker!$F$2:$F$321,$A42,Tracker!$H$2:$H$321,"Proposal sent")+COUNTIFS(Tracker!$F$2:$F$321,$A42,Tracker!$H$2:$H$321,"Won")+COUNTIFS(Tracker!$F$2:$F$321,$A42,Tracker!$H$2:$H$321,"Lost") | F42: =IFERROR(D42/C42,0) | G42: =IFERROR(E42/C42,0)
A43: Company-news voice | B43: =COUNTIF(Tracker!$F$2:$F$321,$A43) | C43: =COUNTIFS(Tracker!$F$2:$F$321,$A43,Tracker!$H$2:$H$321,"Connection sent")+COUNTIFS(Tracker!$F$2:$F$321,$A43,Tracker!$H$2:$H$321,"Connected")+COUNTIFS(Tracker!$F$2:$F$321,$A43,Tracker!$H$2:$H$321,"DM sent")+COUNTIFS(Tracker!$F$2:$F$321,$A43,Tracker!$H$2:$H$321,"Follow-up 1 sent")+COUNTIFS(Tracker!$F$2:$F$321,$A43,Tracker!$H$2:$H$321,"Follow-up 2 sent")+COUNTIFS(Tracker!$F$2:$F$321,$A43,Tracker!$H$2:$H$321,"Replied")+COUNTIFS(Tracker!$F$2:$F$321,$A43,Tracker!$H$2:$H$321,"Teardown sent")+COUNTIFS(Tracker!$F$2:$F$321,$A43,Tracker!$H$2:$H$321,"Call booked")+COUNTIFS(Tracker!$F$2:$F$321,$A43,Tracker!$H$2:$H$321,"Call held")+COUNTIFS(Tracker!$F$2:$F$321,$A43,Tracker!$H$2:$H$321,"Proposal sent")+COUNTIFS(Tracker!$F$2:$F$321,$A43,Tracker!$H$2:$H$321,"Won")+COUNTIFS(Tracker!$F$2:$F$321,$A43,Tracker!$H$2:$H$321,"Lost")+COUNTIFS(Tracker!$F$2:$F$321,$A43,Tracker!$H$2:$H$321,"No response") | D43: =COUNTIFS(Tracker!$F$2:$F$321,$A43,Tracker!$H$2:$H$321,"Replied")+COUNTIFS(Tracker!$F$2:$F$321,$A43,Tracker!$H$2:$H$321,"Teardown sent")+COUNTIFS(Tracker!$F$2:$F$321,$A43,Tracker!$H$2:$H$321,"Call booked")+COUNTIFS(Tracker!$F$2:$F$321,$A43,Tracker!$H$2:$H$321,"Call held")+COUNTIFS(Tracker!$F$2:$F$321,$A43,Tracker!$H$2:$H$321,"Proposal sent")+COUNTIFS(Tracker!$F$2:$F$321,$A43,Tracker!$H$2:$H$321,"Won")+COUNTIFS(Tracker!$F$2:$F$321,$A43,Tracker!$H$2:$H$321,"Lost") | E43: =COUNTIFS(Tracker!$F$2:$F$321,$A43,Tracker!$H$2:$H$321,"Call booked")+COUNTIFS(Tracker!$F$2:$F$321,$A43,Tracker!$H$2:$H$321,"Call held")+COUNTIFS(Tracker!$F$2:$F$321,$A43,Tracker!$H$2:$H$321,"Proposal sent")+COUNTIFS(Tracker!$F$2:$F$321,$A43,Tracker!$H$2:$H$321,"Won")+COUNTIFS(Tracker!$F$2:$F$321,$A43,Tracker!$H$2:$H$321,"Lost") | F43: =IFERROR(D43/C43,0) | G43: =IFERROR(E43/C43,0)
A44: Company-page voice | B44: =COUNTIF(Tracker!$F$2:$F$321,$A44) | C44: =COUNTIFS(Tracker!$F$2:$F$321,$A44,Tracker!$H$2:$H$321,"Connection sent")+COUNTIFS(Tracker!$F$2:$F$321,$A44,Tracker!$H$2:$H$321,"Connected")+COUNTIFS(Tracker!$F$2:$F$321,$A44,Tracker!$H$2:$H$321,"DM sent")+COUNTIFS(Tracker!$F$2:$F$321,$A44,Tracker!$H$2:$H$321,"Follow-up 1 sent")+COUNTIFS(Tracker!$F$2:$F$321,$A44,Tracker!$H$2:$H$321,"Follow-up 2 sent")+COUNTIFS(Tracker!$F$2:$F$321,$A44,Tracker!$H$2:$H$321,"Replied")+COUNTIFS(Tracker!$F$2:$F$321,$A44,Tracker!$H$2:$H$321,"Teardown sent")+COUNTIFS(Tracker!$F$2:$F$321,$A44,Tracker!$H$2:$H$321,"Call booked")+COUNTIFS(Tracker!$F$2:$F$321,$A44,Tracker!$H$2:$H$321,"Call held")+COUNTIFS(Tracker!$F$2:$F$321,$A44,Tracker!$H$2:$H$321,"Proposal sent")+COUNTIFS(Tracker!$F$2:$F$321,$A44,Tracker!$H$2:$H$321,"Won")+COUNTIFS(Tracker!$F$2:$F$321,$A44,Tracker!$H$2:$H$321,"Lost")+COUNTIFS(Tracker!$F$2:$F$321,$A44,Tracker!$H$2:$H$321,"No response") | D44: =COUNTIFS(Tracker!$F$2:$F$321,$A44,Tracker!$H$2:$H$321,"Replied")+COUNTIFS(Tracker!$F$2:$F$321,$A44,Tracker!$H$2:$H$321,"Teardown sent")+COUNTIFS(Tracker!$F$2:$F$321,$A44,Tracker!$H$2:$H$321,"Call booked")+COUNTIFS(Tracker!$F$2:$F$321,$A44,Tracker!$H$2:$H$321,"Call held")+COUNTIFS(Tracker!$F$2:$F$321,$A44,Tracker!$H$2:$H$321,"Proposal sent")+COUNTIFS(Tracker!$F$2:$F$321,$A44,Tracker!$H$2:$H$321,"Won")+COUNTIFS(Tracker!$F$2:$F$321,$A44,Tracker!$H$2:$H$321,"Lost") | E44: =COUNTIFS(Tracker!$F$2:$F$321,$A44,Tracker!$H$2:$H$321,"Call booked")+COUNTIFS(Tracker!$F$2:$F$321,$A44,Tracker!$H$2:$H$321,"Call held")+COUNTIFS(Tracker!$F$2:$F$321,$A44,Tracker!$H$2:$H$321,"Proposal sent")+COUNTIFS(Tracker!$F$2:$F$321,$A44,Tracker!$H$2:$H$321,"Won")+COUNTIFS(Tracker!$F$2:$F$321,$A44,Tracker!$H$2:$H$321,"Lost") | F44: =IFERROR(D44/C44,0) | G44: =IFERROR(E44/C44,0)
A45: Emerging writer | B45: =COUNTIF(Tracker!$F$2:$F$321,$A45) | C45: =COUNTIFS(Tracker!$F$2:$F$321,$A45,Tracker!$H$2:$H$321,"Connection sent")+COUNTIFS(Tracker!$F$2:$F$321,$A45,Tracker!$H$2:$H$321,"Connected")+COUNTIFS(Tracker!$F$2:$F$321,$A45,Tracker!$H$2:$H$321,"DM sent")+COUNTIFS(Tracker!$F$2:$F$321,$A45,Tracker!$H$2:$H$321,"Follow-up 1 sent")+COUNTIFS(Tracker!$F$2:$F$321,$A45,Tracker!$H$2:$H$321,"Follow-up 2 sent")+COUNTIFS(Tracker!$F$2:$F$321,$A45,Tracker!$H$2:$H$321,"Replied")+COUNTIFS(Tracker!$F$2:$F$321,$A45,Tracker!$H$2:$H$321,"Teardown sent")+COUNTIFS(Tracker!$F$2:$F$321,$A45,Tracker!$H$2:$H$321,"Call booked")+COUNTIFS(Tracker!$F$2:$F$321,$A45,Tracker!$H$2:$H$321,"Call held")+COUNTIFS(Tracker!$F$2:$F$321,$A45,Tracker!$H$2:$H$321,"Proposal sent")+COUNTIFS(Tracker!$F$2:$F$321,$A45,Tracker!$H$2:$H$321,"Won")+COUNTIFS(Tracker!$F$2:$F$321,$A45,Tracker!$H$2:$H$321,"Lost")+COUNTIFS(Tracker!$F$2:$F$321,$A45,Tracker!$H$2:$H$321,"No response") | D45: =COUNTIFS(Tracker!$F$2:$F$321,$A45,Tracker!$H$2:$H$321,"Replied")+COUNTIFS(Tracker!$F$2:$F$321,$A45,Tracker!$H$2:$H$321,"Teardown sent")+COUNTIFS(Tracker!$F$2:$F$321,$A45,Tracker!$H$2:$H$321,"Call booked")+COUNTIFS(Tracker!$F$2:$F$321,$A45,Tracker!$H$2:$H$321,"Call held")+COUNTIFS(Tracker!$F$2:$F$321,$A45,Tracker!$H$2:$H$321,"Proposal sent")+COUNTIFS(Tracker!$F$2:$F$321,$A45,Tracker!$H$2:$H$321,"Won")+COUNTIFS(Tracker!$F$2:$F$321,$A45,Tracker!$H$2:$H$321,"Lost") | E45: =COUNTIFS(Tracker!$F$2:$F$321,$A45,Tracker!$H$2:$H$321,"Call booked")+COUNTIFS(Tracker!$F$2:$F$321,$A45,Tracker!$H$2:$H$321,"Call held")+COUNTIFS(Tracker!$F$2:$F$321,$A45,Tracker!$H$2:$H$321,"Proposal sent")+COUNTIFS(Tracker!$F$2:$F$321,$A45,Tracker!$H$2:$H$321,"Won")+COUNTIFS(Tracker!$F$2:$F$321,$A45,Tracker!$H$2:$H$321,"Lost") | F45: =IFERROR(D45/C45,0) | G45: =IFERROR(E45/C45,0)
A46: Milestone-only | B46: =COUNTIF(Tracker!$F$2:$F$321,$A46) | C46: =COUNTIFS(Tracker!$F$2:$F$321,$A46,Tracker!$H$2:$H$321,"Connection sent")+COUNTIFS(Tracker!$F$2:$F$321,$A46,Tracker!$H$2:$H$321,"Connected")+COUNTIFS(Tracker!$F$2:$F$321,$A46,Tracker!$H$2:$H$321,"DM sent")+COUNTIFS(Tracker!$F$2:$F$321,$A46,Tracker!$H$2:$H$321,"Follow-up 1 sent")+COUNTIFS(Tracker!$F$2:$F$321,$A46,Tracker!$H$2:$H$321,"Follow-up 2 sent")+COUNTIFS(Tracker!$F$2:$F$321,$A46,Tracker!$H$2:$H$321,"Replied")+COUNTIFS(Tracker!$F$2:$F$321,$A46,Tracker!$H$2:$H$321,"Teardown sent")+COUNTIFS(Tracker!$F$2:$F$321,$A46,Tracker!$H$2:$H$321,"Call booked")+COUNTIFS(Tracker!$F$2:$F$321,$A46,Tracker!$H$2:$H$321,"Call held")+COUNTIFS(Tracker!$F$2:$F$321,$A46,Tracker!$H$2:$H$321,"Proposal sent")+COUNTIFS(Tracker!$F$2:$F$321,$A46,Tracker!$H$2:$H$321,"Won")+COUNTIFS(Tracker!$F$2:$F$321,$A46,Tracker!$H$2:$H$321,"Lost")+COUNTIFS(Tracker!$F$2:$F$321,$A46,Tracker!$H$2:$H$321,"No response") | D46: =COUNTIFS(Tracker!$F$2:$F$321,$A46,Tracker!$H$2:$H$321,"Replied")+COUNTIFS(Tracker!$F$2:$F$321,$A46,Tracker!$H$2:$H$321,"Teardown sent")+COUNTIFS(Tracker!$F$2:$F$321,$A46,Tracker!$H$2:$H$321,"Call booked")+COUNTIFS(Tracker!$F$2:$F$321,$A46,Tracker!$H$2:$H$321,"Call held")+COUNTIFS(Tracker!$F$2:$F$321,$A46,Tracker!$H$2:$H$321,"Proposal sent")+COUNTIFS(Tracker!$F$2:$F$321,$A46,Tracker!$H$2:$H$321,"Won")+COUNTIFS(Tracker!$F$2:$F$321,$A46,Tracker!$H$2:$H$321,"Lost") | E46: =COUNTIFS(Tracker!$F$2:$F$321,$A46,Tracker!$H$2:$H$321,"Call booked")+COUNTIFS(Tracker!$F$2:$F$321,$A46,Tracker!$H$2:$H$321,"Call held")+COUNTIFS(Tracker!$F$2:$F$321,$A46,Tracker!$H$2:$H$321,"Proposal sent")+COUNTIFS(Tracker!$F$2:$F$321,$A46,Tracker!$H$2:$H$321,"Won")+COUNTIFS(Tracker!$F$2:$F$321,$A46,Tracker!$H$2:$H$321,"Lost") | F46: =IFERROR(D46/C46,0) | G46: =IFERROR(E46/C46,0)
A47: Near-silent | B47: =COUNTIF(Tracker!$F$2:$F$321,$A47) | C47: =COUNTIFS(Tracker!$F$2:$F$321,$A47,Tracker!$H$2:$H$321,"Connection sent")+COUNTIFS(Tracker!$F$2:$F$321,$A47,Tracker!$H$2:$H$321,"Connected")+COUNTIFS(Tracker!$F$2:$F$321,$A47,Tracker!$H$2:$H$321,"DM sent")+COUNTIFS(Tracker!$F$2:$F$321,$A47,Tracker!$H$2:$H$321,"Follow-up 1 sent")+COUNTIFS(Tracker!$F$2:$F$321,$A47,Tracker!$H$2:$H$321,"Follow-up 2 sent")+COUNTIFS(Tracker!$F$2:$F$321,$A47,Tracker!$H$2:$H$321,"Replied")+COUNTIFS(Tracker!$F$2:$F$321,$A47,Tracker!$H$2:$H$321,"Teardown sent")+COUNTIFS(Tracker!$F$2:$F$321,$A47,Tracker!$H$2:$H$321,"Call booked")+COUNTIFS(Tracker!$F$2:$F$321,$A47,Tracker!$H$2:$H$321,"Call held")+COUNTIFS(Tracker!$F$2:$F$321,$A47,Tracker!$H$2:$H$321,"Proposal sent")+COUNTIFS(Tracker!$F$2:$F$321,$A47,Tracker!$H$2:$H$321,"Won")+COUNTIFS(Tracker!$F$2:$F$321,$A47,Tracker!$H$2:$H$321,"Lost")+COUNTIFS(Tracker!$F$2:$F$321,$A47,Tracker!$H$2:$H$321,"No response") | D47: =COUNTIFS(Tracker!$F$2:$F$321,$A47,Tracker!$H$2:$H$321,"Replied")+COUNTIFS(Tracker!$F$2:$F$321,$A47,Tracker!$H$2:$H$321,"Teardown sent")+COUNTIFS(Tracker!$F$2:$F$321,$A47,Tracker!$H$2:$H$321,"Call booked")+COUNTIFS(Tracker!$F$2:$F$321,$A47,Tracker!$H$2:$H$321,"Call held")+COUNTIFS(Tracker!$F$2:$F$321,$A47,Tracker!$H$2:$H$321,"Proposal sent")+COUNTIFS(Tracker!$F$2:$F$321,$A47,Tracker!$H$2:$H$321,"Won")+COUNTIFS(Tracker!$F$2:$F$321,$A47,Tracker!$H$2:$H$321,"Lost") | E47: =COUNTIFS(Tracker!$F$2:$F$321,$A47,Tracker!$H$2:$H$321,"Call booked")+COUNTIFS(Tracker!$F$2:$F$321,$A47,Tracker!$H$2:$H$321,"Call held")+COUNTIFS(Tracker!$F$2:$F$321,$A47,Tracker!$H$2:$H$321,"Proposal sent")+COUNTIFS(Tracker!$F$2:$F$321,$A47,Tracker!$H$2:$H$321,"Won")+COUNTIFS(Tracker!$F$2:$F$321,$A47,Tracker!$H$2:$H$321,"Lost") | F47: =IFERROR(D47/C47,0) | G47: =IFERROR(E47/C47,0)
